Workbook

Sheet FUO
A1: CAJIGA — FACTORES DE UTILIDAD (FUO)
A2: El FUO multiplica el costo del componente para obtener el precio de venta. Edita solo las celdas azules.
A4: NIVEL | B4: NOMBRE | C4: FACTOR FUO | D4: DESCRIPCIÓN / CUÁNDO USARLO | E4: IVA APLICADO
A5: FUO 1.15 | B5: ECONÓMICO | C5: 1.15 | D5: Proyectos muy básicos: melamina sencilla, sin herrajes especiales, sin acabados. | E5: 1.16
A6: FUO 1.25 | B6: BÁSICO | C6: 1.25 | D6: Proyectos sencillos: melamina con chapa, herrajes estándar, diseño básico. | E6: 1.16
A7: FUO 1.32 | B7: BÁSICO+ | C7: 1.32 | D7: Proyectos sencillos con mejor acabado: MDF lacado, herrajes estándar, diseño semi-personalizado. | E7: 1.16
A8: FUO 1.40 | B8: ESTÁNDAR | C8: 1.4 | D8: Proyectos intermedios: MDF lacado, herrajes de calidad media, diseño personalizado. | E8: 1.16
A9: FUO 1.48 | B9: ESTÁNDAR+ | C9: 1.48 | D9: Proyectos intermedios-altos: MDF + madera maciza combinada, herrajes soft-close, iluminación básica. | E9: 1.16
A10: FUO 1.55 | B10: PREMIUM | C10: 1.55 | D10: Proyectos de alta gama: madera maciza, herrajes premium, iluminación LED, diseño exclusivo. | E10: 1.16
A11: FUO 1.65 | B11: PREMIUM+ | C11: 1.65 | D11: Proyectos de lujo: maderas finas (nogal/encino), herrajes de alta gama, iluminación completa. | E11: 1.16
A12: FUO 1.75 | B12: LUJO | C12: 1.75 | D12: Proyectos de lujo completo: maderas selectas, herrajes europeos, domótica básica, diseño a medida. | E12: 1.16
A13: FUO 1.88 | B13: LUJO+ | C13: 1.88 | D13: Proyectos exclusivos: maderas importadas, herrajes de diseñador, domótica, acabados artesanales. | E13: 1.16
A14: FUO 2.00 | B14: ULTRA PREMIUM | C14: 2 | D14: Proyectos ultra exclusivos: materiales importados, diseño de autor, instalación especial, garantía extendida. | E14: 1.16
A16: ℹ️ El factor FUO incluye: costo de fabricación + mano de obra + gastos indirectos + utilidad. El IVA se aplica sobre el precio de venta al momento de facturar.

Sheet INSUMOS
A1: FÁBRICA CAJIGA — CATÁLOGO MAESTRO DE INSUMOS
A2: 368 insumos • 12 líneas • Precios en MXN • Actualizar precios en azul • Clave original conservada para cruce
A3: TIPO DE CAMBIO USD/MXN | C3: 21.08 | D3: ← Actualizar mensualmente
A5: LÍNEA | B5: SUBLÍNEA | C5: CLAVE | D5: CLAVE ORIG. | E5: DESCRIPCIÓN | F5: UNIDAD | G5: PRECIO USD | H5: PRECIO MXN | I5: MERMA % | J5: COSTO EFECT. | K5: USO | L5: NOTAS
A6: 🎨 BARNIZ (19 items)
A7: BARNIZ | B7: ACEITE | C7: BAR-ACE-002 | D7: MYRV048 | E7: ACEITE IMPREGNANTE CHOCOLATE HI-0129.40 | F7: LT | G7: =IF(H7="","",ROUND(H7/$C$3,2)) -> 7.84 | H7: 165.2 | J7: =IF(H7="","",ROUND(H7*(1+IF(I7="",0,I7)),2)) -> 165.2 | K7: 1
A8: BARNIZ | B8: ACEITE | C8: BAR-ACE-001 | D8: MYRV047 | E8: ACEITE IMPREGNANTE NOGALCLASICO HI-0115.40 | F8: LT | G8: =IF(H8="","",ROUND(H8/$C$3,2)) -> 7.84 | H8: 165.2 | J8: =IF(H8="","",ROUND(H8*(1+IF(I8="",0,I8)),2)) -> 165.2 | K8: 1
A9: BARNIZ | B9: ACEITE | C9: BAR-ACE-003 | D9: MYRV049 | E9: PROTECTOLACK TRANSPARENTE 20UB MATE HI-0600.40 | F9: LT | G9: =IF(H9="","",ROUND(H9/$C$3,2)) -> 7.84 | H9: 165.2 | J9: =IF(H9="","",ROUND(H9*(1+IF(I9="",0,I9)),2)) -> 165.2 | K9: 1 | L9: Fb:0.4 | $66.08
A10: BARNIZ | B10: FONDO | C10: BAR-FON-002 | D10: BFON011 | E10: FONDO POLIACRILICO | F10: LT MEZCLA | G10: =IF(H10="","",ROUND(H10/$C$3,2)) -> 8.85 | H10: 186.56 | J10: =IF(H10="","",ROUND(H10*(1+IF(I10="",0,I10)),2)) -> 186.56 | K10: 1 | L10: Fb:0.6 | $111.94
A11: BARNIZ | B11: FONDO | C11: BAR-FON-001 | D11: BFON010 | E11: FONDO POLIURETANO | F11: LT MEZCLA | G11: =IF(H11="","",ROUND(H11/$C$3,2)) -> 4.47 | H11: 94.27 | J11: =IF(H11="","",ROUND(H11*(1+IF(I11="",0,I11)),2)) -> 94.27 | K11: 1 | L11: Fb:0.44 | $41.48
A12: BARNIZ | B12: HIDROLACA | C12: BAR-HID-001 | D12: BLAC066 | E12: HIDROLACA | F12: LT MEZCLA | G12: =IF(H12="","",ROUND(H12/$C$3,2)) -> 4.87 | H12: 102.7 | J12: =IF(H12="","",ROUND(H12*(1+IF(I12="",0,I12)),2)) -> 102.7 | K12: 1
A13: BARNIZ | B13: LACA | C13: BAR-LAC-005 | D13: BLAC069 | E13: AUTOLACK MEZCLA DE COLORES BROCHA | F13: LT MEZCLA | G13: =IF(H13="","",ROUND(H13/$C$3,2)) -> 4.83 | H13: 101.77 | J13: =IF(H13="","",ROUND(H13*(1+IF(I13="",0,I13)),2)) -> 101.77 | K13: 1 | L13: Fb:0.37 | $37.65
A14: BARNIZ | B14: LACA | C14: BAR-LAC-004 | D14: BLAC067 | E14: AUTOLACK MEZCLA DE COLORES PISTOLA | F14: LT MEZCLA | G14: =IF(H14="","",ROUND(H14/$C$3,2)) -> 4.83 | H14: 101.77 | J14: =IF(H14="","",ROUND(H14*(1+IF(I14="",0,I14)),2)) -> 101.77 | K14: 1 | L14: Fb:0.93 | $94.65
A15: BARNIZ | B15: LACA | C15: BAR-LAC-003 | D15: BLAC064 | E15: BICAPA | F15: LT MEZCLA | G15: =IF(H15="","",ROUND(H15/$C$3,2)) -> 8.13 | H15: 171.47 | J15: =IF(H15="","",ROUND(H15*(1+IF(I15="",0,I15)),2)) -> 171.47 | K15: 1 | L15: Fb:0.4 | $68.59
A16: BARNIZ | B16: LACA | C16: BAR-LAC-001 | D16: BLAC062 | E16: LACA ACRILICA | F16: LT MEZCLA | G16: =IF(H16="","",ROUND(H16/$C$3,2)) -> 4.58 | H16: 96.6 | J16: =IF(H16="","",ROUND(H16*(1+IF(I16="",0,I16)),2)) -> 96.6 | K16: 1 | L16: Fb:0.93 | $89.84
A17: BARNIZ | B17: LACA | C17: BAR-LAC-002 | D17: BLAC063 | E17: LACA MATE | F17: LT MEZCLA | G17: =IF(H17="","",ROUND(H17/$C$3,2)) -> 3.49 | H17: 73.49 | J17: =IF(H17="","",ROUND(H17*(1+IF(I17="",0,I17)),2)) -> 73.49 | K17: 1 | L17: Fb:0.93 | $68.35
A18: BARNIZ | B18: POLYLACK | C18: BAR-PLK-001 | D18: BLAC065 | E18: POLYLACK ( PAROTAS ) | F18: LT MEZCLA | G18: =IF(H18="","",ROUND(H18/$C$3,2)) -> 6.15 | H18: 129.71 | J18: =IF(H18="","",ROUND(H18*(1+IF(I18="",0,I18)),2)) -> 129.71 | K18: 1 | L18: Fb:0.36 | $46.70
A19: BARNIZ | B19: TINTA | C19: BAR-TIN-005 | D19: BTIN70 | E19: BONA NATURE | F19: LT MEZCLA | G19: =IF(H19="","",ROUND(H19/$C$3,2)) -> 47.74 | H19: 1006.28 | J19: =IF(H19="","",ROUND(H19*(1+IF(I19="",0,I19)),2)) -> 1006.28 | K19: 1
A20: BARNIZ | B20: TINTA | C20: BAR-TIN-001 | D20: BTIN033 | E20: TINTA TONO 1/ TZALAM COLOR (ALCOHOL) | F20: LT MEZCLA | G20: =IF(H20="","",ROUND(H20/$C$3,2)) -> 1.56 | H20: 32.94 | J20: =IF(H20="","",ROUND(H20*(1+IF(I20="",0,I20)),2)) -> 32.94 | K20: 1 | L20: Fb:0.37 | $12.19
A21: BARNIZ | B21: TINTA | C21: BAR-TIN-002 | D21: BTIN034 | E21: TINTA TONO NOGAL COLOR | F21: LT MEZCLA | G21: =IF(H21="","",ROUND(H21/$C$3,2)) -> 2.67 | H21: 56.34 | J21: =IF(H21="","",ROUND(H21*(1+IF(I21="",0,I21)),2)) -> 56.34 | K21: 1 | L21: Fb:0.37 | $20.85
A22: BARNIZ | B22: TINTA | C22: BAR-TIN-003 | D22: BTIN035 | E22: TINTA TONO 1/ TZALAM FONDO (ACEITE) | F22: LT MEZCLA | G22: =IF(H22="","",ROUND(H22/$C$3,2)) -> 1.7 | H22: 35.79 | J22: =IF(H22="","",ROUND(H22*(1+IF(I22="",0,I22)),2)) -> 35.79 | K22: 1 | L22: Fb:0.37 | $13.24
A23: BARNIZ | B23: TINTA | C23: BAR-TIN-004 | D23: BTIN036 | E23: TINTA TONO NOGAL FONDO | F23: LT MEZCLA | G23: =IF(H23="","",ROUND(H23/$C$3,2)) -> 1.7 | H23: 35.8 | J23: =IF(H23="","",ROUND(H23*(1+IF(I23="",0,I23)),2)) -> 35.8 | K23: 1 | L23: Fb:0.37 | $13.25
A24: BARNIZ | B24: VARIOS | C24: BAR-VAR-001 | D24: SOL001 | E24: THINNER AMERICANO | F24: LT | G24: =IF(H24="","",ROUND(H24/$C$3,2)) -> 2.41 | H24: 50.9 | J24: =IF(H24="","",ROUND(H24*(1+IF(I24="",0,I24)),2)) -> 50.9 | K24: 1
A25: BARNIZ | B25: VARIOS | C25: BAR-VAR-002 | D25: SOL002 | E25: THINNER ESTANDAR | F25: LT | G25: =IF(H25="","",ROUND(H25/$C$3,2)) -> 1.68 | H25: 35.4 | J25: =IF(H25="","",ROUND(H25*(1+IF(I25="",0,I25)),2)) -> 35.4 | K25: 1
A27: 🪵 MADERA (45 items)
A28: MADERA | B28: CHAPA | C28: MAD-CHP-001 | D28: ACHA048 | E28: CHAPA ENCINO ROJO | F28: M2 | G28: =IF(H28="","",ROUND(H28/$C$3,2)) -> 2.18 | H28: 46 | J28: =IF(H28="","",ROUND(H28*(1+IF(I28="",0,I28)),2)) -> 46 | K28: 1
A29: MADERA | B29: CHAPA | C29: MAD-CHP-005 | D29: ACHA052 | E29: CHAPA HUANACAXTLE | F29: M2 | G29: =IF(H29="","",ROUND(H29/$C$3,2)) -> 3.44 | H29: 72.41 | J29: =IF(H29="","",ROUND(H29*(1+IF(I29="",0,I29)),2)) -> 72.41 | K29: 1
A30: MADERA | B30: CHAPA | C30: MAD-CHP-002 | D30: ACHA049 | E30: CHAPA NOGAL NATURAL | F30: M2 | G30: =IF(H30="","",ROUND(H30/$C$3,2)) -> 4.36 | H30: 92 | J30: =IF(H30="","",ROUND(H30*(1+IF(I30="",0,I30)),2)) -> 92 | K30: 1
A31: MADERA | B31: CHAPA | C31: MAD-CHP-003 | D31: ACHA050 | E31: CHAPA OKUME T.A. X 2.50 | F31: M2 | G31: =IF(H31="","",ROUND(H31/$C$3,2)) -> 2 | H31: 42.2413 | J31: =IF(H31="","",ROUND(H31*(1+IF(I31="",0,I31)),2)) -> 42.24 | K31: 1
A32: MADERA | B32: CHAPA | C32: MAD-CHP-004 | D32: ACHA051 | E32: CHAPA TZALAM | F32: M2 | G32: =IF(H32="","",ROUND(H32/$C$3,2)) -> 3.6 | H32: 75.8621 | J32: =IF(H32="","",ROUND(H32*(1+IF(I32="",0,I32)),2)) -> 75.86 | K32: 1
A33: MADERA | B33: GUALDRA | C33: MAD-GUA-001 | D33: AMAG006 | E33: TABLA DE LA GUALDRA | F33: PIE | G33: =IF(H33="","",ROUND(H33/$C$3,2)) -> 0.95 | H33: 20 | J33: =IF(H33="","",ROUND(H33*(1+IF(I33="",0,I33)),2)) -> 20 | K33: 2
A34: MADERA | B34: MADERA | C34: MAD-MAC-004 | D34: AMAA004 | E34: MADERA POPLAR ESFUTADO (ALAMO )1" 4/4 1COMUN | F34: PIE | G34: =IF(H34="","",ROUND(H34/$C$3,2)) -> 1.1 | H34: 23.188 | J34: =IF(H34="","",ROUND(H34*(1+IF(I34="",0,I34)),2)) -> 23.19 | K34: 1
A35: MADERA | B35: MADERA | C35: MAD-MAC-003 | D35: AMAA001 | E35: MADERA POPLAR ESFUTADO (ALAMO )1" 4/4 2C | F35: PIE | G35: =IF(H35="","",ROUND(H35/$C$3,2)) -> 1.59 | H35: 33.5172 | J35: =IF(H35="","",ROUND(H35*(1+IF(I35="",0,I35)),2)) -> 33.52 | K35: 1
A36: MADERA | B36: MADERA | C36: MAD-MAC-005 | D36: AMAA002 | E36: MADERA DE ALAMO 1 1/2" 6/4 1COMUN | F36: PIE | G36: =IF(H36="","",ROUND(H36/$C$3,2)) -> 1.43 | H36: 30.1444 | J36: =IF(H36="","",ROUND(H36*(1+IF(I36="",0,I36)),2)) -> 30.14 | K36: 2
A37: MADERA | B37: MADERA | C37: MAD-MAC-001 | D37: AMAE001 | E37: MADERA DE ENCINO ROJO FAS 4/4" 1" | F37: PIE | G37: =IF(H37="","",ROUND(H37/$C$3,2)) -> 2.09 | H37: 44 | J37: =IF(H37="","",ROUND(H37*(1+IF(I37="",0,I37)),2)) -> 44 | K37: 1
A38: MADERA | B38: MADERA | C38: MAD-MAC-002 | D38: AMAE002 | E38: MADERA DE ENCINO ROJO FAS 6/4" 1 1/2" | F38: PIE | G38: =IF(H38="","",ROUND(H38/$C$3,2)) -> 4.22 | H38: 89 | J38: =IF(H38="","",ROUND(H38*(1+IF(I38="",0,I38)),2)) -> 89 | K38: 1
A39: MADERA | B39: MADERA | C39: MAD-MAC-012 | D39: AMAH001 | E39: MADERA HUACASTLE 1" | F39: PIE | G39: =IF(H39="","",ROUND(H39/$C$3,2)) -> 2.61 | H39: 55 | J39: =IF(H39="","",ROUND(H39*(1+IF(I39="",0,I39)),2)) -> 55 | K39: 2
... A72: MADERA | B72: TRIPLAY | C72: MAD-TRI-001 | D72: ATRT001 | E72: TRIPLAY TZALAM 6mm 244L | F72: PZA | G72: =IF(H72="","",ROUND(H72/$C$3,2)) -> 45 | H72: 948.6 | J72: =IF(H72="","",ROUND(H72*(1+IF(I72="",0,I72)),2)) -> 948.6 | K72: 1
A74: 🔩 HERRAJE (46 items)
A75: HERRAJE | B75: BISAGRA | C75: HER-BIS-001 | D75: MYRV584 | E75: BISAGRA ACERO INOX 3" X 3" | F75: PZA | G75: =IF(H75="","",ROUND(H75/$C$3,2)) -> 2.86 | H75: 60.39 | J75: =IF(H75="","",ROUND(H75*(1+IF(I75="",0,I75)),2)) -> 60.39 | K75: 1
A76: HERRAJE | B76: BISAGRA | C76: HER-BIS-002 | D76: MYRV585 | E76: BISAGRA ACERO INOX 4" X 4" | F76: PZA | G76: =IF(H76="","",ROUND(H76/$C$3,2)) -> 3.77 | H76: 79.53 | J76: =IF(H76="","",ROUND(H76*(1+IF(I76="",0,I76)),2)) -> 79.53 | K76: 1
A77: HERRAJE | B77: BISAGRA | C77: HER-BIS-007 | D77: MYR112 | E77: BISAGRA COBERTURA COMPLETA 30 mm | F77: PZA | G77: =IF(H77="","",ROUND(H77/$C$3,2)) -> 2.87 | H77: 60.57 | J77: =IF(H77="","",ROUND(H77*(1+IF(I77="",0,I77)),2)) -> 60.57 | K77: 1
A78: HERRAJE | B78: BISAGRA | C78: HER-BIS-008 | D78: MYR114 | E78: BISAGRA MEDIA COBERTURA 30 mm | F78: PZA | G78: =IF(H78="","",ROUND(H78/$C$3,2)) -> 3.03 | H78: 63.84 | J78: =IF(H78="","",ROUND(H78*(1+IF(I78="",0,I78)),2)) -> 63.84 | K78: 1
A79: HERRAJE | B79: BISAGRA | C79: HER-BIS-003 | D79: MYRV086 | E79: BISAGRA OCULTA CROMO 080-0063 | F79: PAR | G79: =IF(H79="","",ROUND(H79/$C$3,2)) -> 10.28 | H79: 216.61 | J79: =IF(H79="","",ROUND(H79*(1+IF(I79="",0,I79)),2)) -> 216.61 | K79: 2
A80: HERRAJE | B80: BISAGRA | C80: HER-BIS-006 | D80: MYRV586 | E80: BISAGRA OCULTA CROMO 080-0065 116 MM | F80: PZA | G80: =IF(H80="","",ROUND(H80/$C$3,2)) -> 21.37 | H80: 450.43 | J80: =IF(H80="","",ROUND(H80*(1+IF(I80="",0,I80)),2)) -> 450.43 | K80: 2
A81: HERRAJE | B81: BISAGRA | C81: HER-BIS-009 | D81: MYR116 | E81: BISAGRA SIN COBERTURA 30 mm | F81: PZA | G81: =IF(H81="","",ROUND(H81/$C$3,2)) -> 3.23 | H81: 68.02 | J81: =IF(H81="","",ROUND(H81*(1+IF(I81="",0,I81)),2)) -> 68.02 | K81: 1
A82: HERRAJE | B82: BISAGRA | C82: HER-BIS-004 | D82: MYRV089 | E82: SN BISAGRA OCULTA CROMO 43.7 MM 080-0061 | F82: PZA | G82: =IF(H82="","",ROUND(H82/$C$3,2)) -> 2.87 | H82: 60.53 | J82: =IF(H82="","",ROUND(H82*(1+IF(I82="",0,I82)),2)) -> 60.53 | K82: 2
A83: HERRAJE | B83: BISAGRA | C83: HER-BIS-005 | D83: MYRV090 | E83: SN BISAGRA OCULTA CROMO 60.4 MM | F83: PZA | G83: =IF(H83="","",ROUND(H83/$C$3,2)) -> 4.11 | H83: 86.57 | J83: =IF(H83="","",ROUND(H83*(1+IF(I83="",0,I83)),2)) -> 86.57 | K83: 2
A84: HERRAJE | B84: BRIDA | C84: HER-BRI-001 | D84: HHER008 | E84: BRIDA OVALADA CROMADA NÍQUEL | F84: PZA | G84: =IF(H84="","",ROUND(H84/$C$3,2)) -> 0.06 | H84: 1.37 | J84: =IF(H84="","",ROUND(H84*(1+IF(I84="",0,I84)),2)) -> 1.37 | K84: 1
A85: HERRAJE | B85: CERRADURA | C85: HER-CER-002 | D85: MYRV581 | E85: CERRADURA GANCHO ACERO INOX 1684CH | F85: PZA | G85: =IF(H85="","",ROUND(H85/$C$3,2)) -> 8.24 | H85: 173.79 | J85: =IF(H85="","",ROUND(H85*(1+IF(I85="",0,I85)),2)) -> 173.79 | K85: 2
A86: HERRAJE | B86: CERRADURA | C86: HER-CER-001 | D86: MYRV534 | E86: CILINDRO KL106 90 MM 45 X 45 LLAVE LLAVE SATIN | F86: PZA | G86: =IF(H86="","",ROUND(H86/$C$3,2)) -> 8.31 | H86: 175.23 | J86: =IF(H86="","",ROUND(H86*(1+IF(I86="",0,I86)),2)) -> 175.23 | K86: 2
... A120: HERRAJE | B120: TUBO | C120: HER-TUB-001 | D120: MYR094 | E120: TUBO OVAL 6 MTS | F120: PZA | G120: =IF(H120="","",ROUND(H120/$C$3,2)) -> 15.7 | H120: 331.04 | J120: =IF(H120="","",ROUND(H120*(1+IF(I120="",0,I120)),2)) -> 331.04 | K120: 1
A122: ⚡ ELECTRICO (15 items)
A123: ELECTRICO | B123: APAGADOR | C123: ELE-APG-001 | D123: MYRV354 | E123: APAGADOR SIMON SENCILLO | F123: PZA | G123: =IF(H123="","",ROUND(H123/$C$3,2)) -> 0.69 | H123: 14.5 | J123: =IF(H123="","",ROUND(H123*(1+IF(I123="",0,I123)),2)) -> 14.5 | K123: 1
A124: ELECTRICO | B124: CABLE | C124: ELE-CAB-001 | D124: MYR230 | E124: CABLE CONDUMEX THHW 12 VERDE, BLANCO Y NEGRO | F124: MTS | G124: =IF(H124="","",ROUND(H124/$C$3,2)) -> 0.28 | H124: 5.85 | J124: =IF(H124="","",ROUND(H124*(1+IF(I124="",0,I124)),2)) -> 5.85 | K124: 1
A125: ELECTRICO | B125: CON | C125: ELE-CON-003 | D125: MYRV598 | E125: CONTACTO LIVINGLIGHT DUPLEX | F125: PZA | G125: =IF(H125="","",ROUND(H125/$C$3,2)) -> 4.23 | H125: 89.25 | J125: =IF(H125="","",ROUND(H125*(1+IF(I125="",0,I125)),2)) -> 89.25 | K125: 2
A126: ELECTRICO | B126: CONECTOR | C126: ELE-CON-001 | D126: MYRV351 | E126: CONECTOR RAPIDO PARA TIRA LED 5050 | F126: PZA | G126: =IF(H126="","",ROUND(H126/$C$3,2)) -> 0.66 | H126: 14 | J126: =IF(H126="","",ROUND(H126*(1+IF(I126="",0,I126)),2)) -> 14 | K126: 1
A127: ELECTRICO | B127: CONECTOR | C127: ELE-CON-002 | D127: MYRV272 | E127: CONECTOR TIRA LEDS AC -506-ACCON | F127: PZA | G127: =IF(H127="","",ROUND(H127/$C$3,2)) -> 3.59 | H127: 75.65 | J127: =IF(H127="","",ROUND(H127*(1+IF(I127="",0,I127)),2)) -> 75.65 | K127: 1
A128: ELECTRICO | B128: FUENTE | C128: ELE-FUE-001 | D128: MYRV349 | E128: FUENTE 40W | F128: PZA | G128: =IF(H128="","",ROUND(H128/$C$3,2)) -> 35.1 | H128: 739.94 | J128: =IF(H128="","",ROUND(H128*(1+IF(I128="",0,I128)),2)) -> 739.94 | K128: 1
A129: ELECTRICO | B129: FUENTE | C129: ELE-FUE-002 | D129: MYRV597 | E129: FUENTE 60W | F129: PZA | G129: =IF(H129="","",ROUND(H129/$C$3,2)) -> 45.58 | H129: 960.76 | J129: =IF(H129="","",ROUND(H129*(1+IF(I129="",0,I129)),2)) -> 960.76 | K129: 1
A130: ELECTRICO | B130: MANGUERA | C130: ELE-MNG-001 | D130: MYRV271 | E130: MANGERA ACLDPB3014WW60R 506-ACLD | F130: MTS | G130: =IF(H130="","",ROUND(H130/$C$3,2)) -> 3.41 | H130: 71.82 | J130: =IF(H130="","",ROUND(H130*(1+IF(I130="",0,I130)),2)) -> 71.82 | K130: 1
A131: ELECTRICO | B131: TERMINADO | C131: ELE-TER-003 | D131: MYRV601 | E131: APAGADOR LIVINGLIGHT 4 V + | F131: PZA | G131: =IF(H131="","",ROUND(H131/$C$3,2)) -> 4.81 | H131: 101.45 | J131: =IF(H131="","",ROUND(H131*(1+IF(I131="",0,I131)),2)) -> 101.45 | K131: 2
A132: ELECTRICO | B132: TERMINADO | C132: ELE-TER-002 | D132: MYRV600 | E132: APAGADOR LIVINGLIGHT ESCALERA + | F132: PZA | G132: =IF(H132="","",ROUND(H132/$C$3,2)) -> 3.12 | H132: 65.81 | J132: =IF(H132="","",ROUND(H132*(1+IF(I132="",0,I132)),2)) -> 65.81 | K132: 2
A133: ELECTRICO | B133: TERMINADO | C133: ELE-TER-004 | D133: MYRV602 | E133: APAGADOR LIVINGLIGHT SENCILLO + | F133: PZA | G133: =IF(H133="","",ROUND(H133/$C$3,2)) -> 2.54 | H133: 53.48 | J133: =IF(H133="","",ROUND(H133*(1+IF(I133="",0,I133)),2)) -> 53.48 | K133: 2
A134: ELECTRICO | B134: TERMINADO | C134: ELE-TER-001 | D134: MYRV599 | E134: CONTACTO LIVINGLIGHT POLARIZADO 1-M+ | F134: PZA | G134: =IF(H134="","",ROUND(H134/$C$3,2)) -> 2.65 | H134: 55.84 | J134: =IF(H134="","",ROUND(H134*(1+IF(I134="",0,I134)),2)) -> 55.84 | K134: 2
... A137: ELECTRICO | B137: TIRA | C137: ELE-TIR-001 | D137: MYR658 | E137: TIRA LED HAFELE | F137: PZA | G137: =IF(H137="","",ROUND(H137/$C$3,2)) -> 47.82 | H137: 1008 | J137: =IF(H137="","",ROUND(H137*(1+IF(I137="",0,I137)),2)) -> 1008 | K137: 1
A139: 🪞 ESPEJO (12 items)
A140: ESPEJO | B140: CRISTAL | C140: ESP-CRI-005 | D140: MYRV590 | E140: CANTOS PULIDO 10 MM | F140: M LINEAL | G140: =IF(H140="","",ROUND(H140/$C$3,2)) -> 1.1 | H140: 23.2 | J140: =IF(H140="","",ROUND(H140*(1+IF(I140="",0,I140)),2)) -> 23.2 | K140: 2
A141: ESPEJO | B141: CRISTAL | C141: ESP-CRI-006 | D141: MYRV591 | E141: CANTOS PULIDO 12 MM | F141: M LINEAL | G141: =IF(H141="","",ROUND(H141/$C$3,2)) -> 1.66 | H141: 35 | J141: =IF(H141="","",ROUND(H141*(1+IF(I141="",0,I141)),2)) -> 35 | K141: 2
A142: ESPEJO | B142: CRISTAL | C142: ESP-CRI-007 | D142: MYRV592 | E142: CANTOS PULIDO 19 MM | F142: M LINEAL | G142: =IF(H142="","",ROUND(H142/$C$3,2)) -> 2.75 | H142: 58 | J142: =IF(H142="","",ROUND(H142*(1+IF(I142="",0,I142)),2)) -> 58 | K142: 2
A143: ESPEJO | B143: CRISTAL | C143: ESP-CRI-002 | D143: MYRV587 | E143: CRISTAL AL CORTE CLARO 10 MM | F143: M2 | G143: =IF(H143="","",ROUND(H143/$C$3,2)) -> 26.9 | H143: 567 | J143: =IF(H143="","",ROUND(H143*(1+IF(I143="",0,I143)),2)) -> 567 | K143: 2
A144: ESPEJO | B144: CRISTAL | C144: ESP-CRI-003 | D144: MYRV588 | E144: CRISTAL AL CORTE CLARO 12 MM | F144: M2 | G144: =IF(H144="","",ROUND(H144/$C$3,2)) -> 41.41 | H144: 873 | J144: =IF(H144="","",ROUND(H144*(1+IF(I144="",0,I144)),2)) -> 873 | K144: 2
A145: ESPEJO | B145: CRISTAL | C145: ESP-CRI-004 | D145: MYRV589 | E145: CRISTAL AL CORTE CLARO 19 MM | F145: M2 | G145: =IF(H145="","",ROUND(H145/$C$3,2)) -> 70.87 | H145: 1494 | J145: =IF(H145="","",ROUND(H145*(1+IF(I145="",0,I145)),2)) -> 1494 | K145: 2
A146: ESPEJO | B146: CRISTAL | C146: ESP-CRI-001 | D146: MYRV453 | E146: CRISTAL FLOTADO CLARO 6 MM 180 X 260 | F146: M2 | G146: =IF(H146="","",ROUND(H146/$C$3,2)) -> 9.89 | H146: 208.54 | J146: =IF(H146="","",ROUND(H146*(1+IF(I146="",0,I146)),2)) -> 208.54 | K146: 1
A147: ESPEJO | B147: CRISTAL | C147: ESP-CRI-011 | D147: MYRV596 | E147: CRISTAL FLOTADO DIAMANTE 6MM X 321X225 | F147: M2 | G147: =IF(H147="","",ROUND(H147/$C$3,2)) -> 13.1 | H147: 276.23 | J147: =IF(H147="","",ROUND(H147*(1+IF(I147="",0,I147)),2)) -> 276.23 | K147: 2
A148: ESPEJO | B148: CRISTAL | C148: ESP-CRI-008 | D148: MYRV593 | E148: CRISTAL TEMPLADO 10 MM | F148: M2 | G148: =IF(H148="","",ROUND(H148/$C$3,2)) -> 30.55 | H148: 644 | J148: =IF(H148="","",ROUND(H148*(1+IF(I148="",0,I148)),2)) -> 644 | K148: 2
A149: ESPEJO | B149: CRISTAL | C149: ESP-CRI-009 | D149: MYRV594 | E149: CRISTAL TEMPLADO 12 MM | F149: M2 | G149: =IF(H149="","",ROUND(H149/$C$3,2)) -> 49.29 | H149: 1039 | J149: =IF(H149="","",ROUND(H149*(1+IF(I149="",0,I149)),2)) -> 1039 | K149: 2
A150: ESPEJO | B150: CRISTAL | C150: ESP-CRI-010 | D150: MYRV595 | E150: CRISTAL TEMPLADO 18 MM | F150: M2 | G150: =IF(H150="","",ROUND(H150/$C$3,2)) -> 93.74 | H150: 1976 | J150: =IF(H150="","",ROUND(H150*(1+IF(I150="",0,I150)),2)) -> 1976 | K150: 2
A151: ESPEJO | B151: ESPEJO | C151: ESP-ESP-001 | D151: MYRV452 | E151: ESPEJO FLOTADO CLARO 6 MM 180 X 260 | F151: M2 | G151: =IF(H151="","",ROUND(H151/$C$3,2)) -> 21.37 | H151: 450.42 | J151: =IF(H151="","",ROUND(H151*(1+IF(I151="",0,I151)),2)) -> 450.42 | K151: 1
A153: 📐 FORMAICA (6 items)
A154: FORMAICA | B154: FORMAICA | C154: FOR-LAM-006 | D154: MYRV575 | E154: FORMAICA LP BLANCO BRILLANTE 1101.31 .6 MM | F154: PZA | G154: =IF(H154="","",ROUND(H154/$C$3,2)) -> 7.54 | H154: 159 | J154: =IF(H154="","",ROUND(H154*(1+IF(I154="",0,I154)),2)) -> 159 | K154: 2
A155: FORMAICA | B155: FORMAICA | C155: FOR-LAM-005 | D155: MYRV574 | E155: FORMAICA LP JAKARTA TEAK 778-37 .7 MM | F155: PZA | G155: =IF(H155="","",ROUND(H155/$C$3,2)) -> 25.14 | H155: 530 | J155: =IF(H155="","",ROUND(H155*(1+IF(I155="",0,I155)),2)) -> 530 | K155: 2
A156: FORMAICA | B156: FORMAICA | C156: FOR-LAM-001 | D156: MYR778 | E156: L PLASTICO GRIS R TX | F156: PZA | G156: =IF(H156="","",ROUND(H156/$C$3,2)) -> 10.22 | H156: 215.52 | J156: =IF(H156="","",ROUND(H156*(1+IF(I156="",0,I156)),2)) -> 215.52 | K156: 2
A157: FORMAICA | B157: FORMAICA | C157: FOR-LAM-002 | D157: MYRV571 | E157: L. PLASTICO ALUMINIO BRUSH 1.22 X 2.44 | F157: PZA | G157: =IF(H157="","",ROUND(H157/$C$3,2)) -> 39.26 | H157: 827.59 | J157: =IF(H157="","",ROUND(H157*(1+IF(I157="",0,I157)),2)) -> 827.59 | K157: 2
A158: FORMAICA | B158: FORMAICA | C158: FOR-LAM-003 | D158: MYRV572 | E158: L. PLASTICO NEGRO MATE 293 1.22 X 2.44 | F158: PZA | G158: =IF(H158="","",ROUND(H158/$C$3,2)) -> 7.32 | H158: 154.31 | J158: =IF(H158="","",ROUND(H158*(1+IF(I158="",0,I158)),2)) -> 154.31 | K158: 2
A159: FORMAICA | B159: FORMAICA | C159: FOR-LAM-004 | D159: MYRV573 | E159: L.PLASTICO NEGRO TOUCH 1.22 X 2.44 | F159: PZA | G159: =IF(H159="","",ROUND(H159/$C$3,2)) -> 22.06 | H159: 465 | J159: =IF(H159="","",ROUND(H159*(1+IF(I159="",0,I159)),2)) -> 465 | K159: 2
A161: 🧱 MATERIALES (1 items)
A162: MATERIALES | B162: DUROCK | C162: MAT-DUR-001 | D162: DUR001 | E162: PLACA DE DUROCK 1.22 X 2.44 | F162: PZA | G162: =IF(H162="","",ROUND(H162/$C$3,2)) -> 18.89 | H162: 398.27 | J162: =IF(H162="","",ROUND(H162*(1+IF(I162="",0,I162)),2)) -> 398.27 | K162: 1
A164: ⚙️ METAL (89 items)
A165: METAL | B165: ANGULO | C165: MET-ANG-012 | D165: MYRV501 | E165: ANGULO 1/4 X 4 | F165: PZA | G165: =IF(H165="","",ROUND(H165/$C$3,2)) -> 42.16 | H165: 888.72 | J165: =IF(H165="","",ROUND(H165*(1+IF(I165="",0,I165)),2)) -> 888.72 | K165: 2
A166: METAL | B166: ANGULO | C166: MET-ANG-003 | D166: MYRV345 | E166: ANGULO 1/8 X 1" | F166: PZA | G166: =IF(H166="","",ROUND(H166/$C$3,2)) -> 5.29 | H166: 111.54 | J166: =IF(H166="","",ROUND(H166*(1+IF(I166="",0,I166)),2)) -> 111.54 | K166: 2
A167: METAL | B167: ANGULO | C167: MET-ANG-005 | D167: MYR865 | E167: ANGULO 1/8 X 1 1/2 | F167: PZA | G167: =IF(H167="","",ROUND(H167/$C$3,2)) -> 15.27 | H167: 321.8 | J167: =IF(H167="","",ROUND(H167*(1+IF(I167="",0,I167)),2)) -> 321.8 | K167: 1
A168: METAL | B168: ANGULO | C168: MET-ANG-004 | D168: MYR629 | E168: ANGULO 1/8 X 1 1/4 | F168: PZA | G168: =IF(H168="","",ROUND(H168/$C$3,2)) -> 6.39 | H168: 134.66 | J168: =IF(H168="","",ROUND(H168*(1+IF(I168="",0,I168)),2)) -> 134.66 | K168: 1
A169: METAL | B169: ANGULO | C169: MET-ANG-001 | D169: MYRV559 | E169: ANGULO 1/8 X 1/2 | F169: PZA | G169: =IF(H169="","",ROUND(H169/$C$3,2)) -> 7.38 | H169: 155.55 | J169: =IF(H169="","",ROUND(H169*(1+IF(I169="",0,I169)),2)) -> 155.55 | K169: 2
A170: METAL | B170: ANGULO | C170: MET-ANG-006 | D170: MYRV179 | E170: ANGULO 1/8 X 2 | F170: PZA | G170: =IF(H170="","",ROUND(H170/$C$3,2)) -> 12.72 | H170: 268.04 | J170: =IF(H170="","",ROUND(H170*(1+IF(I170="",0,I170)),2)) -> 268.04 | K170: 1
A171: METAL | B171: ANGULO | C171: MET-ANG-002 | D171: MYRV566 | E171: ANGULO 1/8 X 3/4 | F171: PZA | G171: =IF(H171="","",ROUND(H171/$C$3,2)) -> 3.75 | H171: 79 | J171: =IF(H171="","",ROUND(H171*(1+IF(I171="",0,I171)),2)) -> 79 | K171: 2
A172: METAL | B172: ANGULO | C172: MET-ANG-008 | D172: MYR578 | E172: ANGULO 3/16 X 1 1/2 | F172: PZA | G172: =IF(H172="","",ROUND(H172/$C$3,2)) -> 22.28 | H172: 469.56 | J172: =IF(H172="","",ROUND(H172*(1+IF(I172="",0,I172)),2)) -> 469.56 | K172: 2
A173: METAL | B173: ANGULO | C173: MET-ANG-007 | D173: MYR336 | E173: ANGULO 3/16 X 1 1/4 | F173: PZA | G173: =IF(H173="","",ROUND(H173/$C$3,2)) -> 15.46 | H173: 326 | J173: =IF(H173="","",ROUND(H173*(1+IF(I173="",0,I173)),2)) -> 326 | K173: 2
A174: METAL | B174: ANGULO | C174: MET-ANG-009 | D174: MYR584 | E174: ANGULO 3/16 X 2 | F174: PZA | G174: =IF(H174="","",ROUND(H174/$C$3,2)) -> 30.28 | H174: 638.23 | J174: =IF(H174="","",ROUND(H174*(1+IF(I174="",0,I174)),2)) -> 638.23 | K174: 1
A175: METAL | B175: ANGULO | C175: MET-ANG-010 | D175: MYR553 | E175: ANGULO 3/16 X 2 1/2 | F175: PZA | G175: =IF(H175="","",ROUND(H175/$C$3,2)) -> 19.59 | H175: 412.94 | J175: =IF(H175="","",ROUND(H175*(1+IF(I175="",0,I175)),2)) -> 412.94 | K175: 2
...

Sheet COSTOS_M2
A1: CAJIGA — COSTO DE MATERIAL + CONSUMIBLES POR M²
A2: Incluye triplay + chapa + madera maciza + MDF + consumibles de barniz (fondo, laca, tinta). Datos extraídos de la tabla de componentes real.
A4: COMPONENTE | B4: TAMAÑO | C4: M² HASTA | D4: HUANACAXTLE $/m² | E4: ENCINO $/m² | F4: NOGAL $/m² | G4: CONSUMIBLES $/m² | H4: CLAVE
A5: PARAL 1 VISTA | B5: CHICO | C5: 0.5 | D5: 522 | E5: 472 | F5: 495 | G5: 174 | H5: PARAL 1 VISTA|CHICO
A6: PARAL 1 VISTA | B6: MEDIANO | C6: 1 | D6: 583 | E6: 532 | F6: 552 | G6: 176 | H6: PARAL 1 VISTA|MEDIANO
A7: PARAL 1 VISTA | B7: GRANDE | C7: 99 | D7: 559 | E7: 511 | F7: 527 | G7: 162 | H7: PARAL 1 VISTA|GRANDE
A8: PARAL 2 VISTAS | B8: CHICO | C8: 0.5 | D8: 871 | E8: 773 | F8: 807 | G8: 339 | H8: PARAL 2 VISTAS|CHICO
A9: PARAL 2 VISTAS | B9: MEDIANO | C9: 1 | D9: 978 | E9: 873 | F9: 905 | G9: 343 | H9: PARAL 2 VISTAS|MEDIANO
A10: PARAL 2 VISTAS | B10: GRANDE | C10: 99 | D10: 883 | E10: 791 | F10: 817 | G10: 316 | H10: PARAL 2 VISTAS|GRANDE
A11: PISO | B11: CHICO | C11: 0.5 | D11: 531 | E11: 485 | F11: 501 | G11: 174 | H11: PISO|CHICO
A12: PISO | B12: MEDIANO | C12: 1 | D12: 494 | E12: 448 | F12: 462 | G12: 176 | H12: PISO|MEDIANO
A13: PISO | B13: GRANDE | C13: 99 | D13: 482 | E13: 438 | F13: 450 | G13: 162 | H13: PISO|GRANDE
A14: PISO CON ZOCLO | B14: CHICO | C14: 0.5 | D14: 584 | E14: 534 | F14: 551 | G14: 191 | H14: PISO CON ZOCLO|CHICO
A15: PISO CON ZOCLO | B15: MEDIANO | C15: 1 | D15: 543 | E15: 493 | F15: 508 | G15: 194 | H15: PISO CON ZOCLO|MEDIANO
A16: PISO CON ZOCLO | B16: GRANDE | C16: 99 | D16: 530 | E16: 482 | F16: 495 | G16: 178 | H16: PISO CON ZOCLO|GRANDE
... A40: TUBO COLGAR | B40: GRANDE | C40: 99 | D40: 66 | E40: 66 | F40: 66 | G40: 0 | H40: TUBO COLGAR|GRANDE
A41: ZAPATERA EXTRAÍBLE | B41: CHICO | C41: 0.5 | D41: 367 | E41: 329 | F41: 408 | G41: 213 | H41: =A41&"|"&B41 -> ZAPATERA EXTRAÍBLE|CHICO
A42: ZAPATERA EXTRAÍBLE | B42: MEDIANO | C42: 1 | D42: 344 | E42: 310 | F42: 384 | G42: 198 | H42: =A42&"|"&B42 -> ZAPATERA EXTRAÍBLE|MEDIANO
A43: ZAPATERA EXTRAÍBLE | B43: GRANDE | C43: 99 | D43: 317 | E43: 285 | F43: 354 | G43: 181 | H43: =A43&"|"&B43 -> ZAPATERA EXTRAÍBLE|GRANDE
A44: PARAL DELGADO 2V | B44: CHICO | C44: 0.5 | D44: 575 | E44: 435 | F44: 535 | G44: 300 | H44: =A44&"|"&B44 -> PARAL DELGADO 2V|CHICO
A45: PARAL DELGADO 2V | B45: MEDIANO | C45: 1 | D45: 540 | E45: 400 | F45: 500 | G45: 285 | H45: =A45&"|"&B45 -> PARAL DELGADO 2V|MEDIANO
A46: PARAL DELGADO 2V | B46: GRANDE | C46: 99 | D46: 520 | E46: 385 | F46: 480 | G46: 265 | H46: =A46&"|"&B46 -> PARAL DELGADO 2V|GRANDE
A47: ENTREPAÑO DELGADO | B47: CHICO | C47: 0.5 | D47: 575 | E47: 435 | F47: 535 | G47: 300 | H47: =A47&"|"&B47 -> ENTREPAÑO DELGADO|CHICO
A48: ENTREPAÑO DELGADO | B48: MEDIANO | C48: 1 | D48: 540 | E48: 400 | F48: 500 | G48: 285 | H48: =A48&"|"&B48 -> ENTREPAÑO DELGADO|MEDIANO
A49: ENTREPAÑO DELGADO | B49: GRANDE | C49: 99 | D49: 520 | E49: 385 | F49: 480 | G49: 265 | H49: =A49&"|"&B49 -> ENTREPAÑO DELGADO|GRANDE
A50: ESPEJO | B50: CHICO | C50: 0.5 | D50: 520 | E50: 520 | F50: 520 | G50: 0 | H50: =A50&"|"&B50 -> ESPEJO|CHICO
A51: ESPEJO | B51: MEDIANO | C51: 1 | D51: 480 | E51: 480 | F51: 480 | G51: 0 | H51: =A51&"|"&B51 -> ESPEJO|MEDIANO
A52: ESPEJO | B52: GRANDE | C52: 99 | D52: 470 | E52: 470 | F52: 470 | G52: 0 | H52: =A52&"|"&B52 -> ESPEJO|GRANDE
... A67: FONDO MADERA | B67: GRANDE | C67: 99 | D67: 160 | E67: 120 | F67: 135 | G67: 100 | H67: =A67&"|"&B67 -> FONDO MADERA|GRANDE
A69: FACTOR ESPECIAL | B69: FACTOR | C69: APLICA CUANDO
A70: ANCHO ESPECIAL | B70: 1.3 | C70: Ancho > 70 cm
A71: LARGO/ALTO ESPECIAL | B71: 1.3 | C71: Largo/Alto > 244 cm

Sheet MANO_DE_OBRA
A1: y
A2: Ingresa las HORAS (o minutos para CNC) que tarda cada área por componente. El costo se calcula automáticamente.
A4: PRECIO / HORA (O MINUTO) POR ÁREA
A5: HABILIT. | B5: CNC (min) | C5: ARMADO GRAL | D5: CHAPA | E5: PULIDO | F5: ENTINTADO | G5: FONDO | H5: PUL. FONDO | I5: PREPARADO | J5: BARNIZ COL. | K5: INST. ARMAD | L5: INST. BARN
A6: 134.7 | B6: 4.45 | C6: 134.7 | D6: 135.75 | E6: 127.65 | F6: 136.89 | G6: 136.89 | H6: 127.65 | I6: 136.89 | J6: 136.89 | K6: 134.7 | L6: 136.89
A8: HORAS POR COMPONENTE Y TAMAÑO (ingresa horas; para CNC ingresa minutos)
A9: COMPONENTE | B9: TAMAÑO | C9: M² HASTA | D9: HABILIT. | E9: CNC (min) | F9: ARM.GRAL | G9: CHAPA | H9: PULIDO | I9: ENTINT. | J9: FONDO | K9: PUL.FON | L9: PREPAR. | M9: BARNIZ | N9: I.ARMAD | O9: I.BARN | P9: COSTO MO | Q9: CLAVE
A10: PARAL 1 VISTA | B10: CHICO | C10: 0.5 | D10: 0.2 | E10: 0 | F10: 0.3 | G10: 0.166 | H10: 0.104 | I10: 0.104 | J10: 0.104 | K10: 0.1048 | L10: 0.104 | M10: 0.4 | N10: 1.5 | O10: 0.25 | P10: =D10*$A$6+E10*$B$6+F10*$C$6+G10*$D$6+H10*$E$6+I10*$F$6+J10*$G$6+K10*$H$6+L10*$I$6+M10*$J$6+N10*$K$6+O10*$L$6 -> 450.276 | Q10: =A10&"|"&B10 -> PARAL 1 VISTA|CHICO
A11: PARAL 1 VISTA | B11: MEDIANO | C11: 1 | D11: 0.2 | E11: 0 | F11: 0.4 | G11: 0.166 | H11: 0.176 | I11: 0.176 | J11: 0.176 | K11: 0.1772 | L11: 0.176 | M11: 0.4 | N11: 1.5 | O11: 0.25 | P11: =D11*$A$6+E11*$B$6+F11*$C$6+G11*$D$6+H11*$E$6+I11*$F$6+J11*$G$6+K11*$H$6+L11*$I$6+M11*$J$6+N11*$K$6+O11*$L$6 -> 511.7469 | Q11: =A11&"|"&B11 -> PARAL 1 VISTA|MEDIANO
A12: PARAL 1 VISTA | B12: GRANDE | C12: 99 | D12: 0.2 | E12: 0 | F12: 0.467 | G12: 0.166 | H12: 0.288 | I12: 0.288 | J12: 0.288 | K12: 0.2255 | L12: 0.288 | M12: 0.4 | N12: 1.5 | O12: 0.25 | P12: =D12*$A$6+E12*$B$6+F12*$C$6+G12*$D$6+H12*$E$6+I12*$F$6+J12*$G$6+K12*$H$6+L12*$I$6+M12*$J$6+N12*$K$6+O12*$L$6 -> 587.22913 | Q12: =A12&"|"&B12 -> PARAL 1 VISTA|GRANDE
A13: PARAL 2 VISTAS | B13: CHICO | C13: 0.5 | D13: 0.2 | E13: 0 | F13: 0.5 | G13: 0.166 | H13: 0.201 | I13: 0.201 | J13: 0.201 | K13: 0.2014 | L13: 0.201 | M13: 0.5 | N13: 1 | O13: 0.25 | P13: =D13*$A$6+E13*$B$6+F13*$C$6+G13*$D$6+H13*$E$6+I13*$F$6+J13*$G$6+K13*$H$6+L13*$I$6+M13*$J$6+N13*$K$6+O13*$L$6 -> 488.10303 | Q13: =A13&"|"&B13 -> PARAL 2 VISTAS|CHICO
A14: PARAL 2 VISTAS | B14: MEDIANO | C14: 1 | D14: 0.2 | E14: 0 | F14: 0.625 | G14: 0.166 | H14: 0.356 | I14: 0.356 | J14: 0.356 | K14: 0.3558 | L14: 0.356 | M14: 0.5 | N14: 1 | O14: 0.25 | P14: =D14*$A$6+E14*$B$6+F14*$C$6+G14*$D$6+H14*$E$6+I14*$F$6+J14*$G$6+K14*$H$6+L14*$I$6+M14*$J$6+N14*$K$6+O14*$L$6 -> 608.08929 | Q14: =A14&"|"&B14 -> PARAL 2 VISTAS|MEDIANO
A15: PARAL 2 VISTAS | B15: GRANDE | C15: 99 | D15: 0.2 | E15: 0 | F15: 0.708 | G15: 0.166 | H15: 0.554 | I15: 0.554 | J15: 0.554 | K15: 0.554 | L15: 0.554 | M15: 0.5 | N15: 1 | O15: 0.25 | P15: =D15*$A$6+E15*$B$6+F15*$C$6+G15*$D$6+H15*$E$6+I15*$F$6+J15*$G$6+K15*$H$6+L15*$I$6+M15*$J$6+N15*$K$6+O15*$L$6 -> 751.15698 | Q15: =A15&"|"&B15 -> PARAL 2 VISTAS|GRANDE
A16: PISO | B16: CHICO | C16: 0.5 | D16: 0.2 | E16: 0 | F16: 0.5 | G16: 0.166 | H16: 0.069 | I16: 0.069 | J16: 0.069 | K16: 0.069 | L16: 0.069 | M16: 0.25 | N16: 1 | O16: 0.2 | P16: =D16*$A$6+E16*$B$6+F16*$C$6+G16*$D$6+H16*$E$6+I16*$F$6+J16*$G$6+K16*$H$6+L16*$I$6+M16*$J$6+N16*$K$6+O16*$L$6 -> 359.07693 | Q16: =A16&"|"&B16 -> PISO|CHICO
A17: PISO | B17: MEDIANO | C17: 1 | D17: 0.2 | E17: 0 | F17: 0.533 | G17: 0.171 | H17: 0.147 | I17: 0.147 | J17: 0.147 | K17: 0.1457 | L17: 0.147 | M17: 0.33 | N17: 1 | O17: 0.2 | P17: =D17*$A$6+E17*$B$6+F17*$C$6+G17*$D$6+H17*$E$6+I17*$F$6+J17*$G$6+K17*$H$6+L17*$I$6+M17*$J$6+N17*$K$6+O17*$L$6 -> 426.93169 | Q17: =A17&"|"&B17 -> PISO|MEDIANO
A18: PISO | B18: GRANDE | C18: 99 | D18: 0.3 | E18: 0 | F18: 0.7 | G18: 0.2 | H18: 0.27 | I18: 0.27 | J18: 0.27 | K18: 0.2698 | L18: 0.27 | M18: 0.4 | N18: 1 | O18: 0.2 | P18: =D18*$A$6+E18*$B$6+F18*$C$6+G18*$D$6+H18*$E$6+I18*$F$6+J18*$G$6+K18*$H$6+L18*$I$6+M18*$J$6+N18*$K$6+O18*$L$6 -> 558.47037 | Q18: =A18&"|"&B18 -> PISO|GRANDE
A19: PISO CON ZOCLO | B19: CHICO | C19: 0.5 | D19: 0.22 | E19: 0 | F19: 0.55 | G19: 0.183 | H19: 0.076 | I19: 0.076 | J19: 0.076 | K19: 0.076 | L19: 0.076 | M19: 0.28 | N19: 1.1 | O19: 0.22 | P19: =D19*$A$6+E19*$B$6+F19*$C$6+G19*$D$6+H19*$E$6+I19*$F$6+J19*$G$6+K19*$H$6+L19*$I$6+M19*$J$6+N19*$K$6+O19*$L$6 -> 395.78997 | Q19: =A19&"|"&B19 -> PISO CON ZOCLO|CHICO
A20: PISO CON ZOCLO | B20: MEDIANO | C20: 1 | D20: 0.22 | E20: 0 | F20: 0.586 | G20: 0.188 | H20: 0.162 | I20: 0.162 | J20: 0.162 | K20: 0.16 | L20: 0.162 | M20: 0.36 | N20: 1.1 | O20: 0.22 | P20: =D20*$A$6+E20*$B$6+F20*$C$6+G20*$D$6+H20*$E$6+I20*$F$6+J20*$G$6+K20*$H$6+L20*$I$6+M20*$J$6+N20*$K$6+O20*$L$6 -> 469.28724 | Q20: =A20&"|"&B20 -> PISO CON ZOCLO|MEDIANO
A21: PISO CON ZOCLO | B21: GRANDE | C21: 99 | D21: 0.33 | E21: 0 | F21: 0.77 | G21: 0.22 | H21: 0.297 | I21: 0.297 | J21: 0.297 | K21: 0.297 | L21: 0.297 | M21: 0.44 | N21: 1.1 | O21: 0.22 | P21: =D21*$A$6+E21*$B$6+F21*$C$6+G21*$D$6+H21*$E$6+I21*$F$6+J21*$G$6+K21*$H$6+L21*$I$6+M21*$J$6+N21*$K$6+O21*$L$6 -> 614.34549 | Q21: =A21&"|"&B21 -> PISO CON ZOCLO|GRANDE
... A72: FONDO MADERA | B72: GRANDE | C72: 99 | D72: 0.15 | E72: 0 | F72: 0.2 | G72: 0 | H72: 0.25 | I72: 0.25 | J72: 0.25 | K72: 0.2 | L72: 0.25 | M72: 0.3 | N72: 0.2 | O72: 0.15 | P72: =D72*$A$6+E72*$B$6+F72*$C$6+G72*$D$6+H72*$E$6+I72*$F$6+J72*$G$6+K72*$H$6+L72*$I$6+M72*$J$6+N72*$K$6+O72*$L$6 -> 295.7955 | Q72: =A72&"|"&B72 -> FONDO MADERA|GRANDE
A74: ⚡ CHICO = hasta 0.50 m² | MEDIANO = 0.51 a 1.00 m² | GRANDE = más de 1.00 m². Puedes ajustar los límites en la columna "M² HASTA" (C). Ingresa HORAS en todas las áreas excepto CNC que es en MINUTOS.

Sheet HERRAJES
A1: CAJIGA — HERRAJES POR COMPONENTE
A2: Costo de herrajes asignado automáticamente al cotizar. Precios vinculados a INSUMOS.
A4: COMPONENTE | B4: PROFUNDIDAD | C4: CLAVE INSUMO | D4: DESCRIPCIÓN HERRAJE | E4: UNIDAD | F4: PRECIO UNIT. | G4: CANTIDAD | H4: COSTO HERRAJE | I4: NOTAS | J4: CLAVE LOOKUP
A5: CAJÓN | B5: 35 | C5: HER-COR-005 | D5: CORREDERA EXTENSIÓN TOTAL 35 CMS | E5: JGO | F5: 46.94 | G5: 1 | H5: =IF(F5=0,0,F5*G5) -> 46.94 | I5: 1 jgo por cajón | J5: CAJÓN|35
A6: CAJÓN | B6: 40 | C6: HER-COR-006 | D6: CORREDERA EXTENSIÓN TOTAL 40 CMS | E6: JGO | F6: 58.99 | G6: 1 | H6: =IF(F6=0,0,F6*G6) -> 58.99 | I6: 1 jgo por cajón | J6: CAJÓN|40
A7: CAJÓN | B7: 45 | C7: HER-COR-007 | D7: CORREDERA EXTENSIÓN TOTAL 45 CMS | E7: JGO | F7: 60.33 | G7: 1 | H7: =IF(F7=0,0,F7*G7) -> 60.33 | I7: 1 jgo por cajón | J7: CAJÓN|45
A8: CAJÓN | B8: 50 | C8: HER-COR-008 | D8: CORREDERA EXTENSIÓN TOTAL 50 CMS | E8: JGO | F8: 73.73 | G8: 1 | H8: =IF(F8=0,0,F8*G8) -> 73.73 | I8: 1 jgo por cajón | J8: CAJÓN|50
A9: CAJÓN | B9: 55 | C9: HER-COR-009 | D9: CORREDERA EXTENSIÓN TOTAL 55 CMS | E9: JGO | F9: 50.52 | G9: 1 | H9: =IF(F9=0,0,F9*G9) -> 50.52 | I9: 1 jgo por cajón | J9: CAJÓN|55
A10: CAJÓN | B10: 60 | C10: HER-COR-010 | D10: CORREDERA EXTENSIÓN TOTAL 60 CMS | E10: JGO | F10: 54.97 | G10: 1 | H10: =IF(F10=0,0,F10*G10) -> 54.97 | I10: 1 jgo por cajón | J10: CAJÓN|60
A11: PUERTA ABATIBLE | B11: TODAS | C11: HER-BIS-007 | D11: BISAGRA COBERTURA COMPLETA 30 mm | E11: PZA | F11: 60.57 | G11: 4 | H11: =IF(F11=0,0,F11*G11) -> 242.28 | I11: 4 bisagras por puerta | J11: PUERTA ABATIBLE|TODAS
A12: PUERTA ABATIBLE | B12: TODAS | C12: HER-CON-001 | D12: CONTRAS DE BISAGRAS | E12: PZA | F12: 17.28 | G12: 4 | H12: =IF(F12=0,0,F12*G12) -> 69.12 | I12: 4 contras por puerta | J12: PUERTA ABATIBLE|TODAS
A13: PUERTA CORREDERA | B13: TODAS | D13: SISTEMA RIEL INCLUIDO EN PRECIO BASE | F13: 0 | G13: 0 | H13: =IF(F13=0,0,F13*G13) -> 0 | I13: Sin herraje adicional | J13: PUERTA CORREDERA|TODAS
A14: PUERTA ESPEJO | B14: TODAS | C14: HER-BIS-007 | D14: BISAGRA COBERTURA COMPLETA 30 mm | E14: PZA | F14: 60.57 | G14: 4 | H14: =IF(F14=0,0,F14*G14) -> 242.28 | I14: 4 bisagras por puerta | J14: PUERTA ESPEJO|TODAS
A15: PUERTA ESPEJO | B15: TODAS | C15: HER-CON-001 | D15: CONTRAS DE BISAGRAS | E15: PZA | F15: 17.28 | G15: 4 | H15: =IF(F15=0,0,F15*G15) -> 69.12 | I15: 4 contras | J15: PUERTA ESPEJO|TODAS
A16: PUERTA ESPEJO | B16: TODAS | C16: ESP-ESP-001 | D16: ESPEJO FLOTADO CLARO 6 MM | E16: M2 | F16: 450.42 | H16: =IF(F16=0,0,F16*G16) -> 0 | I16: Cantidad = m² de puerta | J16: PUERTA ESPEJO|TODAS
A17: ENTREPAÑO LED | B17: TODAS | C17: ELE-TIR-001 | D17: TIRA LED HAFELE | E17: PZA | F17: 1008 | H17: =IF(F17=0,0,F17*G17) -> 0 | I17: Cant = ancho/100 (metros) | J17: ENTREPAÑO LED|TODAS
A18: TUBO COLGAR | B18: TODAS | C18: HER-TUB-001 | D18: TUBO OVAL 6 MTS | E18: PZA | F18: 331.04 | H18: =IF(F18=0,0,F18*G18) -> 0 | I18: Cant = largo/6 (fracción de tubo) | J18: TUBO COLGAR|TODAS
A19: TUBO COLGAR | B19: TODAS | C19: HER-BRI-001 | D19: BRIDA OVALADA CROMADA NÍQUEL | E19: PZA | F19: 1.37 | G19: 2 | H19: =IF(F19=0,0,F19*G19) -> 2.74 | I19: 2 bridas por tramo | J19: TUBO COLGAR|TODAS
A20: PARAL 1 VISTA | B20: TODAS | D20: SIN HERRAJE | F20: 0 | G20: 0 | H20: =IF(F20=0,0,F20*G20) -> 0 | J20: PARAL 1 VISTA|TODAS
A21: PARAL 2 VISTAS | B21: TODAS | D21: SIN HERRAJE | F21: 0 | G21: 0 | H21: =IF(F21=0,0,F21*G21) -> 0 | J21: PARAL 2 VISTAS|TODAS
A22: PISO | B22: TODAS | D22: SIN HERRAJE | F22: 0 | G22: 0 | H22: =IF(F22=0,0,F22*G22) -> 0 | J22: PISO|TODAS
A23: PISO CON ZOCLO | B23: TODAS | D23: SIN HERRAJE | F23: 0 | G23: 0 | H23: =IF(F23=0,0,F23*G23) -> 0 | J23: PISO CON ZOCLO|TODAS
A24: CIELO | B24: TODAS | D24: SIN HERRAJE | F24: 0 | G24: 0 | H24: =IF(F24=0,0,F24*G24) -> 0 | J24: CIELO|TODAS
A25: ENTREPAÑO | B25: TODAS | D25: SIN HERRAJE | F25: 0 | G25: 0 | H25: =IF(F25=0,0,F25*G25) -> 0 | J25: ENTREPAÑO|TODAS
A26: ZAPATERA EXTRAÍBLE | B26: 55 | C26: HER-COR-009 | D26: CORREDERA EXTENSIÓN TOTAL 55 CMS | E26: JGO | F26: 50.52 | G26: 1 | H26: =IF(F26=0,0,F26*G26) -> 50.52 | I26: 1 jgo por zapatera (prof 60cm) | J26: =A26&"|"&B26 -> ZAPATERA EXTRAÍBLE|55
A27: ZAPATERA EXTRAÍBLE | B27: 60 | C27: HER-COR-010 | D27: CORREDERA EXTENSIÓN TOTAL 60 CMS | E27: JGO | F27: 54.97 | G27: 1 | H27: =IF(F27=0,0,F27*G27) -> 54.97 | I27: 1 jgo por zapatera (prof 68cm) | J27: =A27&"|"&B27 -> ZAPATERA EXTRAÍBLE|60
A29: PARAL DELGADO 2V | B29: TODAS | D29: SIN HERRAJE | F29: 0 | G29: 0 | H29: =IF(F29=0,0,F29*G29) -> 0 | J29: =A29&"|"&B29 -> PARAL DELGADO 2V|TODAS
A30: ENTREPAÑO DELGADO | B30: TODAS | D30: SIN HERRAJE | F30: 0 | G30: 0 | H30: =IF(F30=0,0,F30*G30) -> 0 | J30: =A30&"|"&B30 -> ENTREPAÑO DELGADO|TODAS
A31: ESPEJO | B31: TODAS | D31: SIN HERRAJE | F31: 0 | G31: 0 | H31: =IF(F31=0,0,F31*G31) -> 0 | J31: =A31&"|"&B31 -> ESPEJO|TODAS
A32: MOLDURA SENCILLA | B32: TODAS | D32: SIN HERRAJE | F32: 0 | G32: 0 | H32: =IF(F32=0,0,F32*G32) -> 0 | J32: =A32&"|"&B32 -> MOLDURA SENCILLA|TODAS
A33: MOLDURA MEDIA | B33: TODAS | D33: SIN HERRAJE | F33: 0 | G33: 0 | H33: =IF(F33=0,0,F33*G33) -> 0 | J33: =A33&"|"&B33 -> MOLDURA MEDIA|TODAS
A34: MOLDURA DIFÍCIL | B34: TODAS | D34: SIN HERRAJE | F34: 0 | G34: 0 | H34: =IF(F34=0,0,F34*G34) -> 0 | J34: =A34&"|"&B34 -> MOLDURA DIFÍCIL|TODAS
A35: MOLDURA GRUESA DIFÍCIL | B35: TODAS | D35: SIN HERRAJE | F35: 0 | G35: 0 | H35: =IF(F35=0,0,F35*G35) -> 0 | J35: =A35&"|"&B35 -> MOLDURA GRUESA DIFÍCIL|TODAS
A36: FONDO MADERA | B36: TODAS | D36: SIN HERRAJE | F36: 0 | G36: 0 | H36: =IF(F36=0,0,F36*G36) -> 0 | J36: =A36&"|"&B36 -> FONDO MADERA|TODAS

Sheet COTIZADOR
A1: CAJIGA — COTIZADOR DE CLOSETS (HOJA INTERNA)
A3: PROYECTO: | B3: Closets Monte Tauro 290 — Vestidor Niñas | H3: FECHA: | I3: =TODAY() -> 46081
A4: CLIENTE: | B4: Monte Tauro 290 | H4: COTIZACIÓN #: | I4: COT-2025-001
A5: DIRECCIÓN: | H5: NIVEL (FUO): | I5: FUO 1.25
A6: ELABORÓ: | B6: Tu nombre | H6: VIGENCIA: | I6: 30 días
A8: FACTOR FUO ACTIVO: | D8: =IFERROR(VLOOKUP(I5,FUO!A5:C14,3,FALSE()),"⚠️ FUO no encontrado") -> 1.25 | G8: IVA: | I8: =IFERROR(VLOOKUP(I5,FUO!A5:E14,5,FALSE()),1.16) -> 1.16
B12: ↓ Selecciona componente | C12: ↓ Ver nota: qué mide según componente | D12: ↓ Ver nota: qué mide según componente | E12: ↓ Solo Cajón y Zapatera
A13: LADO | B13: COMPONENTE | C13: ANCHO (cm) | D13: LARGO/ALTO (cm) | E13: PROF. CAJÓN | F13: MATERIAL | G13: CANT. | H13: M² | I13: COSTO MAT. | J13: COSTO MO | K13: COSTO HERR. | L13: COSTO BASE | M13: PRECIO c/FUO | N13: PRECIO REDON. | O13: DSCTO % | P13: SUBTOTAL | Q13: NOTAS
B14: VESTIDOR NIÑAS
A15: V1 | B15: PISO CON ZOCLO | C15: 55 | D15: 100 | E15: — | F15: NOGAL | G15: 1 | H15: =IFERROR(IF(B15="","",(C15/100)*(D15/100)),"") -> 0.55 | I15: =IFERROR(IF(B15="","",_xlfn.LET(_xlpm.tamano,IF(H15<=0.5,"CHICO",IF(H15<=1,"MEDIANO","GRANDE")),_xlpm.clave,B15&"|"&_xlpm.tamano,_xlpm.fila,MATCH(_xlpm.clave,COSTOS_M2!$H$5:$H$67,0),_xlpm.mat_m2,INDEX(IF(F15="HUANACAXTLE",COSTOS_M2!$D$5:$D$67,IF(F15="ENCINO",COSTOS_M2!$E$5:$E$67,COSTOS_M2!$F$5:$F$67)),_xlpm.fila),_xlpm.cons_m2,INDEX(COSTOS_M2!$G$5:$G$67,_xlpm.fila),_xlpm.prof_factor,IF(AND(E15<>"—",E15<>"",ISNUMBER(E15)),POWER(E15/40,1.8),1),_xlpm.total_m2,(_xlpm.mat_m2+_xlpm.cons_m2)*H15*_xlpm.prof_factor*IF(C15>70,COSTOS_M2!$B$70,1)*IF(D15>244,COSTOS_M2!$B$71,1),_xlpm.total_m2)),"") -> 386.1 | J15: =IFERROR(IF(B15="","",INDEX(MANO_DE_OBRA!$P$10:$P$72,MATCH(B15&"|"&IF(H15<=0.5,"CHICO",IF(H15<=1,"MEDIANO","GRANDE")),MANO_DE_OBRA!$Q$10:$Q$72,0))),"") -> 469.28724 | K15: =IFERROR(IF(B15="","",_xlfn.LET(_xlpm.clave_prof,B15&"|"&E15,_xlpm.clave_todas,B15&"|TODAS",_xlpm.herr_prof,SUMIFS(HERRAJES!$H$5:$H$36,HERRAJES!$J$5:$J$36,_xlpm.clave_prof),_xlpm.herr_todas,SUMIFS(HERRAJES!$H$5:$H$36,HERRAJES!$J$5:$J$36,_xlpm.clave_todas),IF(_xlpm.herr_prof>0,_xlpm.herr_prof,_xlpm.herr_todas))),"") -> 0 | L15: =IFERROR(IF(B15="","",IF(I15="",0,I15)+IF(J15="",0,J15)+IF(K15="",0,K15)),"") -> 855.38724 | M15: =IFERROR(IF(L15="","",L15*$D$8),"") -> 1069.2341 | N15: =IFERROR(IF(M15="","",CEILING(M15,50)),"") -> 1100 | O15: 0 | P15: =IFERROR(IF(G15="","",G15*N15*(1-O15)),"") -> 1100
A16: V1 | B16: PISO CON ZOCLO | C16: 55 | D16: 175 | E16: — | F16: NOGAL | G16: 1 | H16: =IFERROR(IF(B16="","",(C16/100)*(D16/100)),"") -> 0.9625 | I16: =IFERROR(IF(B16="","",_xlfn.LET(_xlpm.tamano,IF(H16<=0.5,"CHICO",IF(H16<=1,"MEDIANO","GRANDE")),_xlpm.clave,B16&"|"&_xlpm.tamano,_xlpm.fila,MATCH(_xlpm.clave,COSTOS_M2!$H$5:$H$67,0),_xlpm.mat_m2,INDEX(IF(F16="HUANACAXTLE",COSTOS_M2!$D$5:$D$67,IF(F16="ENCINO",COSTOS_M2!$E$5:$E$67,COSTOS_M2!$F$5:$F$67)),_xlpm.fila),_xlpm.cons_m2,INDEX(COSTOS_M2!$G$5:$G$67,_xlpm.fila),_xlpm.prof_factor,IF(AND(E16<>"—",E16<>"",ISNUMBER(E16)),POWER(E16/40,1.8),1),_xlpm.total_m2,(_xlpm.mat_m2+_xlpm.cons_m2)*H16*_xlpm.prof_factor*IF(C16>70,COSTOS_M2!$B$70,1)*IF(D16>244,COSTOS_M2!$B$71,1),_xlpm.total_m2)),"") -> 675.675 | J16: =IFERROR(IF(B16="","",INDEX(MANO_DE_OBRA!$P$10:$P$72,MATCH(B16&"|"&IF(H16<=0.5,"CHICO",IF(H16<=1,"MEDIANO","GRANDE")),MANO_DE_OBRA!$Q$10:$Q$72,0))),"") -> 469.28724 | K16: =IFERROR(IF(B16="","",_xlfn.LET(_xlpm.clave_prof,B16&"|"&E16,_xlpm.clave_todas,B16&"|TODAS",_xlpm.herr_prof,SUMIFS(HERRAJES!$H$5:$H$36,HERRAJES!$J$5:$J$36,_xlpm.clave_prof),_xlpm.herr_todas,SUMIFS(HERRAJES!$H$5:$H$36,HERRAJES!$J$5:$J$36,_xlpm.clave_todas),IF(_xlpm.herr_prof>0,_xlpm.herr_prof,_xlpm.herr_todas))),"") -> 0 | L16: =IFERROR(IF(B16="","",IF(I16="",0,I16)+IF(J16="",0,J16)+IF(K16="",0,K16)),"") -> 1144.9622 | M16: =IFERROR(IF(L16="","",L16*$D$8),"") -> 1431.2028 | N16: =IFERROR(IF(M16="","",CEILING(M16,50)),"") -> 1450 | O16: 0 | P16: =IFERROR(IF(G16="","",G16*N16*(1-O16)),"") -> 1450
A17: V1 | B17: CIELO | C17: 55 | D17: 100 | E17: — | F17: NOGAL | G17: 1 | H17: =IFERROR(IF(B17="","",(C17/100)*(D17/100)),"") -> 0.55 | I17: =IFERROR(IF(B17="","",_xlfn.LET(_xlpm.tamano,IF(H17<=0.5,"CHICO",IF(H17<=1,"MEDIANO","GRANDE")),_xlpm.clave,B17&"|"&_xlpm.tamano,_xlpm.fila,MATCH(_xlpm.clave,COSTOS_M2!$H$5:$H$67,0),_xlpm.mat_m2,INDEX(IF(F17="HUANACAXTLE",COSTOS_M2!$D$5:$D$67,IF(F17="ENCINO",COSTOS_M2!$E$5:$E$67,COSTOS_M2!$F$5:$F$67)),_xlpm.fila),_xlpm.cons_m2,INDEX(COSTOS_M2!$G$5:$G$67,_xlpm.fila),_xlpm.prof_factor,IF(AND(E17<>"—",E17<>"",ISNUMBER(E17)),POWER(E17/40,1.8),1),_xlpm.total_m2,(_xlpm.mat_m2+_xlpm.cons_m2)*H17*_xlpm.prof_factor*IF(C17>70,COSTOS_M2!$B$70,1)*IF(D17>244,COSTOS_M2!$B$71,1),_xlpm.total_m2)),"") -> 459.8 | J17: =IFERROR(IF(B17="","",INDEX(MANO_DE_OBRA!$P$10:$P$72,MATCH(B17&"|"&IF(H17<=0.5,"CHICO",IF(H17<=1,"MEDIANO","GRANDE")),MANO_DE_OBRA!$Q$10:$Q$72,0))),"") -> 520.0504 | K17: =IFERROR(IF(B17="","",_xlfn.LET(_xlpm.clave_prof,B17&"|"&E17,_xlpm.clave_todas,B17&"|TODAS",_xlpm.herr_prof,SUMIFS(HERRAJES!$H$5:$H$36,HERRAJES!$J$5:$J$36,_xlpm.clave_prof),_xlpm.herr_todas,SUMIFS(HERRAJES!$H$5:$H$36,HERRAJES!$J$5:$J$36,_xlpm.clave_todas),IF(_xlpm.herr_prof>0,_xlpm.herr_prof,_xlpm.herr_todas))),"") -> 0 | L17: =IFERROR(IF(B17="","",IF(I17="",0,I17)+IF(J17="",0,J17)+IF(K17="",0,K17)),"") -> 979.8504 | M17: =IFERROR(IF(L17="","",L17*$D$8),"") -> 1224.813 | N17: =IFERROR(IF(M17="","",CEILING(M17,50)),"") -> 1250 | O17: 0 | P17: =IFERROR(IF(G17="","",G17*N17*(1-O17)),"") -> 1250
A18: V1 | B18: CIELO | C18: 55 | D18: 175 | E18: — | F18: NOGAL | G18: 1 | H18: =IFERROR(IF(B18="","",(C18/100)*(D18/100)),"") -> 0.9625 | I18: =IFERROR(IF(B18="","",_xlfn.LET(_xlpm.tamano,IF(H18<=0.5,"CHICO",IF(H18<=1,"MEDIANO","GRANDE")),_xlpm.clave,B18&"|"&_xlpm.tamano,_xlpm.fila,MATCH(_xlpm.clave,COSTOS_M2!$H$5:$H$67,0),_xlpm.mat_m2,INDEX(IF(F18="HUANACAXTLE",COSTOS_M2!$D$5:$D$67,IF(F18="ENCINO",COSTOS_M2!$E$5:$E$67,COSTOS_M2!$F$5:$F$67)),_xlpm.fila),_xlpm.cons_m2,INDEX(COSTOS_M2!$G$5:$G$67,_xlpm.fila),_xlpm.prof_factor,IF(AND(E18<>"—",E18<>"",ISNUMBER(E18)),POWER(E18/40,1.8),1),_xlpm.total_m2,(_xlpm.mat_m2+_xlpm.cons_m2)*H18*_xlpm.prof_factor*IF(C18>70,COSTOS_M2!$B$70,1)*IF(D18>244,COSTOS_M2!$B$71,1),_xlpm.total_m2)),"") -> 804.65 | J18: =IFERROR(IF(B18="","",INDEX(MANO_DE_OBRA!$P$10:$P$72,MATCH(B18&"|"&IF(H18<=0.5,"CHICO",IF(H18<=1,"MEDIANO","GRANDE")),MANO_DE_OBRA!$Q$10:$Q$72,0))),"") -> 520.0504 | K18: =IFERROR(IF(B18="","",_xlfn.LET(_xlpm.clave_prof,B18&"|"&E18,_xlpm.clave_todas,B18&"|TODAS",_xlpm.herr_prof,SUMIFS(HERRAJES!$H$5:$H$36,HERRAJES!$J$5:$J$36,_xlpm.clave_prof),_xlpm.herr_todas,SUMIFS(HERRAJES!$H$5:$H$36,HERRAJES!$J$5:$J$36,_xlpm.clave_todas),IF(_xlpm.herr_prof>0,_xlpm.herr_prof,_xlpm.herr_todas))),"") -> 0 | L18: =IFERROR(IF(B18="","",IF(I18="",0,I18)+IF(J18="",0,J18)+IF(K18="",0,K18)),"") -> 1324.7004 | M18: =IFERROR(IF(L18="","",L18*$D$8),"") -> 1655.8755 | N18: =IFERROR(IF(M18="","",CEILING(M18,50)),"") -> 1700 | O18: 0 | P18: =IFERROR(IF(G18="","",G18*N18*(1-O18)),"") -> 1700
A19: V1 | B19: PARAL 1 VISTA | C19: 55 | D19: 295 | E19: — | F19: NOGAL | G19: 2 | H19: =IFERROR(IF(B19="","",(C19/100)*(D19/100)),"") -> 1.6225 | I19: =IFERROR(IF(B19="","",_xlfn.LET(_xlpm.tamano,IF(H19<=0.5,"CHICO",IF(H19<=1,"MEDIANO","GRANDE")),_xlpm.clave,B19&"|"&_xlpm.tamano,_xlpm.fila,MATCH(_xlpm.clave,COSTOS_M2!$H$5:$H$67,0),_xlpm.mat_m2,INDEX(IF(F19="HUANACAXTLE",COSTOS_M2!$D$5:$D$67,IF(F19="ENCINO",COSTOS_M2!$E$5:$E$67,COSTOS_M2!$F$5:$F$67)),_xlpm.fila),_xlpm.cons_m2,INDEX(COSTOS_M2!$G$5:$G$67,_xlpm.fila),_xlpm.prof_factor,IF(AND(E19<>"—",E19<>"",ISNUMBER(E19)),POWER(E19/40,1.8),1),_xlpm.total_m2,(_xlpm.mat_m2+_xlpm.cons_m2)*H19*_xlpm.prof_factor*IF(C19>70,COSTOS_M2!$B$70,1)*IF(D19>244,COSTOS_M2!$B$71,1),_xlpm.total_m2)),"") -> 1453.2733 | J19: =IFERROR(IF(B19="","",INDEX(MANO_DE_OBRA!$P$10:$P$72,MATCH(B19&"|"&IF(H19<=0.5,"CHICO",IF(H19<=1,"MEDIANO","GRANDE")),MANO_DE_OBRA!$Q$10:$Q$72,0))),"") -> 587.22913 | K19: =IFERROR(IF(B19="","",_xlfn.LET(_xlpm.clave_prof,B19&"|"&E19,_xlpm.clave_todas,B19&"|TODAS",_xlpm.herr_prof,SUMIFS(HERRAJES!$H$5:$H$36,HERRAJES!$J$5:$J$36,_xlpm.clave_prof),_xlpm.herr_todas,SUMIFS(HERRAJES!$H$5:$H$36,HERRAJES!$J$5:$J$36,_xlpm.clave_todas),IF(_xlpm.herr_prof>0,_xlpm.herr_prof,_xlpm.herr_todas))),"") -> 0 | L19: =IFERROR(IF(B19="","",IF(I19="",0,I19)+IF(J19="",0,J19)+IF(K19="",0,K19)),"") -> 2040.5024 | M19: =IFERROR(IF(L19="","",L19*$D$8),"") -> 2550.628 | N19: =IFERROR(IF(M19="","",CEILING(M19,50)),"") -> 2600 | O19: 0 | P19: =IFERROR(IF(G19="","",G19*N19*(1-O19)),"") -> 5200
A20: V1 | B20: PARAL DELGADO 2V | C20: 55 | D20: 295 | E20: — | F20: NOGAL | G20: 2 | H20: =IFERROR(IF(B20="","",(C20/100)*(D20/100)),"") -> 1.6225 | I20: =IFERROR(IF(B20="","",_xlfn.LET(_xlpm.tamano,IF(H20<=0.5,"CHICO",IF(H20<=1,"MEDIANO","GRANDE")),_xlpm.clave,B20&"|"&_xlpm.tamano,_xlpm.fila,MATCH(_xlpm.clave,COSTOS_M2!$H$5:$H$67,0),_xlpm.mat_m2,INDEX(IF(F20="HUANACAXTLE",COSTOS_M2!$D$5:$D$67,IF(F20="ENCINO",COSTOS_M2!$E$5:$E$67,COSTOS_M2!$F$5:$F$67)),_xlpm.fila),_xlpm.cons_m2,INDEX(COSTOS_M2!$G$5:$G$67,_xlpm.fila),_xlpm.prof_factor,IF(AND(E20<>"—",E20<>"",ISNUMBER(E20)),POWER(E20/40,1.8),1),_xlpm.total_m2,(_xlpm.mat_m2+_xlpm.cons_m2)*H20*_xlpm.prof_factor*IF(C20>70,COSTOS_M2!$B$70,1)*IF(D20>244,COSTOS_M2!$B$71,1),_xlpm.total_m2)),"") -> 1571.3913 | J20: =IFERROR(IF(B20="","",INDEX(MANO_DE_OBRA!$P$10:$P$72,MATCH(B20&"|"&IF(H20<=0.5,"CHICO",IF(H20<=1,"MEDIANO","GRANDE")),MANO_DE_OBRA!$Q$10:$Q$72,0))),"") -> 725.196 | K20: =IFERROR(IF(B20="","",_xlfn.LET(_xlpm.clave_prof,B20&"|"&E20,_xlpm.clave_todas,B20&"|TODAS",_xlpm.herr_prof,SUMIFS(HERRAJES!$H$5:$H$36,HERRAJES!$J$5:$J$36,_xlpm.clave_prof),_xlpm.herr_todas,SUMIFS(HERRAJES!$H$5:$H$36,HERRAJES!$J$5:$J$36,_xlpm.clave_todas),IF(_xlpm.herr_prof>0,_xlpm.herr_prof,_xlpm.herr_todas))),"") -> 0 | L20: =IFERROR(IF(B20="","",IF(I20="",0,I20)+IF(J20="",0,J20)+IF(K20="",0,K20)),"") -> 2296.5873 | M20: =IFERROR(IF(L20="","",L20*$D$8),"") -> 2870.7341 | N20: =IFERROR(IF(M20="","",CEILING(M20,50)),"") -> 2900 | O20: 0 | P20: =IFERROR(IF(G20="","",G20*N20*(1-O20)),"") -> 5800
A21: V1 | B21: ZAPATERA EXTRAÍBLE | C21: 100 | D21: 55 | E21: 55 | F21: NOGAL | G21: 4 | H21: =IFERROR(IF(B21="","",(C21/100)*(D21/100)),"") -> 0.55 | I21: =IFERROR(IF(B21="","",_xlfn.LET(_xlpm.tamano,IF(H21<=0.5,"CHICO",IF(H21<=1,"MEDIANO","GRANDE")),_xlpm.clave,B21&"|"&_xlpm.tamano,_xlpm.fila,MATCH(_xlpm.clave,COSTOS_M2!$H$5:$H$67,0),_xlpm.mat_m2,INDEX(IF(F21="HUANACAXTLE",COSTOS_M2!$D$5:$D$67,IF(F21="ENCINO",COSTOS_M2!$E$5:$E$67,COSTOS_M2!$F$5:$F$67)),_xlpm.fila),_xlpm.cons_m2,INDEX(COSTOS_M2!$G$5:$G$67,_xlpm.fila),_xlpm.prof_factor,IF(AND(E21<>"—",E21<>"",ISNUMBER(E21)),POWER(E21/40,1.8),1),_xlpm.total_m2,(_xlpm.mat_m2+_xlpm.cons_m2)*H21*_xlpm.prof_factor*IF(C21>70,COSTOS_M2!$B$70,1)*IF(D21>244,COSTOS_M2!$B$71,1),_xlpm.total_m2)),"") -> 738.19973 | J21: =IFERROR(IF(B21="","",INDEX(MANO_DE_OBRA!$P$10:$P$72,MATCH(B21&"|"&IF(H21<=0.5,"CHICO",IF(H21<=1,"MEDIANO","GRANDE")),MANO_DE_OBRA!$Q$10:$Q$72,0))),"") -> 410.25956 | K21: =IFERROR(IF(B21="","",_xlfn.LET(_xlpm.clave_prof,B21&"|"&E21,_xlpm.clave_todas,B21&"|TODAS",_xlpm.herr_prof,SUMIFS(HERRAJES!$H$5:$H$36,HERRAJES!$J$5:$J$36,_xlpm.clave_prof),_xlpm.herr_todas,SUMIFS(HERRAJES!$H$5:$H$36,HERRAJES!$J$5:$J$36,_xlpm.clave_todas),IF(_xlpm.herr_prof>0,_xlpm.herr_prof,_xlpm.herr_todas))),"") -> 50.52 | L21: =IFERROR(IF(B21="","",IF(I21="",0,I21)+IF(J21="",0,J21)+IF(K21="",0,K21)),"") -> 1198.9793 | M21: =IFERROR(IF(L21="","",L21*$D$8),"") -> 1498.7241 | N21: =IFERROR(IF(M21="","",CEILING(M21,50)),"") -> 1500 | O21: 0 | P21: =IFERROR(IF(G21="","",G21*N21*(1-O21)),"") -> 6000
A22: V1 | B22: ENTREPAÑO DELGADO | C22: 55 | D22: 100 | E22: — | F22: NOGAL | G22: 2 | H22: =IFERROR(IF(B22="","",(C22/100)*(D22/100)),"") -> 0.55 | I22: =IFERROR(IF(B22="","",_xlfn.LET(_xlpm.tamano,IF(H22<=0.5,"CHICO",IF(H22<=1,"MEDIANO","GRANDE")),_xlpm.clave,B22&"|"&_xlpm.tamano,_xlpm.fila,MATCH(_xlpm.clave,COSTOS_M2!$H$5:$H$67,0),_xlpm.mat_m2,INDEX(IF(F22="HUANACAXTLE",COSTOS_M2!$D$5:$D$67,IF(F22="ENCINO",COSTOS_M2!$E$5:$E$67,COSTOS_M2!$F$5:$F$67)),_xlpm.fila),_xlpm.cons_m2,INDEX(COSTOS_M2!$G$5:$G$67,_xlpm.fila),_xlpm.prof_factor,IF(AND(E22<>"—",E22<>"",ISNUMBER(E22)),POWER(E22/40,1.8),1),_xlpm.total_m2,(_xlpm.mat_m2+_xlpm.cons_m2)*H22*_xlpm.prof_factor*IF(C22>70,COSTOS_M2!$B$70,1)*IF(D22>244,COSTOS_M2!$B$71,1),_xlpm.total_m2)),"") -> 431.75 | J22: =IFERROR(IF(B22="","",INDEX(MANO_DE_OBRA!$P$10:$P$72,MATCH(B22&"|"&IF(H22<=0.5,"CHICO",IF(H22<=1,"MEDIANO","GRANDE")),MANO_DE_OBRA!$Q$10:$Q$72,0))),"") -> 400.5588 | K22: =IFERROR(IF(B22="","",_xlfn.LET(_xlpm.clave_prof,B22&"|"&E22,_xlpm.clave_todas,B22&"|TODAS",_xlpm.herr_prof,SUMIFS(HERRAJES!$H$5:$H$36,HERRAJES!$J$5:$J$36,_xlpm.clave_prof),_xlpm.herr_todas,SUMIFS(HERRAJES!$H$5:$H$36,HERRAJES!$J$5:$J$36,_xlpm.clave_todas),IF(_xlpm.herr_prof>0,_xlpm.herr_prof,_xlpm.herr_todas))),"") -> 0 | L22: =IFERROR(IF(B22="","",IF(I22="",0,I22)+IF(J22="",0,J22)+IF(K22="",0,K22)),"") -> 832.3088 | M22: =IFERROR(IF(L22="","",L22*$D$8),"") -> 1040.386 | N22: =IFERROR(IF(M22="","",CEILING(M22,50)),"") -> 1050 | O22: 0 | P22: =IFERROR(IF(G22="","",G22*N22*(1-O22)),"") -> 2100
A23: V1 | B23: ENTREPAÑO DELGADO | C23: 55 | D23: 71 | E23: — | F23: NOGAL | G23: 6 | H23: =IFERROR(IF(B23="","",(C23/100)*(D23/100)),"") -> 0.3905 | I23: =IFERROR(IF(B23="","",_xlfn.LET(_xlpm.tamano,IF(H23<=0.5,"CHICO",IF(H23<=1,"MEDIANO","GRANDE")),_xlpm.clave,B23&"|"&_xlpm.tamano,_xlpm.fila,MATCH(_xlpm.clave,COSTOS_M2!$H$5:$H$67,0),_xlpm.mat_m2,INDEX(IF(F23="HUANACAXTLE",COSTOS_M2!$D$5:$D$67,IF(F23="ENCINO",COSTOS_M2!$E$5:$E$67,COSTOS_M2!$F$5:$F$67)),_xlpm.fila),_xlpm.cons_m2,INDEX(COSTOS_M2!$G$5:$G$67,_xlpm.fila),_xlpm.prof_factor,IF(AND(E23<>"—",E23<>"",ISNUMBER(E23)),POWER(E23/40,1.8),1),_xlpm.total_m2,(_xlpm.mat_m2+_xlpm.cons_m2)*H23*_xlpm.prof_factor*IF(C23>70,COSTOS_M2!$B$70,1)*IF(D23>244,COSTOS_M2!$B$71,1),_xlpm.total_m2)),"") -> 326.0675 | J23: =IFERROR(IF(B23="","",INDEX(MANO_DE_OBRA!$P$10:$P$72,MATCH(B23&"|"&IF(H23<=0.5,"CHICO",IF(H23<=1,"MEDIANO","GRANDE")),MANO_DE_OBRA!$Q$10:$Q$72,0))),"") -> 265.8015 | K23: =IFERROR(IF(B23="","",_xlfn.LET(_xlpm.clave_prof,B23&"|"&E23,_xlpm.clave_todas,B23&"|TODAS",_xlpm.herr_prof,SUMIFS(HERRAJES!$H$5:$H$36,HERRAJES!$J$5:$J$36,_xlpm.clave_prof),_xlpm.herr_todas,SUMIFS(HERRAJES!$H$5:$H$36,HERRAJES!$J$5:$J$36,_xlpm.clave_todas),IF(_xlpm.herr_prof>0,_xlpm.herr_prof,_xlpm.herr_todas))),"") -> 0 | L23: =IFERROR(IF(B23="","",IF(I23="",0,I23)+IF(J23="",0,J23)+IF(K23="",0,K23)),"") -> 591.869 | M23: =IFERROR(IF(L23="","",L23*$D$8),"") -> 739.83625 | N23: =IFERROR(IF(M23="","",CEILING(M23,50)),"") -> 750 | O23: 0 | P23: =IFERROR(IF(G23="","",G23*N23*(1-O23)),"") -> 4500
A24: V1 | B24: CAJÓN | C24: 71 | D24: 22 | E24: 55 | F24: NOGAL | G24: 4 | H24: =IFERROR(IF(B24="","",(C24/100)*(D24/100)),"") -> 0.1562 | I24: =IFERROR(IF(B24="","",_xlfn.LET(_xlpm.tamano,IF(H24<=0.5,"CHICO",IF(H24<=1,"MEDIANO","GRANDE")),_xlpm.clave,B24&"|"&_xlpm.tamano,_xlpm.fila,MATCH(_xlpm.clave,COSTOS_M2!$H$5:$H$67,0),_xlpm.mat_m2,INDEX(IF(F24="HUANACAXTLE",COSTOS_M2!$D$5:$D$67,IF(F24="ENCINO",COSTOS_M2!$E$5:$E$67,COSTOS_M2!$F$5:$F$67)),_xlpm.fila),_xlpm.cons_m2,INDEX(COSTOS_M2!$G$5:$G$67,_xlpm.fila),_xlpm.prof_factor,IF(AND(E24<>"—",E24<>"",ISNUMBER(E24)),POWER(E24/40,1.8),1),_xlpm.total_m2,(_xlpm.mat_m2+_xlpm.cons_m2)*H24*_xlpm.prof_factor*IF(C24>70,COSTOS_M2!$B$70,1)*IF(D24>244,COSTOS_M2!$B$71,1),_xlpm.total_m2)),"") -> 479.09416 | J24: =IFERROR(IF(B24="","",INDEX(MANO_DE_OBRA!$P$10:$P$72,MATCH(B24&"|"&IF(H24<=0.5,"CHICO",IF(H24<=1,"MEDIANO","GRANDE")),MANO_DE_OBRA!$Q$10:$Q$72,0))),"") -> 434.36213 | K24: =IFERROR(IF(B24="","",_xlfn.LET(_xlpm.clave_prof,B24&"|"&E24,_xlpm.clave_todas,B24&"|TODAS",_xlpm.herr_prof,SUMIFS(HERRAJES!$H$5:$H$36,HERRAJES!$J$5:$J$36,_xlpm.clave_prof),_xlpm.herr_todas,SUMIFS(HERRAJES!$H$5:$H$36,HERRAJES!$J$5:$J$36,_xlpm.clave_todas),IF(_xlpm.herr_prof>0,_xlpm.herr_prof,_xlpm.herr_todas))),"") -> 50.52 | L24: =IFERROR(IF(B24="","",IF(I24="",0,I24)+IF(J24="",0,J24)+IF(K24="",0,K24)),"") -> 963.9763 | M24: =IFERROR(IF(L24="","",L24*$D$8),"") -> 1204.9704 | N24: =IFERROR(IF(M24="","",CEILING(M24,50)),"") -> 1250 | O24: 0 | P24: =IFERROR(IF(G24="","",G24*N24*(1-O24)),"") -> 5000
A25: V1 | B25: TUBO COLGAR | C25: ESPECIAL | D25: 100 | E25: — | F25: NOGAL | G25: 4 | H25: =IFERROR(IF(B25="","",(C25/100)*(D25/100)),"") | I25: =IFERROR(IF(B25="","",_xlfn.LET(_xlpm.tamano,IF(H25<=0.5,"CHICO",IF(H25<=1,"MEDIANO","GRANDE")),_xlpm.clave,B25&"|"&_xlpm.tamano,_xlpm.fila,MATCH(_xlpm.clave,COSTOS_M2!$H$5:$H$67,0),_xlpm.mat_m2,INDEX(IF(F25="HUANACAXTLE",COSTOS_M2!$D$5:$D$67,IF(F25="ENCINO",COSTOS_M2!$E$5:$E$67,COSTOS_M2!$F$5:$F$67)),_xlpm.fila),_xlpm.cons_m2,INDEX(COSTOS_M2!$G$5:$G$67,_xlpm.fila),_xlpm.prof_factor,IF(AND(E25<>"—",E25<>"",ISNUMBER(E25)),POWER(E25/40,1.8),1),_xlpm.total_m2,(_xlpm.mat_m2+_xlpm.cons_m2)*H25*_xlpm.prof_factor*IF(C25>70,COSTOS_M2!$B$70,1)*IF(D25>244,COSTOS_M2!$B$71,1),_xlpm.total_m2)),"") | J25: =IFERROR(IF(B25="","",INDEX(MANO_DE_OBRA!$P$10:$P$72,MATCH(B25&"|"&IF(H25<=0.5,"CHICO",IF(H25<=1,"MEDIANO","GRANDE")),MANO_DE_OBRA!$Q$10:$Q$72,0))),"") -> 25.593 | K25: =IFERROR(IF(B25="","",_xlfn.LET(_xlpm.clave_prof,B25&"|"&E25,_xlpm.clave_todas,B25&"|TODAS",_xlpm.herr_prof,SUMIFS(HERRAJES!$H$5:$H$36,HERRAJES!$J$5:$J$36,_xlpm.clave_prof),_xlpm.herr_todas,SUMIFS(HERRAJES!$H$5:$H$36,HERRAJES!$J$5:$J$36,_xlpm.clave_todas),IF(_xlpm.herr_prof>0,_xlpm.herr_prof,_xlpm.herr_todas))),"") -> 2.74 | L25: =IFERROR(IF(B25="","",IF(I25="",0,I25)+IF(J25="",0,J25)+IF(K25="",0,K25)),"") -> 28.333 | M25: =IFERROR(IF(L25="","",L25*$D$8),"") -> 35.41625 | N25: =IFERROR(IF(M25="","",CEILING(M25,50)),"") -> 50 | O25: 0 | P25: =IFERROR(IF(G25="","",G25*N25*(1-O25)),"") -> 200
A26: V1 | B26: FONDO MADERA | C26: 275 | D26: 305 | E26: — | F26: NOGAL | G26: 1 | H26: =IFERROR(IF(B26="","",(C26/100)*(D26/100)),"") -> 8.3875 | I26: =IFERROR(IF(B26="","",_xlfn.LET(_xlpm.tamano,IF(H26<=0.5,"CHICO",IF(H26<=1,"MEDIANO","GRANDE")),_xlpm.clave,B26&"|"&_xlpm.tamano,_xlpm.fila,MATCH(_xlpm.clave,COSTOS_M2!$H$5:$H$67,0),_xlpm.mat_m2,INDEX(IF(F26="HUANACAXTLE",COSTOS_M2!$D$5:$D$67,IF(F26="ENCINO",COSTOS_M2!$E$5:$E$67,COSTOS_M2!$F$5:$F$67)),_xlpm.fila),_xlpm.cons_m2,INDEX(COSTOS_M2!$G$5:$G$67,_xlpm.fila),_xlpm.prof_factor,IF(AND(E26<>"—",E26<>"",ISNUMBER(E26)),POWER(E26/40,1.8),1),_xlpm.total_m2,(_xlpm.mat_m2+_xlpm.cons_m2)*H26*_xlpm.prof_factor*IF(C26>70,COSTOS_M2!$B$70,1)*IF(D26>244,COSTOS_M2!$B$71,1),_xlpm.total_m2)),"") -> 3331.0956 | J26: =IFERROR(IF(B26="","",INDEX(MANO_DE_OBRA!$P$10:$P$72,MATCH(B26&"|"&IF(H26<=0.5,"CHICO",IF(H26<=1,"MEDIANO","GRANDE")),MANO_DE_OBRA!$Q$10:$Q$72,0))),"") -> 295.7955 | K26: =IFERROR(IF(B26="","",_xlfn.LET(_xlpm.clave_prof,B26&"|"&E26,_xlpm.clave_todas,B26&"|TODAS",_xlpm.herr_prof,SUMIFS(HERRAJES!$H$5:$H$36,HERRAJES!$J$5:$J$36,_xlpm.clave_prof),_xlpm.herr_todas,SUMIFS(HERRAJES!$H$5:$H$36,HERRAJES!$J$5:$J$36,_xlpm.clave_todas),IF(_xlpm.herr_prof>0,_xlpm.herr_prof,_xlpm.herr_todas))),"") -> 0 | L26: =IFERROR(IF(B26="","",IF(I26="",0,I26)+IF(J26="",0,J26)+IF(K26="",0,K26)),"") -> 3626.8911 | M26: =IFERROR(IF(L26="","",L26*$D$8),"") -> 4533.6139 | N26: =IFERROR(IF(M26="","",CEILING(M26,50)),"") -> 4550 | O26: 0 | P26: =IFERROR(IF(G26="","",G26*N26*(1-O26)),"") -> 4550
A27: V1 | B27: MOLDURA DIFÍCIL | C27: 5 | D27: 550 | E27: — | F27: NOGAL | G27: 1 | H27: =IFERROR(IF(B27="","",(C27/100)*(D27/100)),"") -> 0.275 | I27: =IFERROR(IF(B27="","",_xlfn.LET(_xlpm.tamano,IF(H27<=0.5,"CHICO",IF(H27<=1,"MEDIANO","GRANDE")),_xlpm.clave,B27&"|"&_xlpm.tamano,_xlpm.fila,MATCH(_xlpm.clave,COSTOS_M2!$H$5:$H$67,0),_xlpm.mat_m2,INDEX(IF(F27="HUANACAXTLE",COSTOS_M2!$D$5:$D$67,IF(F27="ENCINO",COSTOS_M2!$E$5:$E$67,COSTOS_M2!$F$5:$F$67)),_xlpm.fila),_xlpm.cons_m2,INDEX(COSTOS_M2!$G$5:$G$67,_xlpm.fila),_xlpm.prof_factor,IF(AND(E27<>"—",E27<>"",ISNUMBER(E27)),POWER(E27/40,1.8),1),_xlpm.total_m2,(_xlpm.mat_m2+_xlpm.cons_m2)*H27*_xlpm.prof_factor*IF(C27>70,COSTOS_M2!$B$70,1)*IF(D27>244,COSTOS_M2!$B$71,1),_xlpm.total_m2)),"") -> 1841.125 | J27: =IFERROR(IF(B27="","",INDEX(MANO_DE_OBRA!$P$10:$P$72,MATCH(B27&"|"&IF(H27<=0.5,"CHICO",IF(H27<=1,"MEDIANO","GRANDE")),MANO_DE_OBRA!$Q$10:$Q$72,0))),"") -> 477.459 | K27: =IFERROR(IF(B27="","",_xlfn.LET(_xlpm.clave_prof,B27&"|"&E27,_xlpm.clave_todas,B27&"|TODAS",_xlpm.herr_prof,SUMIFS(HERRAJES!$H$5:$H$36,HERRAJES!$J$5:$J$36,_xlpm.clave_prof),_xlpm.herr_todas,SUMIFS(HERRAJES!$H$5:$H$36,HERRAJES!$J$5:$J$36,_xlpm.clave_todas),IF(_xlpm.herr_prof>0,_xlpm.herr_prof,_xlpm.herr_todas))),"") -> 0 | L27: =IFERROR(IF(B27="","",IF(I27="",0,I27)+IF(J27="",0,J27)+IF(K27="",0,K27)),"") -> 2318.584 | M27: =IFERROR(IF(L27="","",L27*$D$8),"") -> 2898.23 | N27: =IFERROR(IF(M27="","",CEILING(M27,50)),"") -> 2900 | O27: 0 | P27: =IFERROR(IF(G27="","",G27*N27*(1-O27)),"") -> 2900
A28: V2 | B28: PISO CON ZOCLO | C28: 55 | D28: 195 | E28: — | F28: NOGAL | G28: 1 | H28: =IFERROR(IF(B28="","",(C28/100)*(D28/100)),"") -> 1.0725 | I28: =IFERROR(IF(B28="","",_xlfn.LET(_xlpm.tamano,IF(H28<=0.5,"CHICO",IF(H28<=1,"MEDIANO","GRANDE")),_xlpm.clave,B28&"|"&_xlpm.tamano,_xlpm.fila,MATCH(_xlpm.clave,COSTOS_M2!$H$5:$H$67,0),_xlpm.mat_m2,INDEX(IF(F28="HUANACAXTLE",COSTOS_M2!$D$5:$D$67,IF(F28="ENCINO",COSTOS_M2!$E$5:$E$67,COSTOS_M2!$F$5:$F$67)),_xlpm.fila),_xlpm.cons_m2,INDEX(COSTOS_M2!$G$5:$G$67,_xlpm.fila),_xlpm.prof_factor,IF(AND(E28<>"—",E28<>"",ISNUMBER(E28)),POWER(E28/40,1.8),1),_xlpm.total_m2,(_xlpm.mat_m2+_xlpm.cons_m2)*H28*_xlpm.prof_factor*IF(C28>70,COSTOS_M2!$B$70,1)*IF(D28>244,COSTOS_M2!$B$71,1),_xlpm.total_m2)),"") -> 721.7925 | J28: =IFERROR(IF(B28="","",INDEX(MANO_DE_OBRA!$P$10:$P$72,MATCH(B28&"|"&IF(H28<=0.5,"CHICO",IF(H28<=1,"MEDIANO","GRANDE")),MANO_DE_OBRA!$Q$10:$Q$72,0))),"") -> 614.34549 | K28: =IFERROR(IF(B28="","",_xlfn.LET(_xlpm.clave_prof,B28&"|"&E28,_xlpm.clave_todas,B28&"|TODAS",_xlpm.herr_prof,SUMIFS(HERRAJES!$H$5:$H$36,HERRAJES!$J$5:$J$36,_xlpm.clave_prof),_xlpm.herr_todas,SUMIFS(HERRAJES!$H$5:$H$36,HERRAJES!$J$5:$J$36,_xlpm.clave_todas),IF(_xlpm.herr_prof>0,_xlpm.herr_prof,_xlpm.herr_todas))),"") -> 0 | L28: =IFERROR(IF(B28="","",IF(I28="",0,I28)+IF(J28="",0,J28)+IF(K28="",0,K28)),"") -> 1336.138 | M28: =IFERROR(IF(L28="","",L28*$D$8),"") -> 1670.1725 | N28: =IFERROR(IF(M28="","",CEILING(M28,50)),"") -> 1700 | O28: 0 | P28: =IFERROR(IF(G28="","",G28*N28*(1-O28)),"") -> 1700
A29: V2 | B29: CIELO | C29: 55 | D29: 195 | E29: — | F29: NOGAL | G29: 1 | H29: =IFERROR(IF(B29="","",(C29/100)*(D29/100)),"") -> 1.0725 | I29: =IFERROR(IF(B29="","",_xlfn.LET(_xlpm.tamano,IF(H29<=0.5,"CHICO",IF(H29<=1,"MEDIANO","GRANDE")),_xlpm.clave,B29&"|"&_xlpm.tamano,_xlpm.fila,MATCH(_xlpm.clave,COSTOS_M2!$H$5:$H$67,0),_xlpm.mat_m2,INDEX(IF(F29="HUANACAXTLE",COSTOS_M2!$D$5:$D$67,IF(F29="ENCINO",COSTOS_M2!$E$5:$E$67,COSTOS_M2!$F$5:$F$67)),_xlpm.fila),_xlpm.cons_m2,INDEX(COSTOS_M2!$G$5:$G$67,_xlpm.fila),_xlpm.prof_factor,IF(AND(E29<>"—",E29<>"",ISNUMBER(E29)),POWER(E29/40,1.8),1),_xlpm.total_m2,(_xlpm.mat_m2+_xlpm.cons_m2)*H29*_xlpm.prof_factor*IF(C29>70,COSTOS_M2!$B$70,1)*IF(D29>244,COSTOS_M2!$B$71,1),_xlpm.total_m2)),"") -> 866.58 | J29: =IFERROR(IF(B29="","",INDEX(MANO_DE_OBRA!$P$10:$P$72,MATCH(B29&"|"&IF(H29<=0.5,"CHICO",IF(H29<=1,"MEDIANO","GRANDE")),MANO_DE_OBRA!$Q$10:$Q$72,0))),"") -> 762.95904 | K29: =IFERROR(IF(B29="","",_xlfn.LET(_xlpm.clave_prof,B29&"|"&E29,_xlpm.clave_todas,B29&"|TODAS",_xlpm.herr_prof,SUMIFS(HERRAJES!$H$5:$H$36,HERRAJES!$J$5:$J$36,_xlpm.clave_prof),_xlpm.herr_todas,SUMIFS(HERRAJES!$H$5:$H$36,HERRAJES!$J$5:$J$36,_xlpm.clave_todas),IF(_xlpm.herr_prof>0,_xlpm.herr_prof,_xlpm.herr_todas))),"") -> 0 | L29: =IFERROR(IF(B29="","",IF(I29="",0,I29)+IF(J29="",0,J29)+IF(K29="",0,K29)),"") -> 1629.539 | M29: =IFERROR(IF(L29="","",L29*$D$8),"") -> 2036.9238 | N29: =IFERROR(IF(M29="","",CEILING(M29,50)),"") -> 2050 | O29: 0 | P29: =IFERROR(IF(G29="","",G29*N29*(1-O29)),"") -> 2050
A30: V2 | B30: PARAL 1 VISTA | C30: 55 | D30: 295 | E30: — | F30: NOGAL | G30: 1 | H30: =IFERROR(IF(B30="","",(C30/100)*(D30/100)),"") -> 1.6225 | I30: =IFERROR(IF(B30="","",_xlfn.LET(_xlpm.tamano,IF(H30<=0.5,"CHICO",IF(H30<=1,"MEDIANO","GRANDE")),_xlpm.clave,B30&"|"&_xlpm.tamano,_xlpm.fila,MATCH(_xlpm.clave,COSTOS_M2!$H$5:$H$67,0),_xlpm.mat_m2,INDEX(IF(F30="HUANACAXTLE",COSTOS_M2!$D$5:$D$67,IF(F30="ENCINO",COSTOS_M2!$E$5:$E$67,COSTOS_M2!$F$5:$F$67)),_xlpm.fila),_xlpm.cons_m2,INDEX(COSTOS_M2!$G$5:$G$67,_xlpm.fila),_xlpm.prof_factor,IF(AND(E30<>"—",E30<>"",ISNUMBER(E30)),POWER(E30/40,1.8),1),_xlpm.total_m2,(_xlpm.mat_m2+_xlpm.cons_m2)*H30*_xlpm.prof_factor*IF(C30>70,COSTOS_M2!$B$70,1)*IF(D30>244,COSTOS_M2!$B$71,1),_xlpm.total_m2)),"") -> 1453.2733 | J30: =IFERROR(IF(B30="","",INDEX(MANO_DE_OBRA!$P$10:$P$72,MATCH(B30&"|"&IF(H30<=0.5,"CHICO",IF(H30<=1,"MEDIANO","GRANDE")),MANO_DE_OBRA!$Q$10:$Q$72,0))),"") -> 587.22913 | K30: =IFERROR(IF(B30="","",_xlfn.LET(_xlpm.clave_prof,B30&"|"&E30,_xlpm.clave_todas,B30&"|TODAS",_xlpm.herr_prof,SUMIFS(HERRAJES!$H$5:$H$36,HERRAJES!$J$5:$J$36,_xlpm.clave_prof),_xlpm.herr_todas,SUMIFS(HERRAJES!$H$5:$H$36,HERRAJES!$J$5:$J$36,_xlpm.clave_todas),IF(_xlpm.herr_prof>0,_xlpm.herr_prof,_xlpm.herr_todas))),"") -> 0 | L30: =IFERROR(IF(B30="","",IF(I30="",0,I30)+IF(J30="",0,J30)+IF(K30="",0,K30)),"") -> 2040.5024 | M30: =IFERROR(IF(L30="","",L30*$D$8),"") -> 2550.628 | N30: =IFERROR(IF(M30="","",CEILING(M30,50)),"") -> 2600 | O30: 0 | P30: =IFERROR(IF(G30="","",G30*N30*(1-O30)),"") -> 2600
A31: V2 | B31: PARAL 2 VISTAS | C31: 55 | D31: 295 | E31: — | F31: NOGAL | G31: 1 | H31: =IFERROR(IF(B31="","",(C31/100)*(D31/100)),"") -> 1.6225 | I31: =IFERROR(IF(B31="","",_xlfn.LET(_xlpm.tamano,IF(H31<=0.5,"CHICO",IF(H31<=1,"MEDIANO","GRANDE")),_xlpm.clave,B31&"|"&_xlpm.tamano,_xlpm.fila,MATCH(_xlpm.clave,COSTOS_M2!$H$5:$H$67,0),_xlpm.mat_m2,INDEX(IF(F31="HUANACAXTLE",COSTOS_M2!$D$5:$D$67,IF(F31="ENCINO",COSTOS_M2!$E$5:$E$67,COSTOS_M2!$F$5:$F$67)),_xlpm.fila),_xlpm.cons_m2,INDEX(COSTOS_M2!$G$5:$G$67,_xlpm.fila),_xlpm.prof_factor,IF(AND(E31<>"—",E31<>"",ISNUMBER(E31)),POWER(E31/40,1.8),1),_xlpm.total_m2,(_xlpm.mat_m2+_xlpm.cons_m2)*H31*_xlpm.prof_factor*IF(C31>70,COSTOS_M2!$B$70,1)*IF(D31>244,COSTOS_M2!$B$71,1),_xlpm.total_m2)),"") -> 2389.7803 | J31: =IFERROR(IF(B31="","",INDEX(MANO_DE_OBRA!$P$10:$P$72,MATCH(B31&"|"&IF(H31<=0.5,"CHICO",IF(H31<=1,"MEDIANO","GRANDE")),MANO_DE_OBRA!$Q$10:$Q$72,0))),"") -> 751.15698 | K31: =IFERROR(IF(B31="","",_xlfn.LET(_xlpm.clave_prof,B31&"|"&E31,_xlpm.clave_todas,B31&"|TODAS",_xlpm.herr_prof,SUMIFS(HERRAJES!$H$5:$H$36,HERRAJES!$J$5:$J$36,_xlpm.clave_prof),_xlpm.herr_todas,SUMIFS(HERRAJES!$H$5:$H$36,HERRAJES!$J$5:$J$36,_xlpm.clave_todas),IF(_xlpm.herr_prof>0,_xlpm.herr_prof,_xlpm.herr_todas))),"") -> 0 | L31: =IFERROR(IF(B31="","",IF(I31="",0,I31)+IF(J31="",0,J31)+IF(K31="",0,K31)),"") -> 3140.9372 | M31: =IFERROR(IF(L31="","",L31*$D$8),"") -> 3926.1715 | N31: =IFERROR(IF(M31="","",CEILING(M31,50)),"") -> 3950 | O31: 0 | P31: =IFERROR(IF(G31="","",G31*N31*(1-O31)),"") -> 3950
A32: V2 | B32: PARAL DELGADO 2V | C32: 55 | D32: 295 | E32: — | F32: NOGAL | G32: 1 | H32: =IFERROR(IF(B32="","",(C32/100)*(D32/100)),"") -> 1.6225 | I32: =IFERROR(IF(B32="","",_xlfn.LET(_xlpm.tamano,IF(H32<=0.5,"CHICO",IF(H32<=1,"MEDIANO","GRANDE")),_xlpm.clave,B32&"|"&_xlpm.tamano,_xlpm.fila,MATCH(_xlpm.clave,COSTOS_M2!$H$5:$H$67,0),_xlpm.mat_m2,INDEX(IF(F32="HUANACAXTLE",COSTOS_M2!$D$5:$D$67,IF(F32="ENCINO",COSTOS_M2!$E$5:$E$67,COSTOS_M2!$F$5:$F$67)),_xlpm.fila),_xlpm.cons_m2,INDEX(COSTOS_M2!$G$5:$G$67,_xlpm.fila),_xlpm.prof_factor,IF(AND(E32<>"—",E32<>"",ISNUMBER(E32)),POWER(E32/40,1.8),1),_xlpm.total_m2,(_xlpm.mat_m2+_xlpm.cons_m2)*H32*_xlpm.prof_factor*IF(C32>70,COSTOS_M2!$B$70,1)*IF(D32>244,COSTOS_M2!$B$71,1),_xlpm.total_m2)),"") -> 1571.3913 | J32: =IFERROR(IF(B32="","",INDEX(MANO_DE_OBRA!$P$10:$P$72,MATCH(B32&"|"&IF(H32<=0.5,"CHICO",IF(H32<=1,"MEDIANO","GRANDE")),MANO_DE_OBRA!$Q$10:$Q$72,0))),"") -> 725.196 | K32: =IFERROR(IF(B32="","",_xlfn.LET(_xlpm.clave_prof,B32&"|"&E32,_xlpm.clave_todas,B32&"|TODAS",_xlpm.herr_prof,SUMIFS(HERRAJES!$H$5:$H$36,HERRAJES!$J$5:$J$36,_xlpm.clave_prof),_xlpm.herr_todas,SUMIFS(HERRAJES!$H$5:$H$36,HERRAJES!$J$5:$J$36,_xlpm.clave_todas),IF(_xlpm.herr_prof>0,_xlpm.herr_prof,_xlpm.herr_todas))),"") -> 0 | L32: =IFERROR(IF(B32="","",IF(I32="",0,I32)+IF(J32="",0,J32)+IF(K32="",0,K32)),"") -> 2296.5873 | M32: =IFERROR(IF(L32="","",L32*$D$8),"") -> 2870.7341 | N32: =IFERROR(IF(M32="","",CEILING(M32,50)),"") -> 2900 | O32: 0 | P32: =IFERROR(IF(G32="","",G32*N32*(1-O32)),"") -> 2900
A33: V2 | B33: ZAPATERA EXTRAÍBLE | C33: 94 | D33: 55 | E33: 55 | F33: NOGAL | G33: 4 | H33: =IFERROR(IF(B33="","",(C33/100)*(D33/100)),"") -> 0.517 | I33: =IFERROR(IF(B33="","",_xlfn.LET(_xlpm.tamano,IF(H33<=0.5,"CHICO",IF(H33<=1,"MEDIANO","GRANDE")),_xlpm.clave,B33&"|"&_xlpm.tamano,_xlpm.fila,MATCH(_xlpm.clave,COSTOS_M2!$H$5:$H$67,0),_xlpm.mat_m2,INDEX(IF(F33="HUANACAXTLE",COSTOS_M2!$D$5:$D$67,IF(F33="ENCINO",COSTOS_M2!$E$5:$E$67,COSTOS_M2!$F$5:$F$67)),_xlpm.fila),_xlpm.cons_m2,INDEX(COSTOS_M2!$G$5:$G$67,_xlpm.fila),_xlpm.prof_factor,IF(AND(E33<>"—",E33<>"",ISNUMBER(E33)),POWER(E33/40,1.8),1),_xlpm.total_m2,(_xlpm.mat_m2+_xlpm.cons_m2)*H33*_xlpm.prof_factor*IF(C33>70,COSTOS_M2!$B$70,1)*IF(D33>244,COSTOS_M2!$B$71,1),_xlpm.total_m2)),"") -> 693.90775 | J33: =IFERROR(IF(B33="","",INDEX(MANO_DE_OBRA!$P$10:$P$72,MATCH(B33&"|"&IF(H33<=0.5,"CHICO",IF(H33<=1,"MEDIANO","GRANDE")),MANO_DE_OBRA!$Q$10:$Q$72,0))),"") -> 410.25956 | K33: =IFERROR(IF(B33="","",_xlfn.LET(_xlpm.clave_prof,B33&"|"&E33,_xlpm.clave_todas,B33&"|TODAS",_xlpm.herr_prof,SUMIFS(HERRAJES!$H$5:$H$36,HERRAJES!$J$5:$J$36,_xlpm.clave_prof),_xlpm.herr_todas,SUMIFS(HERRAJES!$H$5:$H$36,HERRAJES!$J$5:$J$36,_xlpm.clave_todas),IF(_xlpm.herr_prof>0,_xlpm.herr_prof,_xlpm.herr_todas))),"") -> 50.52 | L33: =IFERROR(IF(B33="","",IF(I33="",0,I33)+IF(J33="",0,J33)+IF(K33="",0,K33)),"") -> 1154.6873 | M33: =IFERROR(IF(L33="","",L33*$D$8),"") -> 1443.3591 | N33: =IFERROR(IF(M33="","",CEILING(M33,50)),"") -> 1450 | O33: 0 | P33: =IFERROR(IF(G33="","",G33*N33*(1-O33)),"") -> 5800
A34: V2 | B34: ENTREPAÑO DELGADO | C34: 55 | D34: 94 | E34: — | F34: NOGAL | G34: 2 | H34: =IFERROR(IF(B34="","",(C34/100)*(D34/100)),"") -> 0.517 | I34: =IFERROR(IF(B34="","",_xlfn.LET(_xlpm.tamano,IF(H34<=0.5,"CHICO",IF(H34<=1,"MEDIANO","GRANDE")),_xlpm.clave,B34&"|"&_xlpm.tamano,_xlpm.fila,MATCH(_xlpm.clave,COSTOS_M2!$H$5:$H$67,0),_xlpm.mat_m2,INDEX(IF(F34="HUANACAXTLE",COSTOS_M2!$D$5:$D$67,IF(F34="ENCINO",COSTOS_M2!$E$5:$E$67,COSTOS_M2!$F$5:$F$67)),_xlpm.fila),_xlpm.cons_m2,INDEX(COSTOS_M2!$G$5:$G$67,_xlpm.fila),_xlpm.prof_factor,IF(AND(E34<>"—",E34<>"",ISNUMBER(E34)),POWER(E34/40,1.8),1),_xlpm.total_m2,(_xlpm.mat_m2+_xlpm.cons_m2)*H34*_xlpm.prof_factor*IF(C34>70,COSTOS_M2!$B$70,1)*IF(D34>244,COSTOS_M2!$B$71,1),_xlpm.total_m2)),"") -> 405.845 | J34: =IFERROR(IF(B34="","",INDEX(MANO_DE_OBRA!$P$10:$P$72,MATCH(B34&"|"&IF(H34<=0.5,"CHICO",IF(H34<=1,"MEDIANO","GRANDE")),MANO_DE_OBRA!$Q$10:$Q$72,0))),"") -> 400.5588 | K34: =IFERROR(IF(B34="","",_xlfn.LET(_xlpm.clave_prof,B34&"|"&E34,_xlpm.clave_todas,B34&"|TODAS",_xlpm.herr_prof,SUMIFS(HERRAJES!$H$5:$H$36,HERRAJES!$J$5:$J$36,_xlpm.clave_prof),_xlpm.herr_todas,SUMIFS(HERRAJES!$H$5:$H$36,HERRAJES!$J$5:$J$36,_xlpm.clave_todas),IF(_xlpm.herr_prof>0,_xlpm.herr_prof,_xlpm.herr_todas))),"") -> 0 | L34: =IFERROR(IF(B34="","",IF(I34="",0,I34)+IF(J34="",0,J34)+IF(K34="",0,K34)),"") -> 806.4038 | M34: =IFERROR(IF(L34="","",L34*$D$8),"") -> 1008.0048 | N34: =IFERROR(IF(M34="","",CEILING(M34,50)),"") -> 1050 | O34: 0 | P34: =IFERROR(IF(G34="","",G34*N34*(1-O34)),"") -> 2100
A35: V2 | B35: TUBO COLGAR | C35: ESPECIAL | D35: 94 | E35: — | F35: NOGAL | G35: 4 | H35: =IFERROR(IF(B35="","",(C35/100)*(D35/100)),"") | I35: =IFERROR(IF(B35="","",_xlfn.LET(_xlpm.tamano,IF(H35<=0.5,"CHICO",IF(H35<=1,"MEDIANO","GRANDE")),_xlpm.clave,B35&"|"&_xlpm.tamano,_xlpm.fila,MATCH(_xlpm.clave,COSTOS_M2!$H$5:$H$67,0),_xlpm.mat_m2,INDEX(IF(F35="HUANACAXTLE",COSTOS_M2!$D$5:$D$67,IF(F35="ENCINO",COSTOS_M2!$E$5:$E$67,COSTOS_M2!$F$5:$F$67)),_xlpm.fila),_xlpm.cons_m2,INDEX(COSTOS_M2!$G$5:$G$67,_xlpm.fila),_xlpm.prof_factor,IF(AND(E35<>"—",E35<>"",ISNUMBER(E35)),POWER(E35/40,1.8),1),_xlpm.total_m2,(_xlpm.mat_m2+_xlpm.cons_m2)*H35*_xlpm.prof_factor*IF(C35>70,COSTOS_M2!$B$70,1)*IF(D35>244,COSTOS_M2!$B$71,1),_xlpm.total_m2)),"") | J35: =IFERROR(IF(B35="","",INDEX(MANO_DE_OBRA!$P$10:$P$72,MATCH(B35&"|"&IF(H35<=0.5,"CHICO",IF(H35<=1,"MEDIANO","GRANDE")),MANO_DE_OBRA!$Q$10:$Q$72,0))),"") -> 25.593 | K35: =IFERROR(IF(B35="","",_xlfn.LET(_xlpm.clave_prof,B35&"|"&E35,_xlpm.clave_todas,B35&"|TODAS",_xlpm.herr_prof,SUMIFS(HERRAJES!$H$5:$H$36,HERRAJES!$J$5:$J$36,_xlpm.clave_prof),_xlpm.herr_todas,SUMIFS(HERRAJES!$H$5:$H$36,HERRAJES!$J$5:$J$36,_xlpm.clave_todas),IF(_xlpm.herr_prof>0,_xlpm.herr_prof,_xlpm.herr_todas))),"") -> 2.74 | L35: =IFERROR(IF(B35="","",IF(I35="",0,I35)+IF(J35="",0,J35)+IF(K35="",0,K35)),"") -> 28.333 | M35: =IFERROR(IF(L35="","",L35*$D$8),"") -> 35.41625 | N35: =IFERROR(IF(M35="","",CEILING(M35,50)),"") -> 50 | O35: 0 | P35: =IFERROR(IF(G35="","",G35*N35*(1-O35)),"") -> 200
A36: V2 | B36: FONDO MADERA | C36: 195 | D36: 295 | E36: — | F36: NOGAL | G36: 1 | H36: =IFERROR(IF(B36="","",(C36/100)*(D36/100)),"") -> 5.7525 | I36: =IFERROR(IF(B36="","",_xlfn.LET(_xlpm.tamano,IF(H36<=0.5,"CHICO",IF(H36<=1,"MEDIANO","GRANDE")),_xlpm.clave,B36&"|"&_xlpm.tamano,_xlpm.fila,MATCH(_xlpm.clave,COSTOS_M2!$H$5:$H$67,0),_xlpm.mat_m2,INDEX(IF(F36="HUANACAXTLE",COSTOS_M2!$D$5:$D$67,IF(F36="ENCINO",COSTOS_M2!$E$5:$E$67,COSTOS_M2!$F$5:$F$67)),_xlpm.fila),_xlpm.cons_m2,INDEX(COSTOS_M2!$G$5:$G$67,_xlpm.fila),_xlpm.prof_factor,IF(AND(E36<>"—",E36<>"",ISNUMBER(E36)),POWER(E36/40,1.8),1),_xlpm.total_m2,(_xlpm.mat_m2+_xlpm.cons_m2)*H36*_xlpm.prof_factor*IF(C36>70,COSTOS_M2!$B$70,1)*IF(D36>244,COSTOS_M2!$B$71,1),_xlpm.total_m2)),"") -> 2284.6054 | J36: =IFERROR(IF(B36="","",INDEX(MANO_DE_OBRA!$P$10:$P$72,MATCH(B36&"|"&IF(H36<=0.5,"CHICO",IF(H36<=1,"MEDIANO","GRANDE")),MANO_DE_OBRA!$Q$10:$Q$72,0))),"") -> 295.7955 | K36: =IFERROR(IF(B36="","",_xlfn.LET(_xlpm.clave_prof,B36&"|"&E36,_xlpm.clave_todas,B36&"|TODAS",_xlpm.herr_prof,SUMIFS(HERRAJES!$H$5:$H$36,HERRAJES!$J$5:$J$36,_xlpm.clave_prof),_xlpm.herr_todas,SUMIFS(HERRAJES!$H$5:$H$36,HERRAJES!$J$5:$J$36,_xlpm.clave_todas),IF(_xlpm.herr_prof>0,_xlpm.herr_prof,_xlpm.herr_todas))),"") -> 0 | L36: =IFERROR(IF(B36="","",IF(I36="",0,I36)+IF(J36="",0,J36)+IF(K36="",0,K36)),"") -> 2580.4009 | M36: =IFERROR(IF(L36="","",L36*$D$8),"") -> 3225.5011 | N36: =IFERROR(IF(M36="","",CEILING(M36,50)),"") -> 3250 | O36: 0 | P36: =IFERROR(IF(G36="","",G36*N36*(1-O36)),"") -> 3250
A37: V2 | B37: MOLDURA DIFÍCIL | C37: 5 | D37: 400 | E37: — | F37: NOGAL | G37: 1 | H37: =IFERROR(IF(B37="","",(C37/100)*(D37/100)),"") -> 0.2 | I37: =IFERROR(IF(B37="","",_xlfn.LET(_xlpm.tamano,IF(H37<=0.5,"CHICO",IF(H37<=1,"MEDIANO","GRANDE")),_xlpm.clave,B37&"|"&_xlpm.tamano,_xlpm.fila,MATCH(_xlpm.clave,COSTOS_M2!$H$5:$H$67,0),_xlpm.mat_m2,INDEX(IF(F37="HUANACAXTLE",COSTOS_M2!$D$5:$D$67,IF(F37="ENCINO",COSTOS_M2!$E$5:$E$67,COSTOS_M2!$F$5:$F$67)),_xlpm.fila),_xlpm.cons_m2,INDEX(COSTOS_M2!$G$5:$G$67,_xlpm.fila),_xlpm.prof_factor,IF(AND(E37<>"—",E37<>"",ISNUMBER(E37)),POWER(E37/40,1.8),1),_xlpm.total_m2,(_xlpm.mat_m2+_xlpm.cons_m2)*H37*_xlpm.prof_factor*IF(C37>70,COSTOS_M2!$B$70,1)*IF(D37>244,COSTOS_M2!$B$71,1),_xlpm.total_m2)),"") -> 1339 | J37: =IFERROR(IF(B37="","",INDEX(MANO_DE_OBRA!$P$10:$P$72,MATCH(B37&"|"&IF(H37<=0.5,"CHICO",IF(H37<=1,"MEDIANO","GRANDE")),MANO_DE_OBRA!$Q$10:$Q$72,0))),"") -> 477.459 | K37: =IFERROR(IF(B37="","",_xlfn.LET(_xlpm.clave_prof,B37&"|"&E37,_xlpm.clave_todas,B37&"|TODAS",_xlpm.herr_prof,SUMIFS(HERRAJES!$H$5:$H$36,HERRAJES!$J$5:$J$36,_xlpm.clave_prof),_xlpm.herr_todas,SUMIFS(HERRAJES!$H$5:$H$36,HERRAJES!$J$5:$J$36,_xlpm.clave_todas),IF(_xlpm.herr_prof>0,_xlpm.herr_prof,_xlpm.herr_todas))),"") -> 0 | L37: =IFERROR(IF(B37="","",IF(I37="",0,I37)+IF(J37="",0,J37)+IF(K37="",0,K37)),"") -> 1816.459 | M37: =IFERROR(IF(L37="","",L37*$D$8),"") -> 2270.5738 | N37: =IFERROR(IF(M37="","",CEILING(M37,50)),"") -> 2300 | O37: 0 | P37: =IFERROR(IF(G37="","",G37*N37*(1-O37)),"") -> 2300
A38: V3 | B38: PISO CON ZOCLO | C38: 35 | D38: 100 | E38: — | F38: NOGAL | G38: 1 | H38: =IFERROR(IF(B38="","",(C38/100)*(D38/100)),"") -> 0.35 | I38: =IFERROR(IF(B38="","",_xlfn.LET(_xlpm.tamano,IF(H38<=0.5,"CHICO",IF(H38<=1,"MEDIANO","GRANDE")),_xlpm.clave,B38&"|"&_xlpm.tamano,_xlpm.fila,MATCH(_xlpm.clave,COSTOS_M2!$H$5:$H$67,0),_xlpm.mat_m2,INDEX(IF(F38="HUANACAXTLE",COSTOS_M2!$D$5:$D$67,IF(F38="ENCINO",COSTOS_M2!$E$5:$E$67,COSTOS_M2!$F$5:$F$67)),_xlpm.fila),_xlpm.cons_m2,INDEX(COSTOS_M2!$G$5:$G$67,_xlpm.fila),_xlpm.prof_factor,IF(AND(E38<>"—",E38<>"",ISNUMBER(E38)),POWER(E38/40,1.8),1),_xlpm.total_m2,(_xlpm.mat_m2+_xlpm.cons_m2)*H38*_xlpm.prof_factor*IF(C38>70,COSTOS_M2!$B$70,1)*IF(D38>244,COSTOS_M2!$B$71,1),_xlpm.total_m2)),"") -> 259.7 | J38: =IFERROR(IF(B38="","",INDEX(MANO_DE_OBRA!$P$10:$P$72,MATCH(B38&"|"&IF(H38<=0.5,"CHICO",IF(H38<=1,"MEDIANO","GRANDE")),MANO_DE_OBRA!$Q$10:$Q$72,0))),"") -> 395.78997 | K38: =IFERROR(IF(B38="","",_xlfn.LET(_xlpm.clave_prof,B38&"|"&E38,_xlpm.clave_todas,B38&"|TODAS",_xlpm.herr_prof,SUMIFS(HERRAJES!$H$5:$H$36,HERRAJES!$J$5:$J$36,_xlpm.clave_prof),_xlpm.herr_todas,SUMIFS(HERRAJES!$H$5:$H$36,HERRAJES!$J$5:$J$36,_xlpm.clave_todas),IF(_xlpm.herr_prof>0,_xlpm.herr_prof,_xlpm.herr_todas))),"") -> 0 | L38: =IFERROR(IF(B38="","",IF(I38="",0,I38)+IF(J38="",0,J38)+IF(K38="",0,K38)),"") -> 655.48997 | M38: =IFERROR(IF(L38="","",L38*$D$8),"") -> 819.36246 | N38: =IFERROR(IF(M38="","",CEILING(M38,50)),"") -> 850 | O38: 0 | P38: =IFERROR(IF(G38="","",G38*N38*(1-O38)),"") -> 850
A39: V3 | B39: CIELO | C39: 35 | D39: 100 | E39: — | F39: NOGAL | G39: 1 | H39: =IFERROR(IF(B39="","",(C39/100)*(D39/100)),"") -> 0.35 | I39: =IFERROR(IF(B39="","",_xlfn.LET(_xlpm.tamano,IF(H39<=0.5,"CHICO",IF(H39<=1,"MEDIANO","GRANDE")),_xlpm.clave,B39&"|"&_xlpm.tamano,_xlpm.fila,MATCH(_xlpm.clave,COSTOS_M2!$H$5:$H$67,0),_xlpm.mat_m2,INDEX(IF(F39="HUANACAXTLE",COSTOS_M2!$D$5:$D$67,IF(F39="ENCINO",COSTOS_M2!$E$5:$E$67,COSTOS_M2!$F$5:$F$67)),_xlpm.fila),_xlpm.cons_m2,INDEX(COSTOS_M2!$G$5:$G$67,_xlpm.fila),_xlpm.prof_factor,IF(AND(E39<>"—",E39<>"",ISNUMBER(E39)),POWER(E39/40,1.8),1),_xlpm.total_m2,(_xlpm.mat_m2+_xlpm.cons_m2)*H39*_xlpm.prof_factor*IF(C39>70,COSTOS_M2!$B$70,1)*IF(D39>244,COSTOS_M2!$B$71,1),_xlpm.total_m2)),"") -> 310.8 | J39: =IFERROR(IF(B39="","",INDEX(MANO_DE_OBRA!$P$10:$P$72,MATCH(B39&"|"&IF(H39<=0.5,"CHICO",IF(H39<=1,"MEDIANO","GRANDE")),MANO_DE_OBRA!$Q$10:$Q$72,0))),"") -> 404.95227 | K39: =IFERROR(IF(B39="","",_xlfn.LET(_xlpm.clave_prof,B39&"|"&E39,_xlpm.clave_todas,B39&"|TODAS",_xlpm.herr_prof,SUMIFS(HERRAJES!$H$5:$H$36,HERRAJES!$J$5:$J$36,_xlpm.clave_prof),_xlpm.herr_todas,SUMIFS(HERRAJES!$H$5:$H$36,HERRAJES!$J$5:$J$36,_xlpm.clave_todas),IF(_xlpm.herr_prof>0,_xlpm.herr_prof,_xlpm.herr_todas))),"") -> 0 | L39: =IFERROR(IF(B39="","",IF(I39="",0,I39)+IF(J39="",0,J39)+IF(K39="",0,K39)),"") -> 715.75227 | M39: =IFERROR(IF(L39="","",L39*$D$8),"") -> 894.69034 | N39: =IFERROR(IF(M39="","",CEILING(M39,50)),"") -> 900 | O39: 0 | P39: =IFERROR(IF(G39="","",G39*N39*(1-O39)),"") -> 900
A40: V3 | B40: PARAL 2 VISTAS | C40: 35 | D40: 295 | E40: — | F40: NOGAL | G40: 2 | H40: =IFERROR(IF(B40="","",(C40/100)*(D40/100)),"") -> 1.0325 | I40: =IFERROR(IF(B40="","",_xlfn.LET(_xlpm.tamano,IF(H40<=0.5,"CHICO",IF(H40<=1,"MEDIANO","GRANDE")),_xlpm.clave,B40&"|"&_xlpm.tamano,_xlpm.fila,MATCH(_xlpm.clave,COSTOS_M2!$H$5:$H$67,0),_xlpm.mat_m2,INDEX(IF(F40="HUANACAXTLE",COSTOS_M2!$D$5:$D$67,IF(F40="ENCINO",COSTOS_M2!$E$5:$E$67,COSTOS_M2!$F$5:$F$67)),_xlpm.fila),_xlpm.cons_m2,INDEX(COSTOS_M2!$G$5:$G$67,_xlpm.fila),_xlpm.prof_factor,IF(AND(E40<>"—",E40<>"",ISNUMBER(E40)),POWER(E40/40,1.8),1),_xlpm.total_m2,(_xlpm.mat_m2+_xlpm.cons_m2)*H40*_xlpm.prof_factor*IF(C40>70,COSTOS_M2!$B$70,1)*IF(D40>244,COSTOS_M2!$B$71,1),_xlpm.total_m2)),"") -> 1520.7693 | J40: =IFERROR(IF(B40="","",INDEX(MANO_DE_OBRA!$P$10:$P$72,MATCH(B40&"|"&IF(H40<=0.5,"CHICO",IF(H40<=1,"MEDIANO","GRANDE")),MANO_DE_OBRA!$Q$10:$Q$72,0))),"") -> 751.15698 | K40: =IFERROR(IF(B40="","",_xlfn.LET(_xlpm.clave_prof,B40&"|"&E40,_xlpm.clave_todas,B40&"|TODAS",_xlpm.herr_prof,SUMIFS(HERRAJES!$H$5:$H$36,HERRAJES!$J$5:$J$36,_xlpm.clave_prof),_xlpm.herr_todas,SUMIFS(HERRAJES!$H$5:$H$36,HERRAJES!$J$5:$J$36,_xlpm.clave_todas),IF(_xlpm.herr_prof>0,_xlpm.herr_prof,_xlpm.herr_todas))),"") -> 0 | L40: =IFERROR(IF(B40="","",IF(I40="",0,I40)+IF(J40="",0,J40)+IF(K40="",0,K40)),"") -> 2271.9262 | M40: =IFERROR(IF(L40="","",L40*$D$8),"") -> 2839.9078 | N40: =IFERROR(IF(M40="","",CEILING(M40,50)),"") -> 2850 | O40: 0 | P40: =IFERROR(IF(G40="","",G40*N40*(1-O40)),"") -> 5700
A41: V3 | B41: ZAPATERA EXTRAÍBLE | C41: 100 | D41: 35 | E41: — | F41: NOGAL | G41: 2 | H41: =IFERROR(IF(B41="","",(C41/100)*(D41/100)),"") -> 0.35 | I41: =IFERROR(IF(B41="","",_xlfn.LET(_xlpm.tamano,IF(H41<=0.5,"CHICO",IF(H41<=1,"MEDIANO","GRANDE")),_xlpm.clave,B41&"|"&_xlpm.tamano,_xlpm.fila,MATCH(_xlpm.clave,COSTOS_M2!$H$5:$H$67,0),_xlpm.mat_m2,INDEX(IF(F41="HUANACAXTLE",COSTOS_M2!$D$5:$D$67,IF(F41="ENCINO",COSTOS_M2!$E$5:$E$67,COSTOS_M2!$F$5:$F$67)),_xlpm.fila),_xlpm.cons_m2,INDEX(COSTOS_M2!$G$5:$G$67,_xlpm.fila),_xlpm.prof_factor,IF(AND(E41<>"—",E41<>"",ISNUMBER(E41)),POWER(E41/40,1.8),1),_xlpm.total_m2,(_xlpm.mat_m2+_xlpm.cons_m2)*H41*_xlpm.prof_factor*IF(C41>70,COSTOS_M2!$B$70,1)*IF(D41>244,COSTOS_M2!$B$71,1),_xlpm.total_m2)),"") -> 282.555 | J41: =IFERROR(IF(B41="","",INDEX(MANO_DE_OBRA!$P$10:$P$72,MATCH(B41&"|"&IF(H41<=0.5,"CHICO",IF(H41<=1,"MEDIANO","GRANDE")),MANO_DE_OBRA!$Q$10:$Q$72,0))),"") -> 396.27419 | K41: =IFERROR(IF(B41="","",_xlfn.LET(_xlpm.clave_prof,B41&"|"&E41,_xlpm.clave_todas,B41&"|TODAS",_xlpm.herr_prof,SUMIFS(HERRAJES!$H$5:$H$36,HERRAJES!$J$5:$J$36,_xlpm.clave_prof),_xlpm.herr_todas,SUMIFS(HERRAJES!$H$5:$H$36,HERRAJES!$J$5:$J$36,_xlpm.clave_todas),IF(_xlpm.herr_prof>0,_xlpm.herr_prof,_xlpm.herr_todas))),"") -> 0 | L41: =IFERROR(IF(B41="","",IF(I41="",0,I41)+IF(J41="",0,J41)+IF(K41="",0,K41)),"") -> 678.82919 | M41: =IFERROR(IF(L41="","",L41*$D$8),"") -> 848.53649 | N41: =IFERROR(IF(M41="","",CEILING(M41,50)),"") -> 850 | O41: 0 | P41: =IFERROR(IF(G41="","",G41*N41*(1-O41)),"") -> 1700
A42: V3 | B42: ENTREPAÑO | C42: 35 | D42: 100 | E42: — | F42: NOGAL | G42: 5 | H42: =IFERROR(IF(B42="","",(C42/100)*(D42/100)),"") -> 0.35 | I42: =IFERROR(IF(B42="","",_xlfn.LET(_xlpm.tamano,IF(H42<=0.5,"CHICO",IF(H42<=1,"MEDIANO","GRANDE")),_xlpm.clave,B42&"|"&_xlpm.tamano,_xlpm.fila,MATCH(_xlpm.clave,COSTOS_M2!$H$5:$H$67,0),_xlpm.mat_m2,INDEX(IF(F42="HUANACAXTLE",COSTOS_M2!$D$5:$D$67,IF(F42="ENCINO",COSTOS_M2!$E$5:$E$67,COSTOS_M2!$F$5:$F$67)),_xlpm.fila),_xlpm.cons_m2,INDEX(COSTOS_M2!$G$5:$G$67,_xlpm.fila),_xlpm.prof_factor,IF(AND(E42<>"—",E42<>"",ISNUMBER(E42)),POWER(E42/40,1.8),1),_xlpm.total_m2,(_xlpm.mat_m2+_xlpm.cons_m2)*H42*_xlpm.prof_factor*IF(C42>70,COSTOS_M2!$B$70,1)*IF(D42>244,COSTOS_M2!$B$71,1),_xlpm.total_m2)),"") -> 275.1 | J42: =IFERROR(IF(B42="","",INDEX(MANO_DE_OBRA!$P$10:$P$72,MATCH(B42&"|"&IF(H42<=0.5,"CHICO",IF(H42<=1,"MEDIANO","GRANDE")),MANO_DE_OBRA!$Q$10:$Q$72,0))),"") -> 292.24065 | K42: =IFERROR(IF(B42="","",_xlfn.LET(_xlpm.clave_prof,B42&"|"&E42,_xlpm.clave_todas,B42&"|TODAS",_xlpm.herr_prof,SUMIFS(HERRAJES!$H$5:$H$36,HERRAJES!$J$5:$J$36,_xlpm.clave_prof),_xlpm.herr_todas,SUMIFS(HERRAJES!$H$5:$H$36,HERRAJES!$J$5:$J$36,_xlpm.clave_todas),IF(_xlpm.herr_prof>0,_xlpm.herr_prof,_xlpm.herr_todas))),"") -> 0 | L42: =IFERROR(IF(B42="","",IF(I42="",0,I42)+IF(J42="",0,J42)+IF(K42="",0,K42)),"") -> 567.34065 | M42: =IFERROR(IF(L42="","",L42*$D$8),"") -> 709.17581 | N42: =IFERROR(IF(M42="","",CEILING(M42,50)),"") -> 750 | O42: 0 | P42: =IFERROR(IF(G42="","",G42*N42*(1-O42)),"") -> 3750
A43: V3 | B43: ENTREPAÑO DELGADO | C43: 35 | D43: 100 | E43: — | F43: NOGAL | G43: 1 | H43: =IFERROR(IF(B43="","",(C43/100)*(D43/100)),"") -> 0.35 | I43: =IFERROR(IF(B43="","",_xlfn.LET(_xlpm.tamano,IF(H43<=0.5,"CHICO",IF(H43<=1,"MEDIANO","GRANDE")),_xlpm.clave,B43&"|"&_xlpm.tamano,_xlpm.fila,MATCH(_xlpm.clave,COSTOS_M2!$H$5:$H$67,0),_xlpm.mat_m2,INDEX(IF(F43="HUANACAXTLE",COSTOS_M2!$D$5:$D$67,IF(F43="ENCINO",COSTOS_M2!$E$5:$E$67,COSTOS_M2!$F$5:$F$67)),_xlpm.fila),_xlpm.cons_m2,INDEX(COSTOS_M2!$G$5:$G$67,_xlpm.fila),_xlpm.prof_factor,IF(AND(E43<>"—",E43<>"",ISNUMBER(E43)),POWER(E43/40,1.8),1),_xlpm.total_m2,(_xlpm.mat_m2+_xlpm.cons_m2)*H43*_xlpm.prof_factor*IF(C43>70,COSTOS_M2!$B$70,1)*IF(D43>244,COSTOS_M2!$B$71,1),_xlpm.total_m2)),"") -> 292.25 | J43: =IFERROR(IF(B43="","",INDEX(MANO_DE_OBRA!$P$10:$P$72,MATCH(B43&"|"&IF(H43<=0.5,"CHICO",IF(H43<=1,"MEDIANO","GRANDE")),MANO_DE_OBRA!$Q$10:$Q$72,0))),"") -> 265.8015 | K43: =IFERROR(IF(B43="","",_xlfn.LET(_xlpm.clave_prof,B43&"|"&E43,_xlpm.clave_todas,B43&"|TODAS",_xlpm.herr_prof,SUMIFS(HERRAJES!$H$5:$H$36,HERRAJES!$J$5:$J$36,_xlpm.clave_prof),_xlpm.herr_todas,SUMIFS(HERRAJES!$H$5:$H$36,HERRAJES!$J$5:$J$36,_xlpm.clave_todas),IF(_xlpm.herr_prof>0,_xlpm.herr_prof,_xlpm.herr_todas))),"") -> 0 | L43: =IFERROR(IF(B43="","",IF(I43="",0,I43)+IF(J43="",0,J43)+IF(K43="",0,K43)),"") -> 558.0515 | M43: =IFERROR(IF(L43="","",L43*$D$8),"") -> 697.56438 | N43: =IFERROR(IF(M43="","",CEILING(M43,50)),"") -> 700 | O43: 0 | P43: =IFERROR(IF(G43="","",G43*N43*(1-O43)),"") -> 700
A44: V3 | B44: FONDO MADERA | C44: 100 | D44: 305 | E44: — | F44: NOGAL | G44: 1 | H44: =IFERROR(IF(B44="","",(C44/100)*(D44/100)),"") -> 3.05 | I44: =IFERROR(IF(B44="","",_xlfn.LET(_xlpm.tamano,IF(H44<=0.5,"CHICO",IF(H44<=1,"MEDIANO","GRANDE")),_xlpm.clave,B44&"|"&_xlpm.tamano,_xlpm.fila,MATCH(_xlpm.clave,COSTOS_M2!$H$5:$H$67,0),_xlpm.mat_m2,INDEX(IF(F44="HUANACAXTLE",COSTOS_M2!$D$5:$D$67,IF(F44="ENCINO",COSTOS_M2!$E$5:$E$67,COSTOS_M2!$F$5:$F$67)),_xlpm.fila),_xlpm.cons_m2,INDEX(COSTOS_M2!$G$5:$G$67,_xlpm.fila),_xlpm.prof_factor,IF(AND(E44<>"—",E44<>"",ISNUMBER(E44)),POWER(E44/40,1.8),1),_xlpm.total_m2,(_xlpm.mat_m2+_xlpm.cons_m2)*H44*_xlpm.prof_factor*IF(C44>70,COSTOS_M2!$B$70,1)*IF(D44>244,COSTOS_M2!$B$71,1),_xlpm.total_m2)),"") -> 1211.3075 | J44: =IFERROR(IF(B44="","",INDEX(MANO_DE_OBRA!$P$10:$P$72,MATCH(B44&"|"&IF(H44<=0.5,"CHICO",IF(H44<=1,"MEDIANO","GRANDE")),MANO_DE_OBRA!$Q$10:$Q$72,0))),"") -> 295.7955 | K44: =IFERROR(IF(B44="","",_xlfn.LET(_xlpm.clave_prof,B44&"|"&E44,_xlpm.clave_todas,B44&"|TODAS",_xlpm.herr_prof,SUMIFS(HERRAJES!$H$5:$H$36,HERRAJES!$J$5:$J$36,_xlpm.clave_prof),_xlpm.herr_todas,SUMIFS(HERRAJES!$H$5:$H$36,HERRAJES!$J$5:$J$36,_xlpm.clave_todas),IF(_xlpm.herr_prof>0,_xlpm.herr_prof,_xlpm.herr_todas))),"") -> 0 | L44: =IFERROR(IF(B44="","",IF(I44="",0,I44)+IF(J44="",0,J44)+IF(K44="",0,K44)),"") -> 1507.103 | M44: =IFERROR(IF(L44="","",L44*$D$8),"") -> 1883.8788 | N44: =IFERROR(IF(M44="","",CEILING(M44,50)),"") -> 1900 | O44: 0 | P44: =IFERROR(IF(G44="","",G44*N44*(1-O44)),"") -> 1900
A45: V3 | B45: MOLDURA DIFÍCIL | C45: 5 | D45: 210 | E45: — | F45: NOGAL | G45: 1 | H45: =IFERROR(IF(B45="","",(C45/100)*(D45/100)),"") -> 0.105 | I45: =IFERROR(IF(B45="","",_xlfn.LET(_xlpm.tamano,IF(H45<=0.5,"CHICO",IF(H45<=1,"MEDIANO","GRANDE")),_xlpm.clave,B45&"|"&_xlpm.tamano,_xlpm.fila,MATCH(_xlpm.clave,COSTOS_M2!$H$5:$H$67,0),_xlpm.mat_m2,INDEX(IF(F45="HUANACAXTLE",COSTOS_M2!$D$5:$D$67,IF(F45="ENCINO",COSTOS_M2!$E$5:$E$67,COSTOS_M2!$F$5:$F$67)),_xlpm.fila),_xlpm.cons_m2,INDEX(COSTOS_M2!$G$5:$G$67,_xlpm.fila),_xlpm.prof_factor,IF(AND(E45<>"—",E45<>"",ISNUMBER(E45)),POWER(E45/40,1.8),1),_xlpm.total_m2,(_xlpm.mat_m2+_xlpm.cons_m2)*H45*_xlpm.prof_factor*IF(C45>70,COSTOS_M2!$B$70,1)*IF(D45>244,COSTOS_M2!$B$71,1),_xlpm.total_m2)),"") -> 540.75 | J45: =IFERROR(IF(B45="","",INDEX(MANO_DE_OBRA!$P$10:$P$72,MATCH(B45&"|"&IF(H45<=0.5,"CHICO",IF(H45<=1,"MEDIANO","GRANDE")),MANO_DE_OBRA!$Q$10:$Q$72,0))),"") -> 477.459 | K45: =IFERROR(IF(B45="","",_xlfn.LET(_xlpm.clave_prof,B45&"|"&E45,_xlpm.clave_todas,B45&"|TODAS",_xlpm.herr_prof,SUMIFS(HERRAJES!$H$5:$H$36,HERRAJES!$J$5:$J$36,_xlpm.clave_prof),_xlpm.herr_todas,SUMIFS(HERRAJES!$H$5:$H$36,HERRAJES!$J$5:$J$36,_xlpm.clave_todas),IF(_xlpm.herr_prof>0,_xlpm.herr_prof,_xlpm.herr_todas))),"") -> 0 | L45: =IFERROR(IF(B45="","",IF(I45="",0,I45)+IF(J45="",0,J45)+IF(K45="",0,K45)),"") -> 1018.209 | M45: =IFERROR(IF(L45="","",L45*$D$8),"") -> 1272.7613 | N45: =IFERROR(IF(M45="","",CEILING(M45,50)),"") -> 1300 | O45: 0 | P45: =IFERROR(IF(G45="","",G45*N45*(1-O45)),"") -> 1300
B46: ANTECÁMARA NIÑAS
A47: V1 | B47: PISO CON ZOCLO | C47: 25 | D47: 250 | E47: — | F47: NOGAL | G47: 1 | H47: =IFERROR(IF(B47="","",(C47/100)*(D47/100)),"") -> 0.625 | I47: =IFERROR(IF(B47="","",_xlfn.LET(_xlpm.tamano,IF(H47<=0.5,"CHICO",IF(H47<=1,"MEDIANO","GRANDE")),_xlpm.clave,B47&"|"&_xlpm.tamano,_xlpm.fila,MATCH(_xlpm.clave,COSTOS_M2!$H$5:$H$67,0),_xlpm.mat_m2,INDEX(IF(F47="HUANACAXTLE",COSTOS_M2!$D$5:$D$67,IF(F47="ENCINO",COSTOS_M2!$E$5:$E$67,COSTOS_M2!$F$5:$F$67)),_xlpm.fila),_xlpm.cons_m2,INDEX(COSTOS_M2!$G$5:$G$67,_xlpm.fila),_xlpm.prof_factor,IF(AND(E47<>"—",E47<>"",ISNUMBER(E47)),POWER(E47/40,1.8),1),_xlpm.total_m2,(_xlpm.mat_m2+_xlpm.cons_m2)*H47*_xlpm.prof_factor*IF(C47>70,COSTOS_M2!$B$70,1)*IF(D47>244,COSTOS_M2!$B$71,1),_xlpm.total_m2)),"") -> 570.375 | J47: =IFERROR(IF(B47="","",INDEX(MANO_DE_OBRA!$P$10:$P$72,MATCH(B47&"|"&IF(H47<=0.5,"CHICO",IF(H47<=1,"MEDIANO","GRANDE")),MANO_DE_OBRA!$Q$10:$Q$72,0))),"") -> 469.28724 | K47: =IFERROR(IF(B47="","",_xlfn.LET(_xlpm.clave_prof,B47&"|"&E47,_xlpm.clave_todas,B47&"|TODAS",_xlpm.herr_prof,SUMIFS(HERRAJES!$H$5:$H$36,HERRAJES!$J$5:$J$36,_xlpm.clave_prof),_xlpm.herr_todas,SUMIFS(HERRAJES!$H$5:$H$36,HERRAJES!$J$5:$J$36,_xlpm.clave_todas),IF(_xlpm.herr_prof>0,_xlpm.herr_prof,_xlpm.herr_todas))),"") -> 0 | L47: =IFERROR(IF(B47="","",IF(I47="",0,I47)+IF(J47="",0,J47)+IF(K47="",0,K47)),"") -> 1039.6622 | M47: =IFERROR(IF(L47="","",L47*$D$8),"") -> 1299.5778 | N47: =IFERROR(IF(M47="","",CEILING(M47,50)),"") -> 1300 | O47: 0 | P47: =IFERROR(IF(G47="","",G47*N47*(1-O47)),"") -> 1300
A48: V1 | B48: CIELO | C48: 25 | D48: 250 | E48: — | F48: NOGAL | G48: 1 | H48: =IFERROR(IF(B48="","",(C48/100)*(D48/100)),"") -> 0.625 | I48: =IFERROR(IF(B48="","",_xlfn.LET(_xlpm.tamano,IF(H48<=0.5,"CHICO",IF(H48<=1,"MEDIANO","GRANDE")),_xlpm.clave,B48&"|"&_xlpm.tamano,_xlpm.fila,MATCH(_xlpm.clave,COSTOS_M2!$H$5:$H$67,0),_xlpm.mat_m2,INDEX(IF(F48="HUANACAXTLE",COSTOS_M2!$D$5:$D$67,IF(F48="ENCINO",COSTOS_M2!$E$5:$E$67,COSTOS_M2!$F$5:$F$67)),_xlpm.fila),_xlpm.cons_m2,INDEX(COSTOS_M2!$G$5:$G$67,_xlpm.fila),_xlpm.prof_factor,IF(AND(E48<>"—",E48<>"",ISNUMBER(E48)),POWER(E48/40,1.8),1),_xlpm.total_m2,(_xlpm.mat_m2+_xlpm.cons_m2)*H48*_xlpm.prof_factor*IF(C48>70,COSTOS_M2!$B$70,1)*IF(D48>244,COSTOS_M2!$B$71,1),_xlpm.total_m2)),"") -> 679.25 | J48: =IFERROR(IF(B48="","",INDEX(MANO_DE_OBRA!$P$10:$P$72,MATCH(B48&"|"&IF(H48<=0.5,"CHICO",IF(H48<=1,"MEDIANO","GRANDE")),MANO_DE_OBRA!$Q$10:$Q$72,0))),"") -> 520.0504 | K48: =IFERROR(IF(B48="","",_xlfn.LET(_xlpm.clave_prof,B48&"|"&E48,_xlpm.clave_todas,B48&"|TODAS",_xlpm.herr_prof,SUMIFS(HERRAJES!$H$5:$H$36,HERRAJES!$J$5:$J$36,_xlpm.clave_prof),_xlpm.herr_todas,SUMIFS(HERRAJES!$H$5:$H$36,HERRAJES!$J$5:$J$36,_xlpm.clave_todas),IF(_xlpm.herr_prof>0,_xlpm.herr_prof,_xlpm.herr_todas))),"") -> 0 | L48: =IFERROR(IF(B48="","",IF(I48="",0,I48)+IF(J48="",0,J48)+IF(K48="",0,K48)),"") -> 1199.3004 | M48: =IFERROR(IF(L48="","",L48*$D$8),"") -> 1499.1255 | N48: =IFERROR(IF(M48="","",CEILING(M48,50)),"") -> 1500 | O48: 0 | P48: =IFERROR(IF(G48="","",G48*N48*(1-O48)),"") -> 1500
A49: V1 | B49: PARAL 1 VISTA | C49: 25 | D49: 295 | E49: — | F49: NOGAL | G49: 2 | H49: =IFERROR(IF(B49="","",(C49/100)*(D49/100)),"") -> 0.7375 | I49: =IFERROR(IF(B49="","",_xlfn.LET(_xlpm.tamano,IF(H49<=0.5,"CHICO",IF(H49<=1,"MEDIANO","GRANDE")),_xlpm.clave,B49&"|"&_xlpm.tamano,_xlpm.fila,MATCH(_xlpm.clave,COSTOS_M2!$H$5:$H$67,0),_xlpm.mat_m2,INDEX(IF(F49="HUANACAXTLE",COSTOS_M2!$D$5:$D$67,IF(F49="ENCINO",COSTOS_M2!$E$5:$E$67,COSTOS_M2!$F$5:$F$67)),_xlpm.fila),_xlpm.cons_m2,INDEX(COSTOS_M2!$G$5:$G$67,_xlpm.fila),_xlpm.prof_factor,IF(AND(E49<>"—",E49<>"",ISNUMBER(E49)),POWER(E49/40,1.8),1),_xlpm.total_m2,(_xlpm.mat_m2+_xlpm.cons_m2)*H49*_xlpm.prof_factor*IF(C49>70,COSTOS_M2!$B$70,1)*IF(D49>244,COSTOS_M2!$B$71,1),_xlpm.total_m2)),"") -> 697.97 | J49: =IFERROR(IF(B49="","",INDEX(MANO_DE_OBRA!$P$10:$P$72,MATCH(B49&"|"&IF(H49<=0.5,"CHICO",IF(H49<=1,"MEDIANO","GRANDE")),MANO_DE_OBRA!$Q$10:$Q$72,0))),"") -> 511.7469 | K49: =IFERROR(IF(B49="","",_xlfn.LET(_xlpm.clave_prof,B49&"|"&E49,_xlpm.clave_todas,B49&"|TODAS",_xlpm.herr_prof,SUMIFS(HERRAJES!$H$5:$H$36,HERRAJES!$J$5:$J$36,_xlpm.clave_prof),_xlpm.herr_todas,SUMIFS(HERRAJES!$H$5:$H$36,HERRAJES!$J$5:$J$36,_xlpm.clave_todas),IF(_xlpm.herr_prof>0,_xlpm.herr_prof,_xlpm.herr_todas))),"") -> 0 | L49: =IFERROR(IF(B49="","",IF(I49="",0,I49)+IF(J49="",0,J49)+IF(K49="",0,K49)),"") -> 1209.7169 | M49: =IFERROR(IF(L49="","",L49*$D$8),"") -> 1512.1461 | N49: =IFERROR(IF(M49="","",CEILING(M49,50)),"") -> 1550 | O49: 0 | P49: =IFERROR(IF(G49="","",G49*N49*(1-O49)),"") -> 3100
A50: V1 | B50: PARAL DELGADO 2V | C50: 25 | D50: 295 | E50: — | F50: NOGAL | G50: 1 | H50: =IFERROR(IF(B50="","",(C50/100)*(D50/100)),"") -> 0.7375 | I50: =IFERROR(IF(B50="","",_xlfn.LET(_xlpm.tamano,IF(H50<=0.5,"CHICO",IF(H50<=1,"MEDIANO","GRANDE")),_xlpm.clave,B50&"|"&_xlpm.tamano,_xlpm.fila,MATCH(_xlpm.clave,COSTOS_M2!$H$5:$H$67,0),_xlpm.mat_m2,INDEX(IF(F50="HUANACAXTLE",COSTOS_M2!$D$5:$D$67,IF(F50="ENCINO",COSTOS_M2!$E$5:$E$67,COSTOS_M2!$F$5:$F$67)),_xlpm.fila),_xlpm.cons_m2,INDEX(COSTOS_M2!$G$5:$G$67,_xlpm.fila),_xlpm.prof_factor,IF(AND(E50<>"—",E50<>"",ISNUMBER(E50)),POWER(E50/40,1.8),1),_xlpm.total_m2,(_xlpm.mat_m2+_xlpm.cons_m2)*H50*_xlpm.prof_factor*IF(C50>70,COSTOS_M2!$B$70,1)*IF(D50>244,COSTOS_M2!$B$71,1),_xlpm.total_m2)),"") -> 752.61875 | J50: =IFERROR(IF(B50="","",INDEX(MANO_DE_OBRA!$P$10:$P$72,MATCH(B50&"|"&IF(H50<=0.5,"CHICO",IF(H50<=1,"MEDIANO","GRANDE")),MANO_DE_OBRA!$Q$10:$Q$72,0))),"") -> 558.222 | K50: =IFERROR(IF(B50="","",_xlfn.LET(_xlpm.clave_prof,B50&"|"&E50,_xlpm.clave_todas,B50&"|TODAS",_xlpm.herr_prof,SUMIFS(HERRAJES!$H$5:$H$36,HERRAJES!$J$5:$J$36,_xlpm.clave_prof),_xlpm.herr_todas,SUMIFS(HERRAJES!$H$5:$H$36,HERRAJES!$J$5:$J$36,_xlpm.clave_todas),IF(_xlpm.herr_prof>0,_xlpm.herr_prof,_xlpm.herr_todas))),"") -> 0 | L50: =IFERROR(IF(B50="","",IF(I50="",0,I50)+IF(J50="",0,J50)+IF(K50="",0,K50)),"") -> 1310.8407 | M50: =IFERROR(IF(L50="","",L50*$D$8),"") -> 1638.5509 | N50: =IFERROR(IF(M50="","",CEILING(M50,50)),"") -> 1650 | O50: 0 | P50: =IFERROR(IF(G50="","",G50*N50*(1-O50)),"") -> 1650
A51: V1 | B51: ENTREPAÑO | C51: 25 | D51: 125 | E51: — | F51: NOGAL | G51: 2 | H51: =IFERROR(IF(B51="","",(C51/100)*(D51/100)),"") -> 0.3125 | I51: =IFERROR(IF(B51="","",_xlfn.LET(_xlpm.tamano,IF(H51<=0.5,"CHICO",IF(H51<=1,"MEDIANO","GRANDE")),_xlpm.clave,B51&"|"&_xlpm.tamano,_xlpm.fila,MATCH(_xlpm.clave,COSTOS_M2!$H$5:$H$67,0),_xlpm.mat_m2,INDEX(IF(F51="HUANACAXTLE",COSTOS_M2!$D$5:$D$67,IF(F51="ENCINO",COSTOS_M2!$E$5:$E$67,COSTOS_M2!$F$5:$F$67)),_xlpm.fila),_xlpm.cons_m2,INDEX(COSTOS_M2!$G$5:$G$67,_xlpm.fila),_xlpm.prof_factor,IF(AND(E51<>"—",E51<>"",ISNUMBER(E51)),POWER(E51/40,1.8),1),_xlpm.total_m2,(_xlpm.mat_m2+_xlpm.cons_m2)*H51*_xlpm.prof_factor*IF(C51>70,COSTOS_M2!$B$70,1)*IF(D51>244,COSTOS_M2!$B$71,1),_xlpm.total_m2)),"") -> 245.625 | J51: =IFERROR(IF(B51="","",INDEX(MANO_DE_OBRA!$P$10:$P$72,MATCH(B51&"|"&IF(H51<=0.5,"CHICO",IF(H51<=1,"MEDIANO","GRANDE")),MANO_DE_OBRA!$Q$10:$Q$72,0))),"") -> 292.24065 | K51: =IFERROR(IF(B51="","",_xlfn.LET(_xlpm.clave_prof,B51&"|"&E51,_xlpm.clave_todas,B51&"|TODAS",_xlpm.herr_prof,SUMIFS(HERRAJES!$H$5:$H$36,HERRAJES!$J$5:$J$36,_xlpm.clave_prof),_xlpm.herr_todas,SUMIFS(HERRAJES!$H$5:$H$36,HERRAJES!$J$5:$J$36,_xlpm.clave_todas),IF(_xlpm.herr_prof>0,_xlpm.herr_prof,_xlpm.herr_todas))),"") -> 0 | L51: =IFERROR(IF(B51="","",IF(I51="",0,I51)+IF(J51="",0,J51)+IF(K51="",0,K51)),"") -> 537.86565 | M51: =IFERROR(IF(L51="","",L51*$D$8),"") -> 672.33206 | N51: =IFERROR(IF(M51="","",CEILING(M51,50)),"") -> 700 | O51: 0 | P51: =IFERROR(IF(G51="","",G51*N51*(1-O51)),"") -> 1400
A52: V1 | B52: ENTREPAÑO DELGADO | C52: 25 | D52: 125 | E52: — | F52: NOGAL | G52: 6 | H52: =IFERROR(IF(B52="","",(C52/100)*(D52/100)),"") -> 0.3125 | I52: =IFERROR(IF(B52="","",_xlfn.LET(_xlpm.tamano,IF(H52<=0.5,"CHICO",IF(H52<=1,"MEDIANO","GRANDE")),_xlpm.clave,B52&"|"&_xlpm.tamano,_xlpm.fila,MATCH(_xlpm.clave,COSTOS_M2!$H$5:$H$67,0),_xlpm.mat_m2,INDEX(IF(F52="HUANACAXTLE",COSTOS_M2!$D$5:$D$67,IF(F52="ENCINO",COSTOS_M2!$E$5:$E$67,COSTOS_M2!$F$5:$F$67)),_xlpm.fila),_xlpm.cons_m2,INDEX(COSTOS_M2!$G$5:$G$67,_xlpm.fila),_xlpm.prof_factor,IF(AND(E52<>"—",E52<>"",ISNUMBER(E52)),POWER(E52/40,1.8),1),_xlpm.total_m2,(_xlpm.mat_m2+_xlpm.cons_m2)*H52*_xlpm.prof_factor*IF(C52>70,COSTOS_M2!$B$70,1)*IF(D52>244,COSTOS_M2!$B$71,1),_xlpm.total_m2)),"") -> 260.9375 | J52: =IFERROR(IF(B52="","",INDEX(MANO_DE_OBRA!$P$10:$P$72,MATCH(B52&"|"&IF(H52<=0.5,"CHICO",IF(H52<=1,"MEDIANO","GRANDE")),MANO_DE_OBRA!$Q$10:$Q$72,0))),"") -> 265.8015 | K52: =IFERROR(IF(B52="","",_xlfn.LET(_xlpm.clave_prof,B52&"|"&E52,_xlpm.clave_todas,B52&"|TODAS",_xlpm.herr_prof,SUMIFS(HERRAJES!$H$5:$H$36,HERRAJES!$J$5:$J$36,_xlpm.clave_prof),_xlpm.herr_todas,SUMIFS(HERRAJES!$H$5:$H$36,HERRAJES!$J$5:$J$36,_xlpm.clave_todas),IF(_xlpm.herr_prof>0,_xlpm.herr_prof,_xlpm.herr_todas))),"") -> 0 | L52: =IFERROR(IF(B52="","",IF(I52="",0,I52)+IF(J52="",0,J52)+IF(K52="",0,K52)),"") -> 526.739 | M52: =IFERROR(IF(L52="","",L52*$D$8),"") -> 658.42375 | N52: =IFERROR(IF(M52="","",CEILING(M52,50)),"") -> 700 | O52: 0 | P52: =IFERROR(IF(G52="","",G52*N52*(1-O52)),"") -> 4200
A53: V1 | B53: PUERTA ABATIBLE | C53: 65 | D53: 75 | E53: — | F53: NOGAL | G53: 4 | H53: =IFERROR(IF(B53="","",(C53/100)*(D53/100)),"") -> 0.4875 | I53: =IFERROR(IF(B53="","",_xlfn.LET(_xlpm.tamano,IF(H53<=0.5,"CHICO",IF(H53<=1,"MEDIANO","GRANDE")),_xlpm.clave,B53&"|"&_xlpm.tamano,_xlpm.fila,MATCH(_xlpm.clave,COSTOS_M2!$H$5:$H$67,0),_xlpm.mat_m2,INDEX(IF(F53="HUANACAXTLE",COSTOS_M2!$D$5:$D$67,IF(F53="ENCINO",COSTOS_M2!$E$5:$E$67,COSTOS_M2!$F$5:$F$67)),_xlpm.fila),_xlpm.cons_m2,INDEX(COSTOS_M2!$G$5:$G$67,_xlpm.fila),_xlpm.prof_factor,IF(AND(E53<>"—",E53<>"",ISNUMBER(E53)),POWER(E53/40,1.8),1),_xlpm.total_m2,(_xlpm.mat_m2+_xlpm.cons_m2)*H53*_xlpm.prof_factor*IF(C53>70,COSTOS_M2!$B$70,1)*IF(D53>244,COSTOS_M2!$B$71,1),_xlpm.total_m2)),"") -> 436.3125 | J53: =IFERROR(IF(B53="","",INDEX(MANO_DE_OBRA!$P$10:$P$72,MATCH(B53&"|"&IF(H53<=0.5,"CHICO",IF(H53<=1,"MEDIANO","GRANDE")),MANO_DE_OBRA!$Q$10:$Q$72,0))),"") -> 489.59529 | K53: =IFERROR(IF(B53="","",_xlfn.LET(_xlpm.clave_prof,B53&"|"&E53,_xlpm.clave_todas,B53&"|TODAS",_xlpm.herr_prof,SUMIFS(HERRAJES!$H$5:$H$36,HERRAJES!$J$5:$J$36,_xlpm.clave_prof),_xlpm.herr_todas,SUMIFS(HERRAJES!$H$5:$H$36,HERRAJES!$J$5:$J$36,_xlpm.clave_todas),IF(_xlpm.herr_prof>0,_xlpm.herr_prof,_xlpm.herr_todas))),"") -> 311.4 | L53: =IFERROR(IF(B53="","",IF(I53="",0,I53)+IF(J53="",0,J53)+IF(K53="",0,K53)),"") -> 1237.3078 | M53: =IFERROR(IF(L53="","",L53*$D$8),"") -> 1546.6347 | N53: =IFERROR(IF(M53="","",CEILING(M53,50)),"") -> 1550 | O53: 0 | P53: =IFERROR(IF(G53="","",G53*N53*(1-O53)),"") -> 6200
A54: V1 | B54: MOLDURA SENCILLA | C54: 5 | D54: 960 | E54: — | F54: NOGAL | G54: 1 | H54: =IFERROR(IF(B54="","",(C54/100)*(D54/100)),"") -> 0.48 | I54: =IFERROR(IF(B54="","",_xlfn.LET(_xlpm.tamano,IF(H54<=0.5,"CHICO",IF(H54<=1,"MEDIANO","GRANDE")),_xlpm.clave,B54&"|"&_xlpm.tamano,_xlpm.fila,MATCH(_xlpm.clave,COSTOS_M2!$H$5:$H$67,0),_xlpm.mat_m2,INDEX(IF(F54="HUANACAXTLE",COSTOS_M2!$D$5:$D$67,IF(F54="ENCINO",COSTOS_M2!$E$5:$E$67,COSTOS_M2!$F$5:$F$67)),_xlpm.fila),_xlpm.cons_m2,INDEX(COSTOS_M2!$G$5:$G$67,_xlpm.fila),_xlpm.prof_factor,IF(AND(E54<>"—",E54<>"",ISNUMBER(E54)),POWER(E54/40,1.8),1),_xlpm.total_m2,(_xlpm.mat_m2+_xlpm.cons_m2)*H54*_xlpm.prof_factor*IF(C54>70,COSTOS_M2!$B$70,1)*IF(D54>244,COSTOS_M2!$B$71,1),_xlpm.total_m2)),"") -> 3213.6 | J54: =IFERROR(IF(B54="","",INDEX(MANO_DE_OBRA!$P$10:$P$72,MATCH(B54&"|"&IF(H54<=0.5,"CHICO",IF(H54<=1,"MEDIANO","GRANDE")),MANO_DE_OBRA!$Q$10:$Q$72,0))),"") -> 356.3865 | K54: =IFERROR(IF(B54="","",_xlfn.LET(_xlpm.clave_prof,B54&"|"&E54,_xlpm.clave_todas,B54&"|TODAS",_xlpm.herr_prof,SUMIFS(HERRAJES!$H$5:$H$36,HERRAJES!$J$5:$J$36,_xlpm.clave_prof),_xlpm.herr_todas,SUMIFS(HERRAJES!$H$5:$H$36,HERRAJES!$J$5:$J$36,_xlpm.clave_todas),IF(_xlpm.herr_prof>0,_xlpm.herr_prof,_xlpm.herr_todas))),"") -> 0 | L54: =IFERROR(IF(B54="","",IF(I54="",0,I54)+IF(J54="",0,J54)+IF(K54="",0,K54)),"") -> 3569.9865 | M54: =IFERROR(IF(L54="","",L54*$D$8),"") -> 4462.4831 | N54: =IFERROR(IF(M54="","",CEILING(M54,50)),"") -> 4500 | O54: 0 | P54: =IFERROR(IF(G54="","",G54*N54*(1-O54)),"") -> 4500
A55: V1 | B55: FONDO MADERA | C55: 250 | D55: 305 | E55: — | F55: NOGAL | G55: 1 | H55: =IFERROR(IF(B55="","",(C55/100)*(D55/100)),"") -> 7.625 | I55: =IFERROR(IF(B55="","",_xlfn.LET(_xlpm.tamano,IF(H55<=0.5,"CHICO",IF(H55<=1,"MEDIANO","GRANDE")),_xlpm.clave,B55&"|"&_xlpm.tamano,_xlpm.fila,MATCH(_xlpm.clave,COSTOS_M2!$H$5:$H$67,0),_xlpm.mat_m2,INDEX(IF(F55="HUANACAXTLE",COSTOS_M2!$D$5:$D$67,IF(F55="ENCINO",COSTOS_M2!$E$5:$E$67,COSTOS_M2!$F$5:$F$67)),_xlpm.fila),_xlpm.cons_m2,INDEX(COSTOS_M2!$G$5:$G$67,_xlpm.fila),_xlpm.prof_factor,IF(AND(E55<>"—",E55<>"",ISNUMBER(E55)),POWER(E55/40,1.8),1),_xlpm.total_m2,(_xlpm.mat_m2+_xlpm.cons_m2)*H55*_xlpm.prof_factor*IF(C55>70,COSTOS_M2!$B$70,1)*IF(D55>244,COSTOS_M2!$B$71,1),_xlpm.total_m2)),"") -> 3028.2688 | J55: =IFERROR(IF(B55="","",INDEX(MANO_DE_OBRA!$P$10:$P$72,MATCH(B55&"|"&IF(H55<=0.5,"CHICO",IF(H55<=1,"MEDIANO","GRANDE")),MANO_DE_OBRA!$Q$10:$Q$72,0))),"") -> 295.7955 | K55: =IFERROR(IF(B55="","",_xlfn.LET(_xlpm.clave_prof,B55&"|"&E55,_xlpm.clave_todas,B55&"|TODAS",_xlpm.herr_prof,SUMIFS(HERRAJES!$H$5:$H$36,HERRAJES!$J$5:$J$36,_xlpm.clave_prof),_xlpm.herr_todas,SUMIFS(HERRAJES!$H$5:$H$36,HERRAJES!$J$5:$J$36,_xlpm.clave_todas),IF(_xlpm.herr_prof>0,_xlpm.herr_prof,_xlpm.herr_todas))),"") -> 0 | L55: =IFERROR(IF(B55="","",IF(I55="",0,I55)+IF(J55="",0,J55)+IF(K55="",0,K55)),"") -> 3324.0643 | M55: =IFERROR(IF(L55="","",L55*$D$8),"") -> 4155.0803 | N55: =IFERROR(IF(M55="","",CEILING(M55,50)),"") -> 4200 | O55: 0 | P55: =IFERROR(IF(G55="","",G55*N55*(1-O55)),"") -> 4200
A56: V1 | B56: MOLDURA DIFÍCIL | C56: 5 | D56: 500 | E56: — | F56: NOGAL | G56: 1 | H56: =IFERROR(IF(B56="","",(C56/100)*(D56/100)),"") -> 0.25 | I56: =IFERROR(IF(B56="","",_xlfn.LET(_xlpm.tamano,IF(H56<=0.5,"CHICO",IF(H56<=1,"MEDIANO","GRANDE")),_xlpm.clave,B56&"|"&_xlpm.tamano,_xlpm.fila,MATCH(_xlpm.clave,COSTOS_M2!$H$5:$H$67,0),_xlpm.mat_m2,INDEX(IF(F56="HUANACAXTLE",COSTOS_M2!$D$5:$D$67,IF(F56="ENCINO",COSTOS_M2!$E$5:$E$67,COSTOS_M2!$F$5:$F$67)),_xlpm.fila),_xlpm.cons_m2,INDEX(COSTOS_M2!$G$5:$G$67,_xlpm.fila),_xlpm.prof_factor,IF(AND(E56<>"—",E56<>"",ISNUMBER(E56)),POWER(E56/40,1.8),1),_xlpm.total_m2,(_xlpm.mat_m2+_xlpm.cons_m2)*H56*_xlpm.prof_factor*IF(C56>70,COSTOS_M2!$B$70,1)*IF(D56>244,COSTOS_M2!$B$71,1),_xlpm.total_m2)),"") -> 1673.75 | J56: =IFERROR(IF(B56="","",INDEX(MANO_DE_OBRA!$P$10:$P$72,MATCH(B56&"|"&IF(H56<=0.5,"CHICO",IF(H56<=1,"MEDIANO","GRANDE")),MANO_DE_OBRA!$Q$10:$Q$72,0))),"") -> 477.459 | K56: =IFERROR(IF(B56="","",_xlfn.LET(_xlpm.clave_prof,B56&"|"&E56,_xlpm.clave_todas,B56&"|TODAS",_xlpm.herr_prof,SUMIFS(HERRAJES!$H$5:$H$36,HERRAJES!$J$5:$J$36,_xlpm.clave_prof),_xlpm.herr_todas,SUMIFS(HERRAJES!$H$5:$H$36,HERRAJES!$J$5:$J$36,_xlpm.clave_todas),IF(_xlpm.herr_prof>0,_xlpm.herr_prof,_xlpm.herr_todas))),"") -> 0 | L56: =IFERROR(IF(B56="","",IF(I56="",0,I56)+IF(J56="",0,J56)+IF(K56="",0,K56)),"") -> 2151.209 | M56: =IFERROR(IF(L56="","",L56*$D$8),"") -> 2689.0112 | N56: =IFERROR(IF(M56="","",CEILING(M56,50)),"") -> 2700 | O56: 0 | P56: =IFERROR(IF(G56="","",G56*N56*(1-O56)),"") -> 2700
A57: V2 | B57: ⚠️ ESCRITORIO con pata despuntada y cajón (PENDIENTE DIMENSIONAR) | E57: — | H57: =IFERROR(IF(B57="","",(C57/100)*(D57/100)),"") -> 0 | I57: =IFERROR(IF(B57="","",_xlfn.LET(_xlpm.tamano,IF(H57<=0.5,"CHICO",IF(H57<=1,"MEDIANO","GRANDE")),_xlpm.clave,B57&"|"&_xlpm.tamano,_xlpm.fila,MATCH(_xlpm.clave,COSTOS_M2!$H$5:$H$67,0),_xlpm.mat_m2,INDEX(IF(F57="HUANACAXTLE",COSTOS_M2!$D$5:$D$67,IF(F57="ENCINO",COSTOS_M2!$E$5:$E$67,COSTOS_M2!$F$5:$F$67)),_xlpm.fila),_xlpm.cons_m2,INDEX(COSTOS_M2!$G$5:$G$67,_xlpm.fila),_xlpm.prof_factor,IF(AND(E57<>"—",E57<>"",ISNUMBER(E57)),POWER(E57/40,1.8),1),_xlpm.total_m2,(_xlpm.mat_m2+_xlpm.cons_m2)*H57*_xlpm.prof_factor*IF(C57>70,COSTOS_M2!$B$70,1)*IF(D57>244,COSTOS_M2!$B$71,1),_xlpm.total_m2)),"") | J57: =IFERROR(IF(B57="","",INDEX(MANO_DE_OBRA!$P$10:$P$72,MATCH(B57&"|"&IF(H57<=0.5,"CHICO",IF(H57<=1,"MEDIANO","GRANDE")),MANO_DE_OBRA!$Q$10:$Q$72,0))),"") | K57: =IFERROR(IF(B57="","",_xlfn.LET(_xlpm.clave_prof,B57&"|"&E57,_xlpm.clave_todas,B57&"|TODAS",_xlpm.herr_prof,SUMIFS(HERRAJES!$H$5:$H$36,HERRAJES!$J$5:$J$36,_xlpm.clave_prof),_xlpm.herr_todas,SUMIFS(HERRAJES!$H$5:$H$36,HERRAJES!$J$5:$J$36,_xlpm.clave_todas),IF(_xlpm.herr_prof>0,_xlpm.herr_prof,_xlpm.herr_todas))),"") -> 0 | L57: =IFERROR(IF(B57="","",IF(I57="",0,I57)+IF(J57="",0,J57)+IF(K57="",0,K57)),"") -> 0 | M57: =IFERROR(IF(L57="","",L57*$D$8),"") -> 0 | N57: =IFERROR(IF(M57="","",CEILING(M57,50)),"") -> 0 | P57: =IFERROR(IF(G57="","",G57*N57*(1-O57)),"")
A58: V2 | B58: ⚠️ 3 PAREDES con espejo y moldura (PENDIENTE DIMENSIONAR) | E58: — | H58: =IFERROR(IF(B58="","",(C58/100)*(D58/100)),"") -> 0 | I58: =IFERROR(IF(B58="","",_xlfn.LET(_xlpm.tamano,IF(H58<=0.5,"CHICO",IF(H58<=1,"MEDIANO","GRANDE")),_xlpm.clave,B58&"|"&_xlpm.tamano,_xlpm.fila,MATCH(_xlpm.clave,COSTOS_M2!$H$5:$H$67,0),_xlpm.mat_m2,INDEX(IF(F58="HUANACAXTLE",COSTOS_M2!$D$5:$D$67,IF(F58="ENCINO",COSTOS_M2!$E$5:$E$67,COSTOS_M2!$F$5:$F$67)),_xlpm.fila),_xlpm.cons_m2,INDEX(COSTOS_M2!$G$5:$G$67,_xlpm.fila),_xlpm.prof_factor,IF(AND(E58<>"—",E58<>"",ISNUMBER(E58)),POWER(E58/40,1.8),1),_xlpm.total_m2,(_xlpm.mat_m2+_xlpm.cons_m2)*H58*_xlpm.prof_factor*IF(C58>70,COSTOS_M2!$B$70,1)*IF(D58>244,COSTOS_M2!$B$71,1),_xlpm.total_m2)),"") | J58: =IFERROR(IF(B58="","",INDEX(MANO_DE_OBRA!$P$10:$P$72,MATCH(B58&"|"&IF(H58<=0.5,"CHICO",IF(H58<=1,"MEDIANO","GRANDE")),MANO_DE_OBRA!$Q$10:$Q$72,0))),"") | K58: =IFERROR(IF(B58="","",_xlfn.LET(_xlpm.clave_prof,B58&"|"&E58,_xlpm.clave_todas,B58&"|TODAS",_xlpm.herr_prof,SUMIFS(HERRAJES!$H$5:$H$36,HERRAJES!$J$5:$J$36,_xlpm.clave_prof),_xlpm.herr_todas,SUMIFS(HERRAJES!$H$5:$H$36,HERRAJES!$J$5:$J$36,_xlpm.clave_todas),IF(_xlpm.herr_prof>0,_xlpm.herr_prof,_xlpm.herr_todas))),"") -> 0 | L58: =IFERROR(IF(B58="","",IF(I58="",0,I58)+IF(J58="",0,J58)+IF(K58="",0,K58)),"") -> 0 | M58: =IFERROR(IF(L58="","",L58*$D$8),"") -> 0 | N58: =IFERROR(IF(M58="","",CEILING(M58,50)),"") -> 0 | P58: =IFERROR(IF(G58="","",G58*N58*(1-O58)),"")
B59: CLOSETS INVITADOS | H59: =IFERROR(IF(B59="","",(C59/100)*(D59/100)),"") -> 0
B60: PISO CON ZOCLO | C60: 85 | D60: 200 | E60: — | F60: NOGAL | G60: 1 | H60: =IFERROR(IF(B60="","",(C60/100)*(D60/100)),"") -> 1.7 | I60: =IFERROR(IF(B60="","",_xlfn.LET(_xlpm.tamano,IF(H60<=0.5,"CHICO",IF(H60<=1,"MEDIANO","GRANDE")),_xlpm.clave,B60&"|"&_xlpm.tamano,_xlpm.fila,MATCH(_xlpm.clave,COSTOS_M2!$H$5:$H$67,0),_xlpm.mat_m2,INDEX(IF(F60="HUANACAXTLE",COSTOS_M2!$D$5:$D$67,IF(F60="ENCINO",COSTOS_M2!$E$5:$E$67,COSTOS_M2!$F$5:$F$67)),_xlpm.fila),_xlpm.cons_m2,INDEX(COSTOS_M2!$G$5:$G$67,_xlpm.fila),_xlpm.prof_factor,IF(AND(E60<>"—",E60<>"",ISNUMBER(E60)),POWER(E60/40,1.8),1),_xlpm.total_m2,(_xlpm.mat_m2+_xlpm.cons_m2)*H60*_xlpm.prof_factor*IF(C60>70,COSTOS_M2!$B$70,1)*IF(D60>244,COSTOS_M2!$B$71,1),_xlpm.total_m2)),"") -> 1487.33 | J60: =IFERROR(IF(B60="","",INDEX(MANO_DE_OBRA!$P$10:$P$72,MATCH(B60&"|"&IF(H60<=0.5,"CHICO",IF(H60<=1,"MEDIANO","GRANDE")),MANO_DE_OBRA!$Q$10:$Q$72,0))),"") -> 614.34549 | K60: =IFERROR(IF(B60="","",_xlfn.LET(_xlpm.clave_prof,B60&"|"&E60,_xlpm.clave_todas,B60&"|TODAS",_xlpm.herr_prof,SUMIFS(HERRAJES!$H$5:$H$36,HERRAJES!$J$5:$J$36,_xlpm.clave_prof),_xlpm.herr_todas,SUMIFS(HERRAJES!$H$5:$H$36,HERRAJES!$J$5:$J$36,_xlpm.clave_todas),IF(_xlpm.herr_prof>0,_xlpm.herr_prof,_xlpm.herr_todas))),"") -> 0 | L60: =IFERROR(IF(B60="","",IF(I60="",0,I60)+IF(J60="",0,J60)+IF(K60="",0,K60)),"") -> 2101.6755 | M60: =IFERROR(IF(L60="","",L60*$D$8),"") -> 2627.0944 | N60: =IFERROR(IF(M60="","",CEILING(M60,50)),"") -> 2650 | O60: 0 | P60: =IFERROR(IF(G60="","",G60*N60*(1-O60)),"") -> 2650
B61: CIELO | C61: 85 | D61: 200 | E61: — | F61: NOGAL | G61: 1 | H61: =IFERROR(IF(B61="","",(C61/100)*(D61/100)),"") -> 1.7 | I61: =IFERROR(IF(B61="","",_xlfn.LET(_xlpm.tamano,IF(H61<=0.5,"CHICO",IF(H61<=1,"MEDIANO","GRANDE")),_xlpm.clave,B61&"|"&_xlpm.tamano,_xlpm.fila,MATCH(_xlpm.clave,COSTOS_M2!$H$5:$H$67,0),_xlpm.mat_m2,INDEX(IF(F61="HUANACAXTLE",COSTOS_M2!$D$5:$D$67,IF(F61="ENCINO",COSTOS_M2!$E$5:$E$67,COSTOS_M2!$F$5:$F$67)),_xlpm.fila),_xlpm.cons_m2,INDEX(COSTOS_M2!$G$5:$G$67,_xlpm.fila),_xlpm.prof_factor,IF(AND(E61<>"—",E61<>"",ISNUMBER(E61)),POWER(E61/40,1.8),1),_xlpm.total_m2,(_xlpm.mat_m2+_xlpm.cons_m2)*H61*_xlpm.prof_factor*IF(C61>70,COSTOS_M2!$B$70,1)*IF(D61>244,COSTOS_M2!$B$71,1),_xlpm.total_m2)),"") -> 1785.68 | J61: =IFERROR(IF(B61="","",INDEX(MANO_DE_OBRA!$P$10:$P$72,MATCH(B61&"|"&IF(H61<=0.5,"CHICO",IF(H61<=1,"MEDIANO","GRANDE")),MANO_DE_OBRA!$Q$10:$Q$72,0))),"") -> 762.95904 | K61: =IFERROR(IF(B61="","",_xlfn.LET(_xlpm.clave_prof,B61&"|"&E61,_xlpm.clave_todas,B61&"|TODAS",_xlpm.herr_prof,SUMIFS(HERRAJES!$H$5:$H$36,HERRAJES!$J$5:$J$36,_xlpm.clave_prof),_xlpm.herr_todas,SUMIFS(HERRAJES!$H$5:$H$36,HERRAJES!$J$5:$J$36,_xlpm.clave_todas),IF(_xlpm.herr_prof>0,_xlpm.herr_prof,_xlpm.herr_todas))),"") -> 0 | L61: =IFERROR(IF(B61="","",IF(I61="",0,I61)+IF(J61="",0,J61)+IF(K61="",0,K61)),"") -> 2548.639 | M61: =IFERROR(IF(L61="","",L61*$D$8),"") -> 3185.7988 | N61: =IFERROR(IF(M61="","",CEILING(M61,50)),"") -> 3200 | O61: 0 | P61: =IFERROR(IF(G61="","",G61*N61*(1-O61)),"") -> 3200
B62: PARAL 1 VISTA | C62: 85 | D62: 295 | E62: — | F62: NOGAL | G62: 2 | H62: =IFERROR(IF(B62="","",(C62/100)*(D62/100)),"") -> 2.5075 | I62: =IFERROR(IF(B62="","",_xlfn.LET(_xlpm.tamano,IF(H62<=0.5,"CHICO",IF(H62<=1,"MEDIANO","GRANDE")),_xlpm.clave,B62&"|"&_xlpm.tamano,_xlpm.fila,MATCH(_xlpm.clave,COSTOS_M2!$H$5:$H$67,0),_xlpm.mat_m2,INDEX(IF(F62="HUANACAXTLE",COSTOS_M2!$D$5:$D$67,IF(F62="ENCINO",COSTOS_M2!$E$5:$E$67,COSTOS_M2!$F$5:$F$67)),_xlpm.fila),_xlpm.cons_m2,INDEX(COSTOS_M2!$G$5:$G$67,_xlpm.fila),_xlpm.prof_factor,IF(AND(E62<>"—",E62<>"",ISNUMBER(E62)),POWER(E62/40,1.8),1),_xlpm.total_m2,(_xlpm.mat_m2+_xlpm.cons_m2)*H62*_xlpm.prof_factor*IF(C62>70,COSTOS_M2!$B$70,1)*IF(D62>244,COSTOS_M2!$B$71,1),_xlpm.total_m2)),"") -> 2919.7581 | J62: =IFERROR(IF(B62="","",INDEX(MANO_DE_OBRA!$P$10:$P$72,MATCH(B62&"|"&IF(H62<=0.5,"CHICO",IF(H62<=1,"MEDIANO","GRANDE")),MANO_DE_OBRA!$Q$10:$Q$72,0))),"") -> 587.22913 | K62: =IFERROR(IF(B62="","",_xlfn.LET(_xlpm.clave_prof,B62&"|"&E62,_xlpm.clave_todas,B62&"|TODAS",_xlpm.herr_prof,SUMIFS(HERRAJES!$H$5:$H$36,HERRAJES!$J$5:$J$36,_xlpm.clave_prof),_xlpm.herr_todas,SUMIFS(HERRAJES!$H$5:$H$36,HERRAJES!$J$5:$J$36,_xlpm.clave_todas),IF(_xlpm.herr_prof>0,_xlpm.herr_prof,_xlpm.herr_todas))),"") -> 0 | L62: =IFERROR(IF(B62="","",IF(I62="",0,I62)+IF(J62="",0,J62)+IF(K62="",0,K62)),"") -> 3506.9872 | M62: =IFERROR(IF(L62="","",L62*$D$8),"") -> 4383.734 | N62: =IFERROR(IF(M62="","",CEILING(M62,50)),"") -> 4400 | O62: 0 | P62: =IFERROR(IF(G62="","",G62*N62*(1-O62)),"") -> 8800
B63: PARAL DELGADO 2V | C63: 85 | D63: 295 | E63: — | F63: NOGAL | G63: 1 | H63: =IFERROR(IF(B63="","",(C63/100)*(D63/100)),"") -> 2.5075 | I63: =IFERROR(IF(B63="","",_xlfn.LET(_xlpm.tamano,IF(H63<=0.5,"CHICO",IF(H63<=1,"MEDIANO","GRANDE")),_xlpm.clave,B63&"|"&_xlpm.tamano,_xlpm.fila,MATCH(_xlpm.clave,COSTOS_M2!$H$5:$H$67,0),_xlpm.mat_m2,INDEX(IF(F63="HUANACAXTLE",COSTOS_M2!$D$5:$D$67,IF(F63="ENCINO",COSTOS_M2!$E$5:$E$67,COSTOS_M2!$F$5:$F$67)),_xlpm.fila),_xlpm.cons_m2,INDEX(COSTOS_M2!$G$5:$G$67,_xlpm.fila),_xlpm.prof_factor,IF(AND(E63<>"—",E63<>"",ISNUMBER(E63)),POWER(E63/40,1.8),1),_xlpm.total_m2,(_xlpm.mat_m2+_xlpm.cons_m2)*H63*_xlpm.prof_factor*IF(C63>70,COSTOS_M2!$B$70,1)*IF(D63>244,COSTOS_M2!$B$71,1),_xlpm.total_m2)),"") -> 3157.0679 | J63: =IFERROR(IF(B63="","",INDEX(MANO_DE_OBRA!$P$10:$P$72,MATCH(B63&"|"&IF(H63<=0.5,"CHICO",IF(H63<=1,"MEDIANO","GRANDE")),MANO_DE_OBRA!$Q$10:$Q$72,0))),"") -> 725.196 | K63: =IFERROR(IF(B63="","",_xlfn.LET(_xlpm.clave_prof,B63&"|"&E63,_xlpm.clave_todas,B63&"|TODAS",_xlpm.herr_prof,SUMIFS(HERRAJES!$H$5:$H$36,HERRAJES!$J$5:$J$36,_xlpm.clave_prof),_xlpm.herr_todas,SUMIFS(HERRAJES!$H$5:$H$36,HERRAJES!$J$5:$J$36,_xlpm.clave_todas),IF(_xlpm.herr_prof>0,_xlpm.herr_prof,_xlpm.herr_todas))),"") -> 0 | L63: =IFERROR(IF(B63="","",IF(I63="",0,I63)+IF(J63="",0,J63)+IF(K63="",0,K63)),"") -> 3882.2639 | M63: =IFERROR(IF(L63="","",L63*$D$8),"") -> 4852.8298 | N63: =IFERROR(IF(M63="","",CEILING(M63,50)),"") -> 4900 | O63: 0 | P63: =IFERROR(IF(G63="","",G63*N63*(1-O63)),"") -> 4900
B64: PARAL DELGADO 2V | C64: 85 | D64: 157 | E64: — | F64: NOGAL | G64: 1 | H64: =IFERROR(IF(B64="","",(C64/100)*(D64/100)),"") -> 1.3345 | I64: =IFERROR(IF(B64="","",_xlfn.LET(_xlpm.tamano,IF(H64<=0.5,"CHICO",IF(H64<=1,"MEDIANO","GRANDE")),_xlpm.clave,B64&"|"&_xlpm.tamano,_xlpm.fila,MATCH(_xlpm.clave,COSTOS_M2!$H$5:$H$67,0),_xlpm.mat_m2,INDEX(IF(F64="HUANACAXTLE",COSTOS_M2!$D$5:$D$67,IF(F64="ENCINO",COSTOS_M2!$E$5:$E$67,COSTOS_M2!$F$5:$F$67)),_xlpm.fila),_xlpm.cons_m2,INDEX(COSTOS_M2!$G$5:$G$67,_xlpm.fila),_xlpm.prof_factor,IF(AND(E64<>"—",E64<>"",ISNUMBER(E64)),POWER(E64/40,1.8),1),_xlpm.total_m2,(_xlpm.mat_m2+_xlpm.cons_m2)*H64*_xlpm.prof_factor*IF(C64>70,COSTOS_M2!$B$70,1)*IF(D64>244,COSTOS_M2!$B$71,1),_xlpm.total_m2)),"") -> 1292.4633 | J64: =IFERROR(IF(B64="","",INDEX(MANO_DE_OBRA!$P$10:$P$72,MATCH(B64&"|"&IF(H64<=0.5,"CHICO",IF(H64<=1,"MEDIANO","GRANDE")),MANO_DE_OBRA!$Q$10:$Q$72,0))),"") -> 725.196 | K64: =IFERROR(IF(B64="","",_xlfn.LET(_xlpm.clave_prof,B64&"|"&E64,_xlpm.clave_todas,B64&"|TODAS",_xlpm.herr_prof,SUMIFS(HERRAJES!$H$5:$H$36,HERRAJES!$J$5:$J$36,_xlpm.clave_prof),_xlpm.herr_todas,SUMIFS(HERRAJES!$H$5:$H$36,HERRAJES!$J$5:$J$36,_xlpm.clave_todas),IF(_xlpm.herr_prof>0,_xlpm.herr_prof,_xlpm.herr_todas))),"") -> 0 | L64: =IFERROR(IF(B64="","",IF(I64="",0,I64)+IF(J64="",0,J64)+IF(K64="",0,K64)),"") -> 2017.6593 | M64: =IFERROR(IF(L64="","",L64*$D$8),"") -> 2522.0741 | N64: =IFERROR(IF(M64="","",CEILING(M64,50)),"") -> 2550 | O64: 0 | P64: =IFERROR(IF(G64="","",G64*N64*(1-O64)),"") -> 2550
B65: ZAPATERA EXTRAÍBLE | C65: 100 | D65: 85 | E65: — | F65: NOGAL | G65: 2 | H65: =IFERROR(IF(B65="","",(C65/100)*(D65/100)),"") -> 0.85 | I65: =IFERROR(IF(B65="","",_xlfn.LET(_xlpm.tamano,IF(H65<=0.5,"CHICO",IF(H65<=1,"MEDIANO","GRANDE")),_xlpm.clave,B65&"|"&_xlpm.tamano,_xlpm.fila,MATCH(_xlpm.clave,COSTOS_M2!$H$5:$H$67,0),_xlpm.mat_m2,INDEX(IF(F65="HUANACAXTLE",COSTOS_M2!$D$5:$D$67,IF(F65="ENCINO",COSTOS_M2!$E$5:$E$67,COSTOS_M2!$F$5:$F$67)),_xlpm.fila),_xlpm.cons_m2,INDEX(COSTOS_M2!$G$5:$G$67,_xlpm.fila),_xlpm.prof_factor,IF(AND(E65<>"—",E65<>"",ISNUMBER(E65)),POWER(E65/40,1.8),1),_xlpm.total_m2,(_xlpm.mat_m2+_xlpm.cons_m2)*H65*_xlpm.prof_factor*IF(C65>70,COSTOS_M2!$B$70,1)*IF(D65>244,COSTOS_M2!$B$71,1),_xlpm.total_m2)),"") -> 643.11 | J65: =IFERROR(IF(B65="","",INDEX(MANO_DE_OBRA!$P$10:$P$72,MATCH(B65&"|"&IF(H65<=0.5,"CHICO",IF(H65<=1,"MEDIANO","GRANDE")),MANO_DE_OBRA!$Q$10:$Q$72,0))),"") -> 410.25956 | K65: =IFERROR(IF(B65="","",_xlfn.LET(_xlpm.clave_prof,B65&"|"&E65,_xlpm.clave_todas,B65&"|TODAS",_xlpm.herr_prof,SUMIFS(HERRAJES!$H$5:$H$36,HERRAJES!$J$5:$J$36,_xlpm.clave_prof),_xlpm.herr_todas,SUMIFS(HERRAJES!$H$5:$H$36,HERRAJES!$J$5:$J$36,_xlpm.clave_todas),IF(_xlpm.herr_prof>0,_xlpm.herr_prof,_xlpm.herr_todas))),"") -> 0 | L65: =IFERROR(IF(B65="","",IF(I65="",0,I65)+IF(J65="",0,J65)+IF(K65="",0,K65)),"") -> 1053.3696 | M65: =IFERROR(IF(L65="","",L65*$D$8),"") -> 1316.712 | N65: =IFERROR(IF(M65="","",CEILING(M65,50)),"") -> 1350 | O65: 0 | P65: =IFERROR(IF(G65="","",G65*N65*(1-O65)),"") -> 2700
B66: ENTREPAÑO DELGADO | C66: 85 | D66: 100 | E66: — | F66: NOGAL | G66: 3 | H66: =IFERROR(IF(B66="","",(C66/100)*(D66/100)),"") -> 0.85 | I66: =IFERROR(IF(B66="","",_xlfn.LET(_xlpm.tamano,IF(H66<=0.5,"CHICO",IF(H66<=1,"MEDIANO","GRANDE")),_xlpm.clave,B66&"|"&_xlpm.tamano,_xlpm.fila,MATCH(_xlpm.clave,COSTOS_M2!$H$5:$H$67,0),_xlpm.mat_m2,INDEX(IF(F66="HUANACAXTLE",COSTOS_M2!$D$5:$D$67,IF(F66="ENCINO",COSTOS_M2!$E$5:$E$67,COSTOS_M2!$F$5:$F$67)),_xlpm.fila),_xlpm.cons_m2,INDEX(COSTOS_M2!$G$5:$G$67,_xlpm.fila),_xlpm.prof_factor,IF(AND(E66<>"—",E66<>"",ISNUMBER(E66)),POWER(E66/40,1.8),1),_xlpm.total_m2,(_xlpm.mat_m2+_xlpm.cons_m2)*H66*_xlpm.prof_factor*IF(C66>70,COSTOS_M2!$B$70,1)*IF(D66>244,COSTOS_M2!$B$71,1),_xlpm.total_m2)),"") -> 867.425 | J66: =IFERROR(IF(B66="","",INDEX(MANO_DE_OBRA!$P$10:$P$72,MATCH(B66&"|"&IF(H66<=0.5,"CHICO",IF(H66<=1,"MEDIANO","GRANDE")),MANO_DE_OBRA!$Q$10:$Q$72,0))),"") -> 400.5588 | K66: =IFERROR(IF(B66="","",_xlfn.LET(_xlpm.clave_prof,B66&"|"&E66,_xlpm.clave_todas,B66&"|TODAS",_xlpm.herr_prof,SUMIFS(HERRAJES!$H$5:$H$36,HERRAJES!$J$5:$J$36,_xlpm.clave_prof),_xlpm.herr_todas,SUMIFS(HERRAJES!$H$5:$H$36,HERRAJES!$J$5:$J$36,_xlpm.clave_todas),IF(_xlpm.herr_prof>0,_xlpm.herr_prof,_xlpm.herr_todas))),"") -> 0 | L66: =IFERROR(IF(B66="","",IF(I66="",0,I66)+IF(J66="",0,J66)+IF(K66="",0,K66)),"") -> 1267.9838 | M66: =IFERROR(IF(L66="","",L66*$D$8),"") -> 1584.9797 | N66: =IFERROR(IF(M66="","",CEILING(M66,50)),"") -> 1600 | O66: 0 | P66: =IFERROR(IF(G66="","",G66*N66*(1-O66)),"") -> 4800
B67: ENTREPAÑO DELGADO | C67: 85 | D67: 50 | E67: — | F67: NOGAL | G67: 6 | H67: =IFERROR(IF(B67="","",(C67/100)*(D67/100)),"") -> 0.425 | I67: =IFERROR(IF(B67="","",_xlfn.LET(_xlpm.tamano,IF(H67<=0.5,"CHICO",IF(H67<=1,"MEDIANO","GRANDE")),_xlpm.clave,B67&"|"&_xlpm.tamano,_xlpm.fila,MATCH(_xlpm.clave,COSTOS_M2!$H$5:$H$67,0),_xlpm.mat_m2,INDEX(IF(F67="HUANACAXTLE",COSTOS_M2!$D$5:$D$67,IF(F67="ENCINO",COSTOS_M2!$E$5:$E$67,COSTOS_M2!$F$5:$F$67)),_xlpm.fila),_xlpm.cons_m2,INDEX(COSTOS_M2!$G$5:$G$67,_xlpm.fila),_xlpm.prof_factor,IF(AND(E67<>"—",E67<>"",ISNUMBER(E67)),POWER(E67/40,1.8),1),_xlpm.total_m2,(_xlpm.mat_m2+_xlpm.cons_m2)*H67*_xlpm.prof_factor*IF(C67>70,COSTOS_M2!$B$70,1)*IF(D67>244,COSTOS_M2!$B$71,1),_xlpm.total_m2)),"") -> 461.3375 | J67: =IFERROR(IF(B67="","",INDEX(MANO_DE_OBRA!$P$10:$P$72,MATCH(B67&"|"&IF(H67<=0.5,"CHICO",IF(H67<=1,"MEDIANO","GRANDE")),MANO_DE_OBRA!$Q$10:$Q$72,0))),"") -> 265.8015 | K67: =IFERROR(IF(B67="","",_xlfn.LET(_xlpm.clave_prof,B67&"|"&E67,_xlpm.clave_todas,B67&"|TODAS",_xlpm.herr_prof,SUMIFS(HERRAJES!$H$5:$H$36,HERRAJES!$J$5:$J$36,_xlpm.clave_prof),_xlpm.herr_todas,SUMIFS(HERRAJES!$H$5:$H$36,HERRAJES!$J$5:$J$36,_xlpm.clave_todas),IF(_xlpm.herr_prof>0,_xlpm.herr_prof,_xlpm.herr_todas))),"") -> 0 | L67: =IFERROR(IF(B67="","",IF(I67="",0,I67)+IF(J67="",0,J67)+IF(K67="",0,K67)),"") -> 727.139 | M67: =IFERROR(IF(L67="","",L67*$D$8),"") -> 908.92375 | N67: =IFERROR(IF(M67="","",CEILING(M67,50)),"") -> 950 | O67: 0 | P67: =IFERROR(IF(G67="","",G67*N67*(1-O67)),"") -> 5700
B68: TUBO COLGAR | C68: ESPECIAL | D68: 100 | E68: — | F68: NOGAL | G68: 2 | H68: =IFERROR(IF(B68="","",(C68/100)*(D68/100)),"") | I68: =IFERROR(IF(B68="","",_xlfn.LET(_xlpm.tamano,IF(H68<=0.5,"CHICO",IF(H68<=1,"MEDIANO","GRANDE")),_xlpm.clave,B68&"|"&_xlpm.tamano,_xlpm.fila,MATCH(_xlpm.clave,COSTOS_M2!$H$5:$H$67,0),_xlpm.mat_m2,INDEX(IF(F68="HUANACAXTLE",COSTOS_M2!$D$5:$D$67,IF(F68="ENCINO",COSTOS_M2!$E$5:$E$67,COSTOS_M2!$F$5:$F$67)),_xlpm.fila),_xlpm.cons_m2,INDEX(COSTOS_M2!$G$5:$G$67,_xlpm.fila),_xlpm.prof_factor,IF(AND(E68<>"—",E68<>"",ISNUMBER(E68)),POWER(E68/40,1.8),1),_xlpm.total_m2,(_xlpm.mat_m2+_xlpm.cons_m2)*H68*_xlpm.prof_factor*IF(C68>70,COSTOS_M2!$B$70,1)*IF(D68>244,COSTOS_M2!$B$71,1),_xlpm.total_m2)),"") | J68: =IFERROR(IF(B68="","",INDEX(MANO_DE_OBRA!$P$10:$P$72,MATCH(B68&"|"&IF(H68<=0.5,"CHICO",IF(H68<=1,"MEDIANO","GRANDE")),MANO_DE_OBRA!$Q$10:$Q$72,0))),"") -> 25.593 | K68: =IFERROR(IF(B68="","",_xlfn.LET(_xlpm.clave_prof,B68&"|"&E68,_xlpm.clave_todas,B68&"|TODAS",_xlpm.herr_prof,SUMIFS(HERRAJES!$H$5:$H$36,HERRAJES!$J$5:$J$36,_xlpm.clave_prof),_xlpm.herr_todas,SUMIFS(HERRAJES!$H$5:$H$36,HERRAJES!$J$5:$J$36,_xlpm.clave_todas),IF(_xlpm.herr_prof>0,_xlpm.herr_prof,_xlpm.herr_todas))),"") -> 2.74 | L68: =IFERROR(IF(B68="","",IF(I68="",0,I68)+IF(J68="",0,J68)+IF(K68="",0,K68)),"") -> 28.333 | M68: =IFERROR(IF(L68="","",L68*$D$8),"") -> 35.41625 | N68: =IFERROR(IF(M68="","",CEILING(M68,50)),"") -> 50 | O68: 0 | P68: =IFERROR(IF(G68="","",G68*N68*(1-O68)),"") -> 100
B69: CAJÓN | C69: 100 | D69: 22 | E69: 85 | F69: NOGAL | G69: 4 | H69: =IFERROR(IF(B69="","",(C69/100)*(D69/100)),"") -> 0.22 | I69: =IFERROR(IF(B69="","",_xlfn.LET(_xlpm.tamano,IF(H69<=0.5,"CHICO",IF(H69<=1,"MEDIANO","GRANDE")),_xlpm.clave,B69&"|"&_xlpm.tamano,_xlpm.fila,MATCH(_xlpm.clave,COSTOS_M2!$H$5:$H$67,0),_xlpm.mat_m2,INDEX(IF(F69="HUANACAXTLE",COSTOS_M2!$D$5:$D$67,IF(F69="ENCINO",COSTOS_M2!$E$5:$E$67,COSTOS_M2!$F$5:$F$67)),_xlpm.fila),_xlpm.cons_m2,INDEX(COSTOS_M2!$G$5:$G$67,_xlpm.fila),_xlpm.prof_factor,IF(AND(E69<>"—",E69<>"",ISNUMBER(E69)),POWER(E69/40,1.8),1),_xlpm.total_m2,(_xlpm.mat_m2+_xlpm.cons_m2)*H69*_xlpm.prof_factor*IF(C69>70,COSTOS_M2!$B$70,1)*IF(D69>244,COSTOS_M2!$B$71,1),_xlpm.total_m2)),"") -> 1477.2832 | J69: =IFERROR(IF(B69="","",INDEX(MANO_DE_OBRA!$P$10:$P$72,MATCH(B69&"|"&IF(H69<=0.5,"CHICO",IF(H69<=1,"MEDIANO","GRANDE")),MANO_DE_OBRA!$Q$10:$Q$72,0))),"") -> 434.36213 | K69: =IFERROR(IF(B69="","",_xlfn.LET(_xlpm.clave_prof,B69&"|"&E69,_xlpm.clave_todas,B69&"|TODAS",_xlpm.herr_prof,SUMIFS(HERRAJES!$H$5:$H$36,HERRAJES!$J$5:$J$36,_xlpm.clave_prof),_xlpm.herr_todas,SUMIFS(HERRAJES!$H$5:$H$36,HERRAJES!$J$5:$J$36,_xlpm.clave_todas),IF(_xlpm.herr_prof>0,_xlpm.herr_prof,_xlpm.herr_todas))),"") -> 0 | L69: =IFERROR(IF(B69="","",IF(I69="",0,I69)+IF(J69="",0,J69)+IF(K69="",0,K69)),"") -> 1911.6453 | M69: =IFERROR(IF(L69="","",L69*$D$8),"") -> 2389.5567 | N69: =IFERROR(IF(M69="","",CEILING(M69,50)),"") -> 2400 | O69: 0 | P69: =IFERROR(IF(G69="","",G69*N69*(1-O69)),"") -> 9600
B70: ⚠️ 8 JALADERAS DE METAL (PENDIENTE - cotizar aparte) | E70: — | H70: =IFERROR(IF(B70="","",(C70/100)*(D70/100)),"") -> 0 | I70: =IFERROR(IF(B70="","",_xlfn.LET(_xlpm.tamano,IF(H70<=0.5,"CHICO",IF(H70<=1,"MEDIANO","GRANDE")),_xlpm.clave,B70&"|"&_xlpm.tamano,_xlpm.fila,MATCH(_xlpm.clave,COSTOS_M2!$H$5:$H$67,0),_xlpm.mat_m2,INDEX(IF(F70="HUANACAXTLE",COSTOS_M2!$D$5:$D$67,IF(F70="ENCINO",COSTOS_M2!$E$5:$E$67,COSTOS_M2!$F$5:$F$67)),_xlpm.fila),_xlpm.cons_m2,INDEX(COSTOS_M2!$G$5:$G$67,_xlpm.fila),_xlpm.prof_factor,IF(AND(E70<>"—",E70<>"",ISNUMBER(E70)),POWER(E70/40,1.8),1),_xlpm.total_m2,(_xlpm.mat_m2+_xlpm.cons_m2)*H70*_xlpm.prof_factor*IF(C70>70,COSTOS_M2!$B$70,1)*IF(D70>244,COSTOS_M2!$B$71,1),_xlpm.total_m2)),"") | J70: =IFERROR(IF(B70="","",INDEX(MANO_DE_OBRA!$P$10:$P$72,MATCH(B70&"|"&IF(H70<=0.5,"CHICO",IF(H70<=1,"MEDIANO","GRANDE")),MANO_DE_OBRA!$Q$10:$Q$72,0))),"") | K70: =IFERROR(IF(B70="","",_xlfn.LET(_xlpm.clave_prof,B70&"|"&E70,_xlpm.clave_todas,B70&"|TODAS",_xlpm.herr_prof,SUMIFS(HERRAJES!$H$5:$H$36,HERRAJES!$J$5:$J$36,_xlpm.clave_prof),_xlpm.herr_todas,SUMIFS(HERRAJES!$H$5:$H$36,HERRAJES!$J$5:$J$36,_xlpm.clave_todas),IF(_xlpm.herr_prof>0,_xlpm.herr_prof,_xlpm.herr_todas))),"") -> 0 | L70: =IFERROR(IF(B70="","",IF(I70="",0,I70)+IF(J70="",0,J70)+IF(K70="",0,K70)),"") -> 0 | M70: =IFERROR(IF(L70="","",L70*$D$8),"") -> 0 | N70: =IFERROR(IF(M70="","",CEILING(M70,50)),"") -> 0 | O70: 0 | P70: =IFERROR(IF(G70="","",G70*N70*(1-O70)),"")
B71: FONDO MADERA | C71: 202 | D71: 305 | E71: — | F71: NOGAL | G71: 1 | H71: =IFERROR(IF(B71="","",(C71/100)*(D71/100)),"") -> 6.161 | I71: =IFERROR(IF(B71="","",_xlfn.LET(_xlpm.tamano,IF(H71<=0.5,"CHICO",IF(H71<=1,"MEDIANO","GRANDE")),_xlpm.clave,B71&"|"&_xlpm.tamano,_xlpm.fila,MATCH(_xlpm.clave,COSTOS_M2!$H$5:$H$67,0),_xlpm.mat_m2,INDEX(IF(F71="HUANACAXTLE",COSTOS_M2!$D$5:$D$67,IF(F71="ENCINO",COSTOS_M2!$E$5:$E$67,COSTOS_M2!$F$5:$F$67)),_xlpm.fila),_xlpm.cons_m2,INDEX(COSTOS_M2!$G$5:$G$67,_xlpm.fila),_xlpm.prof_factor,IF(AND(E71<>"—",E71<>"",ISNUMBER(E71)),POWER(E71/40,1.8),1),_xlpm.total_m2,(_xlpm.mat_m2+_xlpm.cons_m2)*H71*_xlpm.prof_factor*IF(C71>70,COSTOS_M2!$B$70,1)*IF(D71>244,COSTOS_M2!$B$71,1),_xlpm.total_m2)),"") -> 2446.8411 | J71: =IFERROR(IF(B71="","",INDEX(MANO_DE_OBRA!$P$10:$P$72,MATCH(B71&"|"&IF(H71<=0.5,"CHICO",IF(H71<=1,"MEDIANO","GRANDE")),MANO_DE_OBRA!$Q$10:$Q$72,0))),"") -> 295.7955 | K71: =IFERROR(IF(B71="","",_xlfn.LET(_xlpm.clave_prof,B71&"|"&E71,_xlpm.clave_todas,B71&"|TODAS",_xlpm.herr_prof,SUMIFS(HERRAJES!$H$5:$H$36,HERRAJES!$J$5:$J$36,_xlpm.clave_prof),_xlpm.herr_todas,SUMIFS(HERRAJES!$H$5:$H$36,HERRAJES!$J$5:$J$36,_xlpm.clave_todas),IF(_xlpm.herr_prof>0,_xlpm.herr_prof,_xlpm.herr_todas))),"") -> 0 | L71: =IFERROR(IF(B71="","",IF(I71="",0,I71)+IF(J71="",0,J71)+IF(K71="",0,K71)),"") -> 2742.6366 | M71: =IFERROR(IF(L71="","",L71*$D$8),"") -> 3428.2958 | N71: =IFERROR(IF(M71="","",CEILING(M71,50)),"") -> 3450 | O71: 0 | P71: =IFERROR(IF(G71="","",G71*N71*(1-O71)),"") -> 3450
B72: PUERTA ABATIBLE | C72: 50 | D72: 305 | E72: — | F72: NOGAL | G72: 4 | H72: =IFERROR(IF(B72="","",(C72/100)*(D72/100)),"") -> 1.525 | I72: =IFERROR(IF(B72="","",_xlfn.LET(_xlpm.tamano,IF(H72<=0.5,"CHICO",IF(H72<=1,"MEDIANO","GRANDE")),_xlpm.clave,B72&"|"&_xlpm.tamano,_xlpm.fila,MATCH(_xlpm.clave,COSTOS_M2!$H$5:$H$67,0),_xlpm.mat_m2,INDEX(IF(F72="HUANACAXTLE",COSTOS_M2!$D$5:$D$67,IF(F72="ENCINO",COSTOS_M2!$E$5:$E$67,COSTOS_M2!$F$5:$F$67)),_xlpm.fila),_xlpm.cons_m2,INDEX(COSTOS_M2!$G$5:$G$67,_xlpm.fila),_xlpm.prof_factor,IF(AND(E72<>"—",E72<>"",ISNUMBER(E72)),POWER(E72/40,1.8),1),_xlpm.total_m2,(_xlpm.mat_m2+_xlpm.cons_m2)*H72*_xlpm.prof_factor*IF(C72>70,COSTOS_M2!$B$70,1)*IF(D72>244,COSTOS_M2!$B$71,1),_xlpm.total_m2)),"") -> 1595.9125 | J72: =IFERROR(IF(B72="","",INDEX(MANO_DE_OBRA!$P$10:$P$72,MATCH(B72&"|"&IF(H72<=0.5,"CHICO",IF(H72<=1,"MEDIANO","GRANDE")),MANO_DE_OBRA!$Q$10:$Q$72,0))),"") -> 810.61836 | K72: =IFERROR(IF(B72="","",_xlfn.LET(_xlpm.clave_prof,B72&"|"&E72,_xlpm.clave_todas,B72&"|TODAS",_xlpm.herr_prof,SUMIFS(HERRAJES!$H$5:$H$36,HERRAJES!$J$5:$J$36,_xlpm.clave_prof),_xlpm.herr_todas,SUMIFS(HERRAJES!$H$5:$H$36,HERRAJES!$J$5:$J$36,_xlpm.clave_todas),IF(_xlpm.herr_prof>0,_xlpm.herr_prof,_xlpm.herr_todas))),"") -> 311.4 | L72: =IFERROR(IF(B72="","",IF(I72="",0,I72)+IF(J72="",0,J72)+IF(K72="",0,K72)),"") -> 2717.9309 | M72: =IFERROR(IF(L72="","",L72*$D$8),"") -> 3397.4136 | N72: =IFERROR(IF(M72="","",CEILING(M72,50)),"") -> 3400 | O72: 0 | P72: =IFERROR(IF(G72="","",G72*N72*(1-O72)),"") -> 13600
B73: MOLDURA SENCILLA | C73: 5 | D73: 750 | E73: — | F73: NOGAL | G73: 1 | H73: =IFERROR(IF(B73="","",(C73/100)*(D73/100)),"") -> 0.375 | I73: =IFERROR(IF(B73="","",_xlfn.LET(_xlpm.tamano,IF(H73<=0.5,"CHICO",IF(H73<=1,"MEDIANO","GRANDE")),_xlpm.clave,B73&"|"&_xlpm.tamano,_xlpm.fila,MATCH(_xlpm.clave,COSTOS_M2!$H$5:$H$67,0),_xlpm.mat_m2,INDEX(IF(F73="HUANACAXTLE",COSTOS_M2!$D$5:$D$67,IF(F73="ENCINO",COSTOS_M2!$E$5:$E$67,COSTOS_M2!$F$5:$F$67)),_xlpm.fila),_xlpm.cons_m2,INDEX(COSTOS_M2!$G$5:$G$67,_xlpm.fila),_xlpm.prof_factor,IF(AND(E73<>"—",E73<>"",ISNUMBER(E73)),POWER(E73/40,1.8),1),_xlpm.total_m2,(_xlpm.mat_m2+_xlpm.cons_m2)*H73*_xlpm.prof_factor*IF(C73>70,COSTOS_M2!$B$70,1)*IF(D73>244,COSTOS_M2!$B$71,1),_xlpm.total_m2)),"") -> 2510.625 | J73: =IFERROR(IF(B73="","",INDEX(MANO_DE_OBRA!$P$10:$P$72,MATCH(B73&"|"&IF(H73<=0.5,"CHICO",IF(H73<=1,"MEDIANO","GRANDE")),MANO_DE_OBRA!$Q$10:$Q$72,0))),"") -> 356.3865 | K73: =IFERROR(IF(B73="","",_xlfn.LET(_xlpm.clave_prof,B73&"|"&E73,_xlpm.clave_todas,B73&"|TODAS",_xlpm.herr_prof,SUMIFS(HERRAJES!$H$5:$H$36,HERRAJES!$J$5:$J$36,_xlpm.clave_prof),_xlpm.herr_todas,SUMIFS(HERRAJES!$H$5:$H$36,HERRAJES!$J$5:$J$36,_xlpm.clave_todas),IF(_xlpm.herr_prof>0,_xlpm.herr_prof,_xlpm.herr_todas))),"") -> 0 | L73: =IFERROR(IF(B73="","",IF(I73="",0,I73)+IF(J73="",0,J73)+IF(K73="",0,K73)),"") -> 2867.0115 | M73: =IFERROR(IF(L73="","",L73*$D$8),"") -> 3583.7644 | N73: =IFERROR(IF(M73="","",CEILING(M73,50)),"") -> 3600 | O73: 0 | P73: =IFERROR(IF(G73="","",G73*N73*(1-O73)),"") -> 3600
B74: MOLDURA DIFÍCIL | C74: 5 | D74: 400 | E74: — | F74: NOGAL | G74: 1 | H74: =IFERROR(IF(B74="","",(C74/100)*(D74/100)),"") -> 0.2 | I74: =IFERROR(IF(B74="","",_xlfn.LET(_xlpm.tamano,IF(H74<=0.5,"CHICO",IF(H74<=1,"MEDIANO","GRANDE")),_xlpm.clave,B74&"|"&_xlpm.tamano,_xlpm.fila,MATCH(_xlpm.clave,COSTOS_M2!$H$5:$H$67,0),_xlpm.mat_m2,INDEX(IF(F74="HUANACAXTLE",COSTOS_M2!$D$5:$D$67,IF(F74="ENCINO",COSTOS_M2!$E$5:$E$67,COSTOS_M2!$F$5:$F$67)),_xlpm.fila),_xlpm.cons_m2,INDEX(COSTOS_M2!$G$5:$G$67,_xlpm.fila),_xlpm.prof_factor,IF(AND(E74<>"—",E74<>"",ISNUMBER(E74)),POWER(E74/40,1.8),1),_xlpm.total_m2,(_xlpm.mat_m2+_xlpm.cons_m2)*H74*_xlpm.prof_factor*IF(C74>70,COSTOS_M2!$B$70,1)*IF(D74>244,COSTOS_M2!$B$71,1),_xlpm.total_m2)),"") -> 1339 | J74: =IFERROR(IF(B74="","",INDEX(MANO_DE_OBRA!$P$10:$P$72,MATCH(B74&"|"&IF(H74<=0.5,"CHICO",IF(H74<=1,"MEDIANO","GRANDE")),MANO_DE_OBRA!$Q$10:$Q$72,0))),"") -> 477.459 | K74: =IFERROR(IF(B74="","",_xlfn.LET(_xlpm.clave_prof,B74&"|"&E74,_xlpm.clave_todas,B74&"|TODAS",_xlpm.herr_prof,SUMIFS(HERRAJES!$H$5:$H$36,HERRAJES!$J$5:$J$36,_xlpm.clave_prof),_xlpm.herr_todas,SUMIFS(HERRAJES!$H$5:$H$36,HERRAJES!$J$5:$J$36,_xlpm.clave_todas),IF(_xlpm.herr_prof>0,_xlpm.herr_prof,_xlpm.herr_todas))),"") -> 0 | L74: =IFERROR(IF(B74="","",IF(I74="",0,I74)+IF(J74="",0,J74)+IF(K74="",0,K74)),"") -> 1816.459 | M74: =IFERROR(IF(L74="","",L74*$D$8),"") -> 2270.5738 | N74: =IFERROR(IF(M74="","",CEILING(M74,50)),"") -> 2300 | P74: =IFERROR(IF(G74="","",G74*N74*(1-O74)),"") -> 2300
H75: =IFERROR(IF(B75="","",(C75/100)*(D75/100)),"") | I75: =IFERROR(IF(B75="","",_xlfn.LET(_xlpm.tamano,IF(H75<=0.5,"CHICO",IF(H75<=1,"MEDIANO","GRANDE")),_xlpm.clave,B75&"|"&_xlpm.tamano,_xlpm.fila,MATCH(_xlpm.clave,COSTOS_M2!$H$5:$H$67,0),_xlpm.mat_m2,INDEX(IF(F75="HUANACAXTLE",COSTOS_M2!$D$5:$D$67,IF(F75="ENCINO",COSTOS_M2!$E$5:$E$67,COSTOS_M2!$F$5:$F$67)),_xlpm.fila),_xlpm.cons_m2,INDEX(COSTOS_M2!$G$5:$G$67,_xlpm.fila),_xlpm.prof_factor,IF(AND(E75<>"—",E75<>"",ISNUMBER(E75)),POWER(E75/40,1.8),1),_xlpm.total_m2,(_xlpm.mat_m2+_xlpm.cons_m2)*H75*_xlpm.prof_factor*IF(C75>70,COSTOS_M2!$B$70,1)*IF(D75>244,COSTOS_M2!$B$71,1),_xlpm.total_m2)),"") | J75: =IFERROR(IF(B75="","",INDEX(MANO_DE_OBRA!$P$10:$P$72,MATCH(B75&"|"&IF(H75<=0.5,"CHICO",IF(H75<=1,"MEDIANO","GRANDE")),MANO_DE_OBRA!$Q$10:$Q$72,0))),"") | K75: =IFERROR(IF(B75="","",_xlfn.LET(_xlpm.clave_prof,B75&"|"&E75,_xlpm.clave_todas,B75&"|TODAS",_xlpm.herr_prof,SUMIFS(HERRAJES!$H$5:$H$36,HERRAJES!$J$5:$J$36,_xlpm.clave_prof),_xlpm.herr_todas,SUMIFS(HERRAJES!$H$5:$H$36,HERRAJES!$J$5:$J$36,_xlpm.clave_todas),IF(_xlpm.herr_prof>0,_xlpm.herr_prof,_xlpm.herr_todas))),"") | L75: =IFERROR(IF(B75="","",IF(I75="",0,I75)+IF(J75="",0,J75)+IF(K75="",0,K75)),"") | M75: =IFERROR(IF(L75="","",L75*$D$8),"") | N75: =IFERROR(IF(M75="","",CEILING(M75,50)),"") | O75: 0 | P75: =IFERROR(IF(G75="","",G75*N75*(1-O75)),"")
B76: CLOSET FRANCISCO
A77: V1 | B77: CAJÓN | C77: 115 | D77: 20 | E77: 37 | F77: NOGAL | G77: 2 | H77: =IFERROR(IF(B77="","",(C77/100)*(D77/100)),"") -> 0.23 | I77: =IFERROR(IF(B77="","",_xlfn.LET(_xlpm.tamano,IF(H77<=0.5,"CHICO",IF(H77<=1,"MEDIANO","GRANDE")),_xlpm.clave,B77&"|"&_xlpm.tamano,_xlpm.fila,MATCH(_xlpm.clave,COSTOS_M2!$H$5:$H$67,0),_xlpm.mat_m2,INDEX(IF(F77="HUANACAXTLE",COSTOS_M2!$D$5:$D$67,IF(F77="ENCINO",COSTOS_M2!$E$5:$E$67,COSTOS_M2!$F$5:$F$67)),_xlpm.fila),_xlpm.cons_m2,INDEX(COSTOS_M2!$G$5:$G$67,_xlpm.fila),_xlpm.prof_factor,IF(AND(E77<>"—",E77<>"",ISNUMBER(E77)),POWER(E77/40,1.8),1),_xlpm.total_m2,(_xlpm.mat_m2+_xlpm.cons_m2)*H77*_xlpm.prof_factor*IF(C77>70,COSTOS_M2!$B$70,1)*IF(D77>244,COSTOS_M2!$B$71,1),_xlpm.total_m2)),"") -> 345.60335 | J77: =IFERROR(IF(B77="","",INDEX(MANO_DE_OBRA!$P$10:$P$72,MATCH(B77&"|"&IF(H77<=0.5,"CHICO",IF(H77<=1,"MEDIANO","GRANDE")),MANO_DE_OBRA!$Q$10:$Q$72,0))),"") -> 434.36213 | K77: =IFERROR(IF(B77="","",_xlfn.LET(_xlpm.clave_prof,B77&"|"&E77,_xlpm.clave_todas,B77&"|TODAS",_xlpm.herr_prof,SUMIFS(HERRAJES!$H$5:$H$36,HERRAJES!$J$5:$J$36,_xlpm.clave_prof),_xlpm.herr_todas,SUMIFS(HERRAJES!$H$5:$H$36,HERRAJES!$J$5:$J$36,_xlpm.clave_todas),IF(_xlpm.herr_prof>0,_xlpm.herr_prof,_xlpm.herr_todas))),"") -> 0 | L77: =IFERROR(IF(B77="","",IF(I77="",0,I77)+IF(J77="",0,J77)+IF(K77="",0,K77)),"") -> 779.96549 | M77: =IFERROR(IF(L77="","",L77*$D$8),"") -> 974.95686 | N77: =IFERROR(IF(M77="","",CEILING(M77,50)),"") -> 1000 | O77: 0 | P77: =IFERROR(IF(G77="","",G77*N77*(1-O77)),"") -> 2000
A78: V1 | B78: ENTREPAÑO | C78: 37 | D78: 115 | E78: — | F78: NOGAL | G78: 2 | H78: =IFERROR(IF(B78="","",(C78/100)*(D78/100)),"") -> 0.4255 | I78: =IFERROR(IF(B78="","",_xlfn.LET(_xlpm.tamano,IF(H78<=0.5,"CHICO",IF(H78<=1,"MEDIANO","GRANDE")),_xlpm.clave,B78&"|"&_xlpm.tamano,_xlpm.fila,MATCH(_xlpm.clave,COSTOS_M2!$H$5:$H$67,0),_xlpm.mat_m2,INDEX(IF(F78="HUANACAXTLE",COSTOS_M2!$D$5:$D$67,IF(F78="ENCINO",COSTOS_M2!$E$5:$E$67,COSTOS_M2!$F$5:$F$67)),_xlpm.fila),_xlpm.cons_m2,INDEX(COSTOS_M2!$G$5:$G$67,_xlpm.fila),_xlpm.prof_factor,IF(AND(E78<>"—",E78<>"",ISNUMBER(E78)),POWER(E78/40,1.8),1),_xlpm.total_m2,(_xlpm.mat_m2+_xlpm.cons_m2)*H78*_xlpm.prof_factor*IF(C78>70,COSTOS_M2!$B$70,1)*IF(D78>244,COSTOS_M2!$B$71,1),_xlpm.total_m2)),"") -> 334.443 | J78: =IFERROR(IF(B78="","",INDEX(MANO_DE_OBRA!$P$10:$P$72,MATCH(B78&"|"&IF(H78<=0.5,"CHICO",IF(H78<=1,"MEDIANO","GRANDE")),MANO_DE_OBRA!$Q$10:$Q$72,0))),"") -> 292.24065 | K78: =IFERROR(IF(B78="","",_xlfn.LET(_xlpm.clave_prof,B78&"|"&E78,_xlpm.clave_todas,B78&"|TODAS",_xlpm.herr_prof,SUMIFS(HERRAJES!$H$5:$H$36,HERRAJES!$J$5:$J$36,_xlpm.clave_prof),_xlpm.herr_todas,SUMIFS(HERRAJES!$H$5:$H$36,HERRAJES!$J$5:$J$36,_xlpm.clave_todas),IF(_xlpm.herr_prof>0,_xlpm.herr_prof,_xlpm.herr_todas))),"") -> 0 | L78: =IFERROR(IF(B78="","",IF(I78="",0,I78)+IF(J78="",0,J78)+IF(K78="",0,K78)),"") -> 626.68365 | M78: =IFERROR(IF(L78="","",L78*$D$8),"") -> 783.35456 | N78: =IFERROR(IF(M78="","",CEILING(M78,50)),"") -> 800 | O78: 0 | P78: =IFERROR(IF(G78="","",G78*N78*(1-O78)),"") -> 1600
A79: V2 | B79: PISO CON ZOCLO | C79: 60 | D79: 205 | E79: — | F79: NOGAL | G79: 1 | H79: =IFERROR(IF(B79="","",(C79/100)*(D79/100)),"") -> 1.23 | I79: =IFERROR(IF(B79="","",_xlfn.LET(_xlpm.tamano,IF(H79<=0.5,"CHICO",IF(H79<=1,"MEDIANO","GRANDE")),_xlpm.clave,B79&"|"&_xlpm.tamano,_xlpm.fila,MATCH(_xlpm.clave,COSTOS_M2!$H$5:$H$67,0),_xlpm.mat_m2,INDEX(IF(F79="HUANACAXTLE",COSTOS_M2!$D$5:$D$67,IF(F79="ENCINO",COSTOS_M2!$E$5:$E$67,COSTOS_M2!$F$5:$F$67)),_xlpm.fila),_xlpm.cons_m2,INDEX(COSTOS_M2!$G$5:$G$67,_xlpm.fila),_xlpm.prof_factor,IF(AND(E79<>"—",E79<>"",ISNUMBER(E79)),POWER(E79/40,1.8),1),_xlpm.total_m2,(_xlpm.mat_m2+_xlpm.cons_m2)*H79*_xlpm.prof_factor*IF(C79>70,COSTOS_M2!$B$70,1)*IF(D79>244,COSTOS_M2!$B$71,1),_xlpm.total_m2)),"") -> 827.79 | J79: =IFERROR(IF(B79="","",INDEX(MANO_DE_OBRA!$P$10:$P$72,MATCH(B79&"|"&IF(H79<=0.5,"CHICO",IF(H79<=1,"MEDIANO","GRANDE")),MANO_DE_OBRA!$Q$10:$Q$72,0))),"") -> 614.34549 | K79: =IFERROR(IF(B79="","",_xlfn.LET(_xlpm.clave_prof,B79&"|"&E79,_xlpm.clave_todas,B79&"|TODAS",_xlpm.herr_prof,SUMIFS(HERRAJES!$H$5:$H$36,HERRAJES!$J$5:$J$36,_xlpm.clave_prof),_xlpm.herr_todas,SUMIFS(HERRAJES!$H$5:$H$36,HERRAJES!$J$5:$J$36,_xlpm.clave_todas),IF(_xlpm.herr_prof>0,_xlpm.herr_prof,_xlpm.herr_todas))),"") -> 0 | L79: =IFERROR(IF(B79="","",IF(I79="",0,I79)+IF(J79="",0,J79)+IF(K79="",0,K79)),"") -> 1442.1355 | M79: =IFERROR(IF(L79="","",L79*$D$8),"") -> 1802.6694 | N79: =IFERROR(IF(M79="","",CEILING(M79,50)),"") -> 1850 | O79: 0 | P79: =IFERROR(IF(G79="","",G79*N79*(1-O79)),"") -> 1850
A80: V2 | B80: CIELO | C80: 60 | D80: 205 | E80: — | F80: NOGAL | G80: 2 | H80: =IFERROR(IF(B80="","",(C80/100)*(D80/100)),"") -> 1.23 | I80: =IFERROR(IF(B80="","",_xlfn.LET(_xlpm.tamano,IF(H80<=0.5,"CHICO",IF(H80<=1,"MEDIANO","GRANDE")),_xlpm.clave,B80&"|"&_xlpm.tamano,_xlpm.fila,MATCH(_xlpm.clave,COSTOS_M2!$H$5:$H$67,0),_xlpm.mat_m2,INDEX(IF(F80="HUANACAXTLE",COSTOS_M2!$D$5:$D$67,IF(F80="ENCINO",COSTOS_M2!$E$5:$E$67,COSTOS_M2!$F$5:$F$67)),_xlpm.fila),_xlpm.cons_m2,INDEX(COSTOS_M2!$G$5:$G$67,_xlpm.fila),_xlpm.prof_factor,IF(AND(E80<>"—",E80<>"",ISNUMBER(E80)),POWER(E80/40,1.8),1),_xlpm.total_m2,(_xlpm.mat_m2+_xlpm.cons_m2)*H80*_xlpm.prof_factor*IF(C80>70,COSTOS_M2!$B$70,1)*IF(D80>244,COSTOS_M2!$B$71,1),_xlpm.total_m2)),"") -> 993.84 | J80: =IFERROR(IF(B80="","",INDEX(MANO_DE_OBRA!$P$10:$P$72,MATCH(B80&"|"&IF(H80<=0.5,"CHICO",IF(H80<=1,"MEDIANO","GRANDE")),MANO_DE_OBRA!$Q$10:$Q$72,0))),"") -> 762.95904 | K80: =IFERROR(IF(B80="","",_xlfn.LET(_xlpm.clave_prof,B80&"|"&E80,_xlpm.clave_todas,B80&"|TODAS",_xlpm.herr_prof,SUMIFS(HERRAJES!$H$5:$H$36,HERRAJES!$J$5:$J$36,_xlpm.clave_prof),_xlpm.herr_todas,SUMIFS(HERRAJES!$H$5:$H$36,HERRAJES!$J$5:$J$36,_xlpm.clave_todas),IF(_xlpm.herr_prof>0,_xlpm.herr_prof,_xlpm.herr_todas))),"") -> 0 | L80: =IFERROR(IF(B80="","",IF(I80="",0,I80)+IF(J80="",0,J80)+IF(K80="",0,K80)),"") -> 1756.799 | M80: =IFERROR(IF(L80="","",L80*$D$8),"") -> 2195.9988 | N80: =IFERROR(IF(M80="","",CEILING(M80,50)),"") -> 2200 | O80: 0 | P80: =IFERROR(IF(G80="","",G80*N80*(1-O80)),"") -> 4400
A81: V2 | B81: PARAL 1 VISTA | C81: 60 | D81: 295 | E81: — | F81: NOGAL | G81: 2 | H81: =IFERROR(IF(B81="","",(C81/100)*(D81/100)),"") -> 1.77 | I81: =IFERROR(IF(B81="","",_xlfn.LET(_xlpm.tamano,IF(H81<=0.5,"CHICO",IF(H81<=1,"MEDIANO","GRANDE")),_xlpm.clave,B81&"|"&_xlpm.tamano,_xlpm.fila,MATCH(_xlpm.clave,COSTOS_M2!$H$5:$H$67,0),_xlpm.mat_m2,INDEX(IF(F81="HUANACAXTLE",COSTOS_M2!$D$5:$D$67,IF(F81="ENCINO",COSTOS_M2!$E$5:$E$67,COSTOS_M2!$F$5:$F$67)),_xlpm.fila),_xlpm.cons_m2,INDEX(COSTOS_M2!$G$5:$G$67,_xlpm.fila),_xlpm.prof_factor,IF(AND(E81<>"—",E81<>"",ISNUMBER(E81)),POWER(E81/40,1.8),1),_xlpm.total_m2,(_xlpm.mat_m2+_xlpm.cons_m2)*H81*_xlpm.prof_factor*IF(C81>70,COSTOS_M2!$B$70,1)*IF(D81>244,COSTOS_M2!$B$71,1),_xlpm.total_m2)),"") -> 1585.389 | J81: =IFERROR(IF(B81="","",INDEX(MANO_DE_OBRA!$P$10:$P$72,MATCH(B81&"|"&IF(H81<=0.5,"CHICO",IF(H81<=1,"MEDIANO","GRANDE")),MANO_DE_OBRA!$Q$10:$Q$72,0))),"") -> 587.22913 | K81: =IFERROR(IF(B81="","",_xlfn.LET(_xlpm.clave_prof,B81&"|"&E81,_xlpm.clave_todas,B81&"|TODAS",_xlpm.herr_prof,SUMIFS(HERRAJES!$H$5:$H$36,HERRAJES!$J$5:$J$36,_xlpm.clave_prof),_xlpm.herr_todas,SUMIFS(HERRAJES!$H$5:$H$36,HERRAJES!$J$5:$J$36,_xlpm.clave_todas),IF(_xlpm.herr_prof>0,_xlpm.herr_prof,_xlpm.herr_todas))),"") -> 0 | L81: =IFERROR(IF(B81="","",IF(I81="",0,I81)+IF(J81="",0,J81)+IF(K81="",0,K81)),"") -> 2172.6181 | M81: =IFERROR(IF(L81="","",L81*$D$8),"") -> 2715.7727 | N81: =IFERROR(IF(M81="","",CEILING(M81,50)),"") -> 2750 | O81: 0 | P81: =IFERROR(IF(G81="","",G81*N81*(1-O81)),"") -> 5500
A82: V2 | B82: PARAL DELGADO 2V | C82: 60 | D82: 295 | E82: — | F82: NOGAL | G82: 3 | H82: =IFERROR(IF(B82="","",(C82/100)*(D82/100)),"") -> 1.77 | I82: =IFERROR(IF(B82="","",_xlfn.LET(_xlpm.tamano,IF(H82<=0.5,"CHICO",IF(H82<=1,"MEDIANO","GRANDE")),_xlpm.clave,B82&"|"&_xlpm.tamano,_xlpm.fila,MATCH(_xlpm.clave,COSTOS_M2!$H$5:$H$67,0),_xlpm.mat_m2,INDEX(IF(F82="HUANACAXTLE",COSTOS_M2!$D$5:$D$67,IF(F82="ENCINO",COSTOS_M2!$E$5:$E$67,COSTOS_M2!$F$5:$F$67)),_xlpm.fila),_xlpm.cons_m2,INDEX(COSTOS_M2!$G$5:$G$67,_xlpm.fila),_xlpm.prof_factor,IF(AND(E82<>"—",E82<>"",ISNUMBER(E82)),POWER(E82/40,1.8),1),_xlpm.total_m2,(_xlpm.mat_m2+_xlpm.cons_m2)*H82*_xlpm.prof_factor*IF(C82>70,COSTOS_M2!$B$70,1)*IF(D82>244,COSTOS_M2!$B$71,1),_xlpm.total_m2)),"") -> 1714.245 | J82: =IFERROR(IF(B82="","",INDEX(MANO_DE_OBRA!$P$10:$P$72,MATCH(B82&"|"&IF(H82<=0.5,"CHICO",IF(H82<=1,"MEDIANO","GRANDE")),MANO_DE_OBRA!$Q$10:$Q$72,0))),"") -> 725.196 | K82: =IFERROR(IF(B82="","",_xlfn.LET(_xlpm.clave_prof,B82&"|"&E82,_xlpm.clave_todas,B82&"|TODAS",_xlpm.herr_prof,SUMIFS(HERRAJES!$H$5:$H$36,HERRAJES!$J$5:$J$36,_xlpm.clave_prof),_xlpm.herr_todas,SUMIFS(HERRAJES!$H$5:$H$36,HERRAJES!$J$5:$J$36,_xlpm.clave_todas),IF(_xlpm.herr_prof>0,_xlpm.herr_prof,_xlpm.herr_todas))),"") -> 0 | L82: =IFERROR(IF(B82="","",IF(I82="",0,I82)+IF(J82="",0,J82)+IF(K82="",0,K82)),"") -> 2439.441 | M82: =IFERROR(IF(L82="","",L82*$D$8),"") -> 3049.3013 | N82: =IFERROR(IF(M82="","",CEILING(M82,50)),"") -> 3050 | O82: 0 | P82: =IFERROR(IF(G82="","",G82*N82*(1-O82)),"") -> 9150
A83: V2 | B83: ZAPATERA EXTRAÍBLE | C83: 100 | D83: 60 | E83: 60 | F83: NOGAL | G83: 8 | H83: =IFERROR(IF(B83="","",(C83/100)*(D83/100)),"") -> 0.6 | I83: =IFERROR(IF(B83="","",_xlfn.LET(_xlpm.tamano,IF(H83<=0.5,"CHICO",IF(H83<=1,"MEDIANO","GRANDE")),_xlpm.clave,B83&"|"&_xlpm.tamano,_xlpm.fila,MATCH(_xlpm.clave,COSTOS_M2!$H$5:$H$67,0),_xlpm.mat_m2,INDEX(IF(F83="HUANACAXTLE",COSTOS_M2!$D$5:$D$67,IF(F83="ENCINO",COSTOS_M2!$E$5:$E$67,COSTOS_M2!$F$5:$F$67)),_xlpm.fila),_xlpm.cons_m2,INDEX(COSTOS_M2!$G$5:$G$67,_xlpm.fila),_xlpm.prof_factor,IF(AND(E83<>"—",E83<>"",ISNUMBER(E83)),POWER(E83/40,1.8),1),_xlpm.total_m2,(_xlpm.mat_m2+_xlpm.cons_m2)*H83*_xlpm.prof_factor*IF(C83>70,COSTOS_M2!$B$70,1)*IF(D83>244,COSTOS_M2!$B$71,1),_xlpm.total_m2)),"") -> 941.85024 | J83: =IFERROR(IF(B83="","",INDEX(MANO_DE_OBRA!$P$10:$P$72,MATCH(B83&"|"&IF(H83<=0.5,"CHICO",IF(H83<=1,"MEDIANO","GRANDE")),MANO_DE_OBRA!$Q$10:$Q$72,0))),"") -> 410.25956 | K83: =IFERROR(IF(B83="","",_xlfn.LET(_xlpm.clave_prof,B83&"|"&E83,_xlpm.clave_todas,B83&"|TODAS",_xlpm.herr_prof,SUMIFS(HERRAJES!$H$5:$H$36,HERRAJES!$J$5:$J$36,_xlpm.clave_prof),_xlpm.herr_todas,SUMIFS(HERRAJES!$H$5:$H$36,HERRAJES!$J$5:$J$36,_xlpm.clave_todas),IF(_xlpm.herr_prof>0,_xlpm.herr_prof,_xlpm.herr_todas))),"") -> 54.97 | L83: =IFERROR(IF(B83="","",IF(I83="",0,I83)+IF(J83="",0,J83)+IF(K83="",0,K83)),"") -> 1407.0798 | M83: =IFERROR(IF(L83="","",L83*$D$8),"") -> 1758.8498 | N83: =IFERROR(IF(M83="","",CEILING(M83,50)),"") -> 1800 | O83: 0 | P83: =IFERROR(IF(G83="","",G83*N83*(1-O83)),"") -> 14400
A84: V2 | B84: ENTREPAÑO DELGADO | C84: 60 | D84: 100 | E84: — | F84: NOGAL | G84: 7 | H84: =IFERROR(IF(B84="","",(C84/100)*(D84/100)),"") -> 0.6 | I84: =IFERROR(IF(B84="","",_xlfn.LET(_xlpm.tamano,IF(H84<=0.5,"CHICO",IF(H84<=1,"MEDIANO","GRANDE")),_xlpm.clave,B84&"|"&_xlpm.tamano,_xlpm.fila,MATCH(_xlpm.clave,COSTOS_M2!$H$5:$H$67,0),_xlpm.mat_m2,INDEX(IF(F84="HUANACAXTLE",COSTOS_M2!$D$5:$D$67,IF(F84="ENCINO",COSTOS_M2!$E$5:$E$67,COSTOS_M2!$F$5:$F$67)),_xlpm.fila),_xlpm.cons_m2,INDEX(COSTOS_M2!$G$5:$G$67,_xlpm.fila),_xlpm.prof_factor,IF(AND(E84<>"—",E84<>"",ISNUMBER(E84)),POWER(E84/40,1.8),1),_xlpm.total_m2,(_xlpm.mat_m2+_xlpm.cons_m2)*H84*_xlpm.prof_factor*IF(C84>70,COSTOS_M2!$B$70,1)*IF(D84>244,COSTOS_M2!$B$71,1),_xlpm.total_m2)),"") -> 471 | J84: =IFERROR(IF(B84="","",INDEX(MANO_DE_OBRA!$P$10:$P$72,MATCH(B84&"|"&IF(H84<=0.5,"CHICO",IF(H84<=1,"MEDIANO","GRANDE")),MANO_DE_OBRA!$Q$10:$Q$72,0))),"") -> 400.5588 | K84: =IFERROR(IF(B84="","",_xlfn.LET(_xlpm.clave_prof,B84&"|"&E84,_xlpm.clave_todas,B84&"|TODAS",_xlpm.herr_prof,SUMIFS(HERRAJES!$H$5:$H$36,HERRAJES!$J$5:$J$36,_xlpm.clave_prof),_xlpm.herr_todas,SUMIFS(HERRAJES!$H$5:$H$36,HERRAJES!$J$5:$J$36,_xlpm.clave_todas),IF(_xlpm.herr_prof>0,_xlpm.herr_prof,_xlpm.herr_todas))),"") -> 0 | L84: =IFERROR(IF(B84="","",IF(I84="",0,I84)+IF(J84="",0,J84)+IF(K84="",0,K84)),"") -> 871.5588 | M84: =IFERROR(IF(L84="","",L84*$D$8),"") -> 1089.4485 | N84: =IFERROR(IF(M84="","",CEILING(M84,50)),"") -> 1100 | O84: 0 | P84: =IFERROR(IF(G84="","",G84*N84*(1-O84)),"") -> 7700
A85: V2 | B85: CAJÓN | C85: 100 | D85: 20 | E85: 60 | F85: NOGAL | G85: 4 | H85: =IFERROR(IF(B85="","",(C85/100)*(D85/100)),"") -> 0.2 | I85: =IFERROR(IF(B85="","",_xlfn.LET(_xlpm.tamano,IF(H85<=0.5,"CHICO",IF(H85<=1,"MEDIANO","GRANDE")),_xlpm.clave,B85&"|"&_xlpm.tamano,_xlpm.fila,MATCH(_xlpm.clave,COSTOS_M2!$H$5:$H$67,0),_xlpm.mat_m2,INDEX(IF(F85="HUANACAXTLE",COSTOS_M2!$D$5:$D$67,IF(F85="ENCINO",COSTOS_M2!$E$5:$E$67,COSTOS_M2!$F$5:$F$67)),_xlpm.fila),_xlpm.cons_m2,INDEX(COSTOS_M2!$G$5:$G$67,_xlpm.fila),_xlpm.prof_factor,IF(AND(E85<>"—",E85<>"",ISNUMBER(E85)),POWER(E85/40,1.8),1),_xlpm.total_m2,(_xlpm.mat_m2+_xlpm.cons_m2)*H85*_xlpm.prof_factor*IF(C85>70,COSTOS_M2!$B$70,1)*IF(D85>244,COSTOS_M2!$B$71,1),_xlpm.total_m2)),"") -> 717.44606 | J85: =IFERROR(IF(B85="","",INDEX(MANO_DE_OBRA!$P$10:$P$72,MATCH(B85&"|"&IF(H85<=0.5,"CHICO",IF(H85<=1,"MEDIANO","GRANDE")),MANO_DE_OBRA!$Q$10:$Q$72,0))),"") -> 434.36213 | K85: =IFERROR(IF(B85="","",_xlfn.LET(_xlpm.clave_prof,B85&"|"&E85,_xlpm.clave_todas,B85&"|TODAS",_xlpm.herr_prof,SUMIFS(HERRAJES!$H$5:$H$36,HERRAJES!$J$5:$J$36,_xlpm.clave_prof),_xlpm.herr_todas,SUMIFS(HERRAJES!$H$5:$H$36,HERRAJES!$J$5:$J$36,_xlpm.clave_todas),IF(_xlpm.herr_prof>0,_xlpm.herr_prof,_xlpm.herr_todas))),"") -> 54.97 | L85: =IFERROR(IF(B85="","",IF(I85="",0,I85)+IF(J85="",0,J85)+IF(K85="",0,K85)),"") -> 1206.7782 | M85: =IFERROR(IF(L85="","",L85*$D$8),"") -> 1508.4727 | N85: =IFERROR(IF(M85="","",CEILING(M85,50)),"") -> 1550 | O85: 0 | P85: =IFERROR(IF(G85="","",G85*N85*(1-O85)),"") -> 6200
A86: V2 | B86: ⚠️ 4 JALADERAS DECORATIVAS (PENDIENTE) | E86: — | H86: =IFERROR(IF(B86="","",(C86/100)*(D86/100)),"") -> 0 | I86: =IFERROR(IF(B86="","",_xlfn.LET(_xlpm.tamano,IF(H86<=0.5,"CHICO",IF(H86<=1,"MEDIANO","GRANDE")),_xlpm.clave,B86&"|"&_xlpm.tamano,_xlpm.fila,MATCH(_xlpm.clave,COSTOS_M2!$H$5:$H$67,0),_xlpm.mat_m2,INDEX(IF(F86="HUANACAXTLE",COSTOS_M2!$D$5:$D$67,IF(F86="ENCINO",COSTOS_M2!$E$5:$E$67,COSTOS_M2!$F$5:$F$67)),_xlpm.fila),_xlpm.cons_m2,INDEX(COSTOS_M2!$G$5:$G$67,_xlpm.fila),_xlpm.prof_factor,IF(AND(E86<>"—",E86<>"",ISNUMBER(E86)),POWER(E86/40,1.8),1),_xlpm.total_m2,(_xlpm.mat_m2+_xlpm.cons_m2)*H86*_xlpm.prof_factor*IF(C86>70,COSTOS_M2!$B$70,1)*IF(D86>244,COSTOS_M2!$B$71,1),_xlpm.total_m2)),"") | J86: =IFERROR(IF(B86="","",INDEX(MANO_DE_OBRA!$P$10:$P$72,MATCH(B86&"|"&IF(H86<=0.5,"CHICO",IF(H86<=1,"MEDIANO","GRANDE")),MANO_DE_OBRA!$Q$10:$Q$72,0))),"") | K86: =IFERROR(IF(B86="","",_xlfn.LET(_xlpm.clave_prof,B86&"|"&E86,_xlpm.clave_todas,B86&"|TODAS",_xlpm.herr_prof,SUMIFS(HERRAJES!$H$5:$H$36,HERRAJES!$J$5:$J$36,_xlpm.clave_prof),_xlpm.herr_todas,SUMIFS(HERRAJES!$H$5:$H$36,HERRAJES!$J$5:$J$36,_xlpm.clave_todas),IF(_xlpm.herr_prof>0,_xlpm.herr_prof,_xlpm.herr_todas))),"") -> 0 | L86: =IFERROR(IF(B86="","",IF(I86="",0,I86)+IF(J86="",0,J86)+IF(K86="",0,K86)),"") -> 0 | M86: =IFERROR(IF(L86="","",L86*$D$8),"") -> 0 | N86: =IFERROR(IF(M86="","",CEILING(M86,50)),"") -> 0 | P86: =IFERROR(IF(G86="","",G86*N86*(1-O86)),"")
A87: V2 | B87: TUBO COLGAR | C87: ESPECIAL | D87: 100 | E87: — | F87: NOGAL | G87: 6 | H87: =IFERROR(IF(B87="","",(C87/100)*(D87/100)),"") | I87: =IFERROR(IF(B87="","",_xlfn.LET(_xlpm.tamano,IF(H87<=0.5,"CHICO",IF(H87<=1,"MEDIANO","GRANDE")),_xlpm.clave,B87&"|"&_xlpm.tamano,_xlpm.fila,MATCH(_xlpm.clave,COSTOS_M2!$H$5:$H$67,0),_xlpm.mat_m2,INDEX(IF(F87="HUANACAXTLE",COSTOS_M2!$D$5:$D$67,IF(F87="ENCINO",COSTOS_M2!$E$5:$E$67,COSTOS_M2!$F$5:$F$67)),_xlpm.fila),_xlpm.cons_m2,INDEX(COSTOS_M2!$G$5:$G$67,_xlpm.fila),_xlpm.prof_factor,IF(AND(E87<>"—",E87<>"",ISNUMBER(E87)),POWER(E87/40,1.8),1),_xlpm.total_m2,(_xlpm.mat_m2+_xlpm.cons_m2)*H87*_xlpm.prof_factor*IF(C87>70,COSTOS_M2!$B$70,1)*IF(D87>244,COSTOS_M2!$B$71,1),_xlpm.total_m2)),"") | J87: =IFERROR(IF(B87="","",INDEX(MANO_DE_OBRA!$P$10:$P$72,MATCH(B87&"|"&IF(H87<=0.5,"CHICO",IF(H87<=1,"MEDIANO","GRANDE")),MANO_DE_OBRA!$Q$10:$Q$72,0))),"") -> 25.593 | K87: =IFERROR(IF(B87="","",_xlfn.LET(_xlpm.clave_prof,B87&"|"&E87,_xlpm.clave_todas,B87&"|TODAS",_xlpm.herr_prof,SUMIFS(HERRAJES!$H$5:$H$36,HERRAJES!$J$5:$J$36,_xlpm.clave_prof),_xlpm.herr_todas,SUMIFS(HERRAJES!$H$5:$H$36,HERRAJES!$J$5:$J$36,_xlpm.clave_todas),IF(_xlpm.herr_prof>0,_xlpm.herr_prof,_xlpm.herr_todas))),"") -> 2.74 | L87: =IFERROR(IF(B87="","",IF(I87="",0,I87)+IF(J87="",0,J87)+IF(K87="",0,K87)),"") -> 28.333 | M87: =IFERROR(IF(L87="","",L87*$D$8),"") -> 35.41625 | N87: =IFERROR(IF(M87="","",CEILING(M87,50)),"") -> 50 | O87: 0 | P87: =IFERROR(IF(G87="","",G87*N87*(1-O87)),"") -> 300
A88: V2 | B88: FONDO MADERA | C88: 409 | D88: 305 | E88: — | F88: NOGAL | G88: 1 | H88: =IFERROR(IF(B88="","",(C88/100)*(D88/100)),"") -> 12.4745 | I88: =IFERROR(IF(B88="","",_xlfn.LET(_xlpm.tamano,IF(H88<=0.5,"CHICO",IF(H88<=1,"MEDIANO","GRANDE")),_xlpm.clave,B88&"|"&_xlpm.tamano,_xlpm.fila,MATCH(_xlpm.clave,COSTOS_M2!$H$5:$H$67,0),_xlpm.mat_m2,INDEX(IF(F88="HUANACAXTLE",COSTOS_M2!$D$5:$D$67,IF(F88="ENCINO",COSTOS_M2!$E$5:$E$67,COSTOS_M2!$F$5:$F$67)),_xlpm.fila),_xlpm.cons_m2,INDEX(COSTOS_M2!$G$5:$G$67,_xlpm.fila),_xlpm.prof_factor,IF(AND(E88<>"—",E88<>"",ISNUMBER(E88)),POWER(E88/40,1.8),1),_xlpm.total_m2,(_xlpm.mat_m2+_xlpm.cons_m2)*H88*_xlpm.prof_factor*IF(C88>70,COSTOS_M2!$B$70,1)*IF(D88>244,COSTOS_M2!$B$71,1),_xlpm.total_m2)),"") -> 4954.2477 | J88: =IFERROR(IF(B88="","",INDEX(MANO_DE_OBRA!$P$10:$P$72,MATCH(B88&"|"&IF(H88<=0.5,"CHICO",IF(H88<=1,"MEDIANO","GRANDE")),MANO_DE_OBRA!$Q$10:$Q$72,0))),"") -> 295.7955 | K88: =IFERROR(IF(B88="","",_xlfn.LET(_xlpm.clave_prof,B88&"|"&E88,_xlpm.clave_todas,B88&"|TODAS",_xlpm.herr_prof,SUMIFS(HERRAJES!$H$5:$H$36,HERRAJES!$J$5:$J$36,_xlpm.clave_prof),_xlpm.herr_todas,SUMIFS(HERRAJES!$H$5:$H$36,HERRAJES!$J$5:$J$36,_xlpm.clave_todas),IF(_xlpm.herr_prof>0,_xlpm.herr_prof,_xlpm.herr_todas))),"") -> 0 | L88: =IFERROR(IF(B88="","",IF(I88="",0,I88)+IF(J88="",0,J88)+IF(K88="",0,K88)),"") -> 5250.0432 | M88: =IFERROR(IF(L88="","",L88*$D$8),"") -> 6562.554 | N88: =IFERROR(IF(M88="","",CEILING(M88,50)),"") -> 6600 | O88: 0 | P88: =IFERROR(IF(G88="","",G88*N88*(1-O88)),"") -> 6600
A89: V2 | B89: MOLDURA DIFÍCIL | C89: 5 | D89: 820 | E89: — | F89: NOGAL | G89: 1 | H89: =IFERROR(IF(B89="","",(C89/100)*(D89/100)),"") -> 0.41 | I89: =IFERROR(IF(B89="","",_xlfn.LET(_xlpm.tamano,IF(H89<=0.5,"CHICO",IF(H89<=1,"MEDIANO","GRANDE")),_xlpm.clave,B89&"|"&_xlpm.tamano,_xlpm.fila,MATCH(_xlpm.clave,COSTOS_M2!$H$5:$H$67,0),_xlpm.mat_m2,INDEX(IF(F89="HUANACAXTLE",COSTOS_M2!$D$5:$D$67,IF(F89="ENCINO",COSTOS_M2!$E$5:$E$67,COSTOS_M2!$F$5:$F$67)),_xlpm.fila),_xlpm.cons_m2,INDEX(COSTOS_M2!$G$5:$G$67,_xlpm.fila),_xlpm.prof_factor,IF(AND(E89<>"—",E89<>"",ISNUMBER(E89)),POWER(E89/40,1.8),1),_xlpm.total_m2,(_xlpm.mat_m2+_xlpm.cons_m2)*H89*_xlpm.prof_factor*IF(C89>70,COSTOS_M2!$B$70,1)*IF(D89>244,COSTOS_M2!$B$71,1),_xlpm.total_m2)),"") -> 2744.95 | J89: =IFERROR(IF(B89="","",INDEX(MANO_DE_OBRA!$P$10:$P$72,MATCH(B89&"|"&IF(H89<=0.5,"CHICO",IF(H89<=1,"MEDIANO","GRANDE")),MANO_DE_OBRA!$Q$10:$Q$72,0))),"") -> 477.459 | K89: =IFERROR(IF(B89="","",_xlfn.LET(_xlpm.clave_prof,B89&"|"&E89,_xlpm.clave_todas,B89&"|TODAS",_xlpm.herr_prof,SUMIFS(HERRAJES!$H$5:$H$36,HERRAJES!$J$5:$J$36,_xlpm.clave_prof),_xlpm.herr_todas,SUMIFS(HERRAJES!$H$5:$H$36,HERRAJES!$J$5:$J$36,_xlpm.clave_todas),IF(_xlpm.herr_prof>0,_xlpm.herr_prof,_xlpm.herr_todas))),"") -> 0 | L89: =IFERROR(IF(B89="","",IF(I89="",0,I89)+IF(J89="",0,J89)+IF(K89="",0,K89)),"") -> 3222.409 | M89: =IFERROR(IF(L89="","",L89*$D$8),"") -> 4028.0113 | N89: =IFERROR(IF(M89="","",CEILING(M89,50)),"") -> 4050 | O89: 0 | P89: =IFERROR(IF(G89="","",G89*N89*(1-O89)),"") -> 4050
A90: V3 | B90: PISO CON ZOCLO | C90: 60 | D90: 205 | E90: — | F90: NOGAL | G90: 1 | H90: =IFERROR(IF(B90="","",(C90/100)*(D90/100)),"") -> 1.23 | I90: =IFERROR(IF(B90="","",_xlfn.LET(_xlpm.tamano,IF(H90<=0.5,"CHICO",IF(H90<=1,"MEDIANO","GRANDE")),_xlpm.clave,B90&"|"&_xlpm.tamano,_xlpm.fila,MATCH(_xlpm.clave,COSTOS_M2!$H$5:$H$67,0),_xlpm.mat_m2,INDEX(IF(F90="HUANACAXTLE",COSTOS_M2!$D$5:$D$67,IF(F90="ENCINO",COSTOS_M2!$E$5:$E$67,COSTOS_M2!$F$5:$F$67)),_xlpm.fila),_xlpm.cons_m2,INDEX(COSTOS_M2!$G$5:$G$67,_xlpm.fila),_xlpm.prof_factor,IF(AND(E90<>"—",E90<>"",ISNUMBER(E90)),POWER(E90/40,1.8),1),_xlpm.total_m2,(_xlpm.mat_m2+_xlpm.cons_m2)*H90*_xlpm.prof_factor*IF(C90>70,COSTOS_M2!$B$70,1)*IF(D90>244,COSTOS_M2!$B$71,1),_xlpm.total_m2)),"") -> 827.79 | J90: =IFERROR(IF(B90="","",INDEX(MANO_DE_OBRA!$P$10:$P$72,MATCH(B90&"|"&IF(H90<=0.5,"CHICO",IF(H90<=1,"MEDIANO","GRANDE")),MANO_DE_OBRA!$Q$10:$Q$72,0))),"") -> 614.34549 | K90: =IFERROR(IF(B90="","",_xlfn.LET(_xlpm.clave_prof,B90&"|"&E90,_xlpm.clave_todas,B90&"|TODAS",_xlpm.herr_prof,SUMIFS(HERRAJES!$H$5:$H$36,HERRAJES!$J$5:$J$36,_xlpm.clave_prof),_xlpm.herr_todas,SUMIFS(HERRAJES!$H$5:$H$36,HERRAJES!$J$5:$J$36,_xlpm.clave_todas),IF(_xlpm.herr_prof>0,_xlpm.herr_prof,_xlpm.herr_todas))),"") -> 0 | L90: =IFERROR(IF(B90="","",IF(I90="",0,I90)+IF(J90="",0,J90)+IF(K90="",0,K90)),"") -> 1442.1355 | M90: =IFERROR(IF(L90="","",L90*$D$8),"") -> 1802.6694 | N90: =IFERROR(IF(M90="","",CEILING(M90,50)),"") -> 1850 | O90: 0 | P90: =IFERROR(IF(G90="","",G90*N90*(1-O90)),"") -> 1850
A91: V3 | B91: CIELO | C91: 60 | D91: 205 | E91: — | F91: NOGAL | G91: 2 | H91: =IFERROR(IF(B91="","",(C91/100)*(D91/100)),"") -> 1.23 | I91: =IFERROR(IF(B91="","",_xlfn.LET(_xlpm.tamano,IF(H91<=0.5,"CHICO",IF(H91<=1,"MEDIANO","GRANDE")),_xlpm.clave,B91&"|"&_xlpm.tamano,_xlpm.fila,MATCH(_xlpm.clave,COSTOS_M2!$H$5:$H$67,0),_xlpm.mat_m2,INDEX(IF(F91="HUANACAXTLE",COSTOS_M2!$D$5:$D$67,IF(F91="ENCINO",COSTOS_M2!$E$5:$E$67,COSTOS_M2!$F$5:$F$67)),_xlpm.fila),_xlpm.cons_m2,INDEX(COSTOS_M2!$G$5:$G$67,_xlpm.fila),_xlpm.prof_factor,IF(AND(E91<>"—",E91<>"",ISNUMBER(E91)),POWER(E91/40,1.8),1),_xlpm.total_m2,(_xlpm.mat_m2+_xlpm.cons_m2)*H91*_xlpm.prof_factor*IF(C91>70,COSTOS_M2!$B$70,1)*IF(D91>244,COSTOS_M2!$B$71,1),_xlpm.total_m2)),"") -> 993.84 | J91: =IFERROR(IF(B91="","",INDEX(MANO_DE_OBRA!$P$10:$P$72,MATCH(B91&"|"&IF(H91<=0.5,"CHICO",IF(H91<=1,"MEDIANO","GRANDE")),MANO_DE_OBRA!$Q$10:$Q$72,0))),"") -> 762.95904 | K91: =IFERROR(IF(B91="","",_xlfn.LET(_xlpm.clave_prof,B91&"|"&E91,_xlpm.clave_todas,B91&"|TODAS",_xlpm.herr_prof,SUMIFS(HERRAJES!$H$5:$H$36,HERRAJES!$J$5:$J$36,_xlpm.clave_prof),_xlpm.herr_todas,SUMIFS(HERRAJES!$H$5:$H$36,HERRAJES!$J$5:$J$36,_xlpm.clave_todas),IF(_xlpm.herr_prof>0,_xlpm.herr_prof,_xlpm.herr_todas))),"") -> 0 | L91: =IFERROR(IF(B91="","",IF(I91="",0,I91)+IF(J91="",0,J91)+IF(K91="",0,K91)),"") -> 1756.799 | M91: =IFERROR(IF(L91="","",L91*$D$8),"") -> 2195.9988 | N91: =IFERROR(IF(M91="","",CEILING(M91,50)),"") -> 2200 | O91: 0 | P91: =IFERROR(IF(G91="","",G91*N91*(1-O91)),"") -> 4400
A92: V3 | B92: PARAL 1 VISTA | C92: 60 | D92: 295 | E92: — | F92: NOGAL | G92: 2 | H92: =IFERROR(IF(B92="","",(C92/100)*(D92/100)),"") -> 1.77 | I92: =IFERROR(IF(B92="","",_xlfn.LET(_xlpm.tamano,IF(H92<=0.5,"CHICO",IF(H92<=1,"MEDIANO","GRANDE")),_xlpm.clave,B92&"|"&_xlpm.tamano,_xlpm.fila,MATCH(_xlpm.clave,COSTOS_M2!$H$5:$H$67,0),_xlpm.mat_m2,INDEX(IF(F92="HUANACAXTLE",COSTOS_M2!$D$5:$D$67,IF(F92="ENCINO",COSTOS_M2!$E$5:$E$67,COSTOS_M2!$F$5:$F$67)),_xlpm.fila),_xlpm.cons_m2,INDEX(COSTOS_M2!$G$5:$G$67,_xlpm.fila),_xlpm.prof_factor,IF(AND(E92<>"—",E92<>"",ISNUMBER(E92)),POWER(E92/40,1.8),1),_xlpm.total_m2,(_xlpm.mat_m2+_xlpm.cons_m2)*H92*_xlpm.prof_factor*IF(C92>70,COSTOS_M2!$B$70,1)*IF(D92>244,COSTOS_M2!$B$71,1),_xlpm.total_m2)),"") -> 1585.389 | J92: =IFERROR(IF(B92="","",INDEX(MANO_DE_OBRA!$P$10:$P$72,MATCH(B92&"|"&IF(H92<=0.5,"CHICO",IF(H92<=1,"MEDIANO","GRANDE")),MANO_DE_OBRA!$Q$10:$Q$72,0))),"") -> 587.22913 | K92: =IFERROR(IF(B92="","",_xlfn.LET(_xlpm.clave_prof,B92&"|"&E92,_xlpm.clave_todas,B92&"|TODAS",_xlpm.herr_prof,SUMIFS(HERRAJES!$H$5:$H$36,HERRAJES!$J$5:$J$36,_xlpm.clave_prof),_xlpm.herr_todas,SUMIFS(HERRAJES!$H$5:$H$36,HERRAJES!$J$5:$J$36,_xlpm.clave_todas),IF(_xlpm.herr_prof>0,_xlpm.herr_prof,_xlpm.herr_todas))),"") -> 0 | L92: =IFERROR(IF(B92="","",IF(I92="",0,I92)+IF(J92="",0,J92)+IF(K92="",0,K92)),"") -> 2172.6181 | M92: =IFERROR(IF(L92="","",L92*$D$8),"") -> 2715.7727 | N92: =IFERROR(IF(M92="","",CEILING(M92,50)),"") -> 2750 | O92: 0 | P92: =IFERROR(IF(G92="","",G92*N92*(1-O92)),"") -> 5500
A93: V3 | B93: PARAL DELGADO 2V | C93: 60 | D93: 295 | E93: — | F93: NOGAL | G93: 3 | H93: =IFERROR(IF(B93="","",(C93/100)*(D93/100)),"") -> 1.77 | I93: =IFERROR(IF(B93="","",_xlfn.LET(_xlpm.tamano,IF(H93<=0.5,"CHICO",IF(H93<=1,"MEDIANO","GRANDE")),_xlpm.clave,B93&"|"&_xlpm.tamano,_xlpm.fila,MATCH(_xlpm.clave,COSTOS_M2!$H$5:$H$67,0),_xlpm.mat_m2,INDEX(IF(F93="HUANACAXTLE",COSTOS_M2!$D$5:$D$67,IF(F93="ENCINO",COSTOS_M2!$E$5:$E$67,COSTOS_M2!$F$5:$F$67)),_xlpm.fila),_xlpm.cons_m2,INDEX(COSTOS_M2!$G$5:$G$67,_xlpm.fila),_xlpm.prof_factor,IF(AND(E93<>"—",E93<>"",ISNUMBER(E93)),POWER(E93/40,1.8),1),_xlpm.total_m2,(_xlpm.mat_m2+_xlpm.cons_m2)*H93*_xlpm.prof_factor*IF(C93>70,COSTOS_M2!$B$70,1)*IF(D93>244,COSTOS_M2!$B$71,1),_xlpm.total_m2)),"") -> 1714.245 | J93: =IFERROR(IF(B93="","",INDEX(MANO_DE_OBRA!$P$10:$P$72,MATCH(B93&"|"&IF(H93<=0.5,"CHICO",IF(H93<=1,"MEDIANO","GRANDE")),MANO_DE_OBRA!$Q$10:$Q$72,0))),"") -> 725.196 | K93: =IFERROR(IF(B93="","",_xlfn.LET(_xlpm.clave_prof,B93&"|"&E93,_xlpm.clave_todas,B93&"|TODAS",_xlpm.herr_prof,SUMIFS(HERRAJES!$H$5:$H$36,HERRAJES!$J$5:$J$36,_xlpm.clave_prof),_xlpm.herr_todas,SUMIFS(HERRAJES!$H$5:$H$36,HERRAJES!$J$5:$J$36,_xlpm.clave_todas),IF(_xlpm.herr_prof>0,_xlpm.herr_prof,_xlpm.herr_todas))),"") -> 0 | L93: =IFERROR(IF(B93="","",IF(I93="",0,I93)+IF(J93="",0,J93)+IF(K93="",0,K93)),"") -> 2439.441 | M93: =IFERROR(IF(L93="","",L93*$D$8),"") -> 3049.3013 | N93: =IFERROR(IF(M93="","",CEILING(M93,50)),"") -> 3050 | O93: 0 | P93: =IFERROR(IF(G93="","",G93*N93*(1-O93)),"") -> 9150
A94: V3 | B94: ZAPATERA EXTRAÍBLE | C94: 100 | D94: 60 | E94: 60 | F94: NOGAL | G94: 8 | H94: =IFERROR(IF(B94="","",(C94/100)*(D94/100)),"") -> 0.6 | I94: =IFERROR(IF(B94="","",_xlfn.LET(_xlpm.tamano,IF(H94<=0.5,"CHICO",IF(H94<=1,"MEDIANO","GRANDE")),_xlpm.clave,B94&"|"&_xlpm.tamano,_xlpm.fila,MATCH(_xlpm.clave,COSTOS_M2!$H$5:$H$67,0),_xlpm.mat_m2,INDEX(IF(F94="HUANACAXTLE",COSTOS_M2!$D$5:$D$67,IF(F94="ENCINO",COSTOS_M2!$E$5:$E$67,COSTOS_M2!$F$5:$F$67)),_xlpm.fila),_xlpm.cons_m2,INDEX(COSTOS_M2!$G$5:$G$67,_xlpm.fila),_xlpm.prof_factor,IF(AND(E94<>"—",E94<>"",ISNUMBER(E94)),POWER(E94/40,1.8),1),_xlpm.total_m2,(_xlpm.mat_m2+_xlpm.cons_m2)*H94*_xlpm.prof_factor*IF(C94>70,COSTOS_M2!$B$70,1)*IF(D94>244,COSTOS_M2!$B$71,1),_xlpm.total_m2)),"") -> 941.85024 | J94: =IFERROR(IF(B94="","",INDEX(MANO_DE_OBRA!$P$10:$P$72,MATCH(B94&"|"&IF(H94<=0.5,"CHICO",IF(H94<=1,"MEDIANO","GRANDE")),MANO_DE_OBRA!$Q$10:$Q$72,0))),"") -> 410.25956 | K94: =IFERROR(IF(B94="","",_xlfn.LET(_xlpm.clave_prof,B94&"|"&E94,_xlpm.clave_todas,B94&"|TODAS",_xlpm.herr_prof,SUMIFS(HERRAJES!$H$5:$H$36,HERRAJES!$J$5:$J$36,_xlpm.clave_prof),_xlpm.herr_todas,SUMIFS(HERRAJES!$H$5:$H$36,HERRAJES!$J$5:$J$36,_xlpm.clave_todas),IF(_xlpm.herr_prof>0,_xlpm.herr_prof,_xlpm.herr_todas))),"") -> 54.97 | L94: =IFERROR(IF(B94="","",IF(I94="",0,I94)+IF(J94="",0,J94)+IF(K94="",0,K94)),"") -> 1407.0798 | M94: =IFERROR(IF(L94="","",L94*$D$8),"") -> 1758.8498 | N94: =IFERROR(IF(M94="","",CEILING(M94,50)),"") -> 1800 | O94: 0 | P94: =IFERROR(IF(G94="","",G94*N94*(1-O94)),"") -> 14400
A95: V3 | B95: ENTREPAÑO DELGADO | C95: 60 | D95: 100 | E95: — | F95: NOGAL | G95: 4 | H95: =IFERROR(IF(B95="","",(C95/100)*(D95/100)),"") -> 0.6 | I95: =IFERROR(IF(B95="","",_xlfn.LET(_xlpm.tamano,IF(H95<=0.5,"CHICO",IF(H95<=1,"MEDIANO","GRANDE")),_xlpm.clave,B95&"|"&_xlpm.tamano,_xlpm.fila,MATCH(_xlpm.clave,COSTOS_M2!$H$5:$H$67,0),_xlpm.mat_m2,INDEX(IF(F95="HUANACAXTLE",COSTOS_M2!$D$5:$D$67,IF(F95="ENCINO",COSTOS_M2!$E$5:$E$67,COSTOS_M2!$F$5:$F$67)),_xlpm.fila),_xlpm.cons_m2,INDEX(COSTOS_M2!$G$5:$G$67,_xlpm.fila),_xlpm.prof_factor,IF(AND(E95<>"—",E95<>"",ISNUMBER(E95)),POWER(E95/40,1.8),1),_xlpm.total_m2,(_xlpm.mat_m2+_xlpm.cons_m2)*H95*_xlpm.prof_factor*IF(C95>70,COSTOS_M2!$B$70,1)*IF(D95>244,COSTOS_M2!$B$71,1),_xlpm.total_m2)),"") -> 471 | J95: =IFERROR(IF(B95="","",INDEX(MANO_DE_OBRA!$P$10:$P$72,MATCH(B95&"|"&IF(H95<=0.5,"CHICO",IF(H95<=1,"MEDIANO","GRANDE")),MANO_DE_OBRA!$Q$10:$Q$72,0))),"") -> 400.5588 | K95: =IFERROR(IF(B95="","",_xlfn.LET(_xlpm.clave_prof,B95&"|"&E95,_xlpm.clave_todas,B95&"|TODAS",_xlpm.herr_prof,SUMIFS(HERRAJES!$H$5:$H$36,HERRAJES!$J$5:$J$36,_xlpm.clave_prof),_xlpm.herr_todas,SUMIFS(HERRAJES!$H$5:$H$36,HERRAJES!$J$5:$J$36,_xlpm.clave_todas),IF(_xlpm.herr_prof>0,_xlpm.herr_prof,_xlpm.herr_todas))),"") -> 0 | L95: =IFERROR(IF(B95="","",IF(I95="",0,I95)+IF(J95="",0,J95)+IF(K95="",0,K95)),"") -> 871.5588 | M95: =IFERROR(IF(L95="","",L95*$D$8),"") -> 1089.4485 | N95: =IFERROR(IF(M95="","",CEILING(M95,50)),"") -> 1100 | O95: 0 | P95: =IFERROR(IF(G95="","",G95*N95*(1-O95)),"") -> 4400
A96: V3 | B96: ENTREPAÑO | C96: 60 | D96: 100 | E96: — | F96: NOGAL | G96: 5 | H96: =IFERROR(IF(B96="","",(C96/100)*(D96/100)),"") -> 0.6 | I96: =IFERROR(IF(B96="","",_xlfn.LET(_xlpm.tamano,IF(H96<=0.5,"CHICO",IF(H96<=1,"MEDIANO","GRANDE")),_xlpm.clave,B96&"|"&_xlpm.tamano,_xlpm.fila,MATCH(_xlpm.clave,COSTOS_M2!$H$5:$H$67,0),_xlpm.mat_m2,INDEX(IF(F96="HUANACAXTLE",COSTOS_M2!$D$5:$D$67,IF(F96="ENCINO",COSTOS_M2!$E$5:$E$67,COSTOS_M2!$F$5:$F$67)),_xlpm.fila),_xlpm.cons_m2,INDEX(COSTOS_M2!$G$5:$G$67,_xlpm.fila),_xlpm.prof_factor,IF(AND(E96<>"—",E96<>"",ISNUMBER(E96)),POWER(E96/40,1.8),1),_xlpm.total_m2,(_xlpm.mat_m2+_xlpm.cons_m2)*H96*_xlpm.prof_factor*IF(C96>70,COSTOS_M2!$B$70,1)*IF(D96>244,COSTOS_M2!$B$71,1),_xlpm.total_m2)),"") -> 452.4 | J96: =IFERROR(IF(B96="","",INDEX(MANO_DE_OBRA!$P$10:$P$72,MATCH(B96&"|"&IF(H96<=0.5,"CHICO",IF(H96<=1,"MEDIANO","GRANDE")),MANO_DE_OBRA!$Q$10:$Q$72,0))),"") -> 435.1911 | K96: =IFERROR(IF(B96="","",_xlfn.LET(_xlpm.clave_prof,B96&"|"&E96,_xlpm.clave_todas,B96&"|TODAS",_xlpm.herr_prof,SUMIFS(HERRAJES!$H$5:$H$36,HERRAJES!$J$5:$J$36,_xlpm.clave_prof),_xlpm.herr_todas,SUMIFS(HERRAJES!$H$5:$H$36,HERRAJES!$J$5:$J$36,_xlpm.clave_todas),IF(_xlpm.herr_prof>0,_xlpm.herr_prof,_xlpm.herr_todas))),"") -> 0 | L96: =IFERROR(IF(B96="","",IF(I96="",0,I96)+IF(J96="",0,J96)+IF(K96="",0,K96)),"") -> 887.5911 | M96: =IFERROR(IF(L96="","",L96*$D$8),"") -> 1109.4889 | N96: =IFERROR(IF(M96="","",CEILING(M96,50)),"") -> 1150 | O96: 0 | P96: =IFERROR(IF(G96="","",G96*N96*(1-O96)),"") -> 5750
A97: V3 | B97: TUBO COLGAR | C97: ESPECIAL | D97: 100 | E97: — | F97: NOGAL | G97: 6 | H97: =IFERROR(IF(B97="","",(C97/100)*(D97/100)),"") | I97: =IFERROR(IF(B97="","",_xlfn.LET(_xlpm.tamano,IF(H97<=0.5,"CHICO",IF(H97<=1,"MEDIANO","GRANDE")),_xlpm.clave,B97&"|"&_xlpm.tamano,_xlpm.fila,MATCH(_xlpm.clave,COSTOS_M2!$H$5:$H$67,0),_xlpm.mat_m2,INDEX(IF(F97="HUANACAXTLE",COSTOS_M2!$D$5:$D$67,IF(F97="ENCINO",COSTOS_M2!$E$5:$E$67,COSTOS_M2!$F$5:$F$67)),_xlpm.fila),_xlpm.cons_m2,INDEX(COSTOS_M2!$G$5:$G$67,_xlpm.fila),_xlpm.prof_factor,IF(AND(E97<>"—",E97<>"",ISNUMBER(E97)),POWER(E97/40,1.8),1),_xlpm.total_m2,(_xlpm.mat_m2+_xlpm.cons_m2)*H97*_xlpm.prof_factor*IF(C97>70,COSTOS_M2!$B$70,1)*IF(D97>244,COSTOS_M2!$B$71,1),_xlpm.total_m2)),"") | J97: =IFERROR(IF(B97="","",INDEX(MANO_DE_OBRA!$P$10:$P$72,MATCH(B97&"|"&IF(H97<=0.5,"CHICO",IF(H97<=1,"MEDIANO","GRANDE")),MANO_DE_OBRA!$Q$10:$Q$72,0))),"") -> 25.593 | K97: =IFERROR(IF(B97="","",_xlfn.LET(_xlpm.clave_prof,B97&"|"&E97,_xlpm.clave_todas,B97&"|TODAS",_xlpm.herr_prof,SUMIFS(HERRAJES!$H$5:$H$36,HERRAJES!$J$5:$J$36,_xlpm.clave_prof),_xlpm.herr_todas,SUMIFS(HERRAJES!$H$5:$H$36,HERRAJES!$J$5:$J$36,_xlpm.clave_todas),IF(_xlpm.herr_prof>0,_xlpm.herr_prof,_xlpm.herr_todas))),"") -> 2.74 | L97: =IFERROR(IF(B97="","",IF(I97="",0,I97)+IF(J97="",0,J97)+IF(K97="",0,K97)),"") -> 28.333 | M97: =IFERROR(IF(L97="","",L97*$D$8),"") -> 35.41625 | N97: =IFERROR(IF(M97="","",CEILING(M97,50)),"") -> 50 | O97: 0 | P97: =IFERROR(IF(G97="","",G97*N97*(1-O97)),"") -> 300
A98: V3 | B98: FONDO MADERA | C98: 409 | D98: 305 | E98: — | F98: NOGAL | G98: 1 | H98: =IFERROR(IF(B98="","",(C98/100)*(D98/100)),"") -> 12.4745 | I98: =IFERROR(IF(B98="","",_xlfn.LET(_xlpm.tamano,IF(H98<=0.5,"CHICO",IF(H98<=1,"MEDIANO","GRANDE")),_xlpm.clave,B98&"|"&_xlpm.tamano,_xlpm.fila,MATCH(_xlpm.clave,COSTOS_M2!$H$5:$H$67,0),_xlpm.mat_m2,INDEX(IF(F98="HUANACAXTLE",COSTOS_M2!$D$5:$D$67,IF(F98="ENCINO",COSTOS_M2!$E$5:$E$67,COSTOS_M2!$F$5:$F$67)),_xlpm.fila),_xlpm.cons_m2,INDEX(COSTOS_M2!$G$5:$G$67,_xlpm.fila),_xlpm.prof_factor,IF(AND(E98<>"—",E98<>"",ISNUMBER(E98)),POWER(E98/40,1.8),1),_xlpm.total_m2,(_xlpm.mat_m2+_xlpm.cons_m2)*H98*_xlpm.prof_factor*IF(C98>70,COSTOS_M2!$B$70,1)*IF(D98>244,COSTOS_M2!$B$71,1),_xlpm.total_m2)),"") -> 4954.2477 | J98: =IFERROR(IF(B98="","",INDEX(MANO_DE_OBRA!$P$10:$P$72,MATCH(B98&"|"&IF(H98<=0.5,"CHICO",IF(H98<=1,"MEDIANO","GRANDE")),MANO_DE_OBRA!$Q$10:$Q$72,0))),"") -> 295.7955 | K98: =IFERROR(IF(B98="","",_xlfn.LET(_xlpm.clave_prof,B98&"|"&E98,_xlpm.clave_todas,B98&"|TODAS",_xlpm.herr_prof,SUMIFS(HERRAJES!$H$5:$H$36,HERRAJES!$J$5:$J$36,_xlpm.clave_prof),_xlpm.herr_todas,SUMIFS(HERRAJES!$H$5:$H$36,HERRAJES!$J$5:$J$36,_xlpm.clave_todas),IF(_xlpm.herr_prof>0,_xlpm.herr_prof,_xlpm.herr_todas))),"") -> 0 | L98: =IFERROR(IF(B98="","",IF(I98="",0,I98)+IF(J98="",0,J98)+IF(K98="",0,K98)),"") -> 5250.0432 | M98: =IFERROR(IF(L98="","",L98*$D$8),"") -> 6562.554 | N98: =IFERROR(IF(M98="","",CEILING(M98,50)),"") -> 6600 | O98: 0 | P98: =IFERROR(IF(G98="","",G98*N98*(1-O98)),"") -> 6600
A99: V3 | B99: MOLDURA DIFÍCIL | C99: 5 | D99: 820 | E99: — | F99: NOGAL | G99: 1 | H99: =IFERROR(IF(B99="","",(C99/100)*(D99/100)),"") -> 0.41 | I99: =IFERROR(IF(B99="","",_xlfn.LET(_xlpm.tamano,IF(H99<=0.5,"CHICO",IF(H99<=1,"MEDIANO","GRANDE")),_xlpm.clave,B99&"|"&_xlpm.tamano,_xlpm.fila,MATCH(_xlpm.clave,COSTOS_M2!$H$5:$H$67,0),_xlpm.mat_m2,INDEX(IF(F99="HUANACAXTLE",COSTOS_M2!$D$5:$D$67,IF(F99="ENCINO",COSTOS_M2!$E$5:$E$67,COSTOS_M2!$F$5:$F$67)),_xlpm.fila),_xlpm.cons_m2,INDEX(COSTOS_M2!$G$5:$G$67,_xlpm.fila),_xlpm.prof_factor,IF(AND(E99<>"—",E99<>"",ISNUMBER(E99)),POWER(E99/40,1.8),1),_xlpm.total_m2,(_xlpm.mat_m2+_xlpm.cons_m2)*H99*_xlpm.prof_factor*IF(C99>70,COSTOS_M2!$B$70,1)*IF(D99>244,COSTOS_M2!$B$71,1),_xlpm.total_m2)),"") -> 2744.95 | J99: =IFERROR(IF(B99="","",INDEX(MANO_DE_OBRA!$P$10:$P$72,MATCH(B99&"|"&IF(H99<=0.5,"CHICO",IF(H99<=1,"MEDIANO","GRANDE")),MANO_DE_OBRA!$Q$10:$Q$72,0))),"") -> 477.459 | K99: =IFERROR(IF(B99="","",_xlfn.LET(_xlpm.clave_prof,B99&"|"&E99,_xlpm.clave_todas,B99&"|TODAS",_xlpm.herr_prof,SUMIFS(HERRAJES!$H$5:$H$36,HERRAJES!$J$5:$J$36,_xlpm.clave_prof),_xlpm.herr_todas,SUMIFS(HERRAJES!$H$5:$H$36,HERRAJES!$J$5:$J$36,_xlpm.clave_todas),IF(_xlpm.herr_prof>0,_xlpm.herr_prof,_xlpm.herr_todas))),"") -> 0 | L99: =IFERROR(IF(B99="","",IF(I99="",0,I99)+IF(J99="",0,J99)+IF(K99="",0,K99)),"") -> 3222.409 | M99: =IFERROR(IF(L99="","",L99*$D$8),"") -> 4028.0113 | N99: =IFERROR(IF(M99="","",CEILING(M99,50)),"") -> 4050 | O99: 0 | P99: =IFERROR(IF(G99="","",G99*N99*(1-O99)),"") -> 4050
B100: VESTIDOR MARINA
A101: V2 PB | B101: PISO CON ZOCLO | C101: 55 | D101: 200 | E101: — | F101: NOGAL | G101: 1 | H101: =IFERROR(IF(B101="","",(C101/100)*(D101/100)),"") -> 1.1 | I101: =IFERROR(IF(B101="","",_xlfn.LET(_xlpm.tamano,IF(H101<=0.5,"CHICO",IF(H101<=1,"MEDIANO","GRANDE")),_xlpm.clave,B101&"|"&_xlpm.tamano,_xlpm.fila,MATCH(_xlpm.clave,COSTOS_M2!$H$5:$H$67,0),_xlpm.mat_m2,INDEX(IF(F101="HUANACAXTLE",COSTOS_M2!$D$5:$D$67,IF(F101="ENCINO",COSTOS_M2!$E$5:$E$67,COSTOS_M2!$F$5:$F$67)),_xlpm.fila),_xlpm.cons_m2,INDEX(COSTOS_M2!$G$5:$G$67,_xlpm.fila),_xlpm.prof_factor,IF(AND(E101<>"—",E101<>"",ISNUMBER(E101)),POWER(E101/40,1.8),1),_xlpm.total_m2,(_xlpm.mat_m2+_xlpm.cons_m2)*H101*_xlpm.prof_factor*IF(C101>70,COSTOS_M2!$B$70,1)*IF(D101>244,COSTOS_M2!$B$71,1),_xlpm.total_m2)),"") -> 740.3 | J101: =IFERROR(IF(B101="","",INDEX(MANO_DE_OBRA!$P$10:$P$72,MATCH(B101&"|"&IF(H101<=0.5,"CHICO",IF(H101<=1,"MEDIANO","GRANDE")),MANO_DE_OBRA!$Q$10:$Q$72,0))),"") -> 614.34549 | K101: =IFERROR(IF(B101="","",_xlfn.LET(_xlpm.clave_prof,B101&"|"&E101,_xlpm.clave_todas,B101&"|TODAS",_xlpm.herr_prof,SUMIFS(HERRAJES!$H$5:$H$36,HERRAJES!$J$5:$J$36,_xlpm.clave_prof),_xlpm.herr_todas,SUMIFS(HERRAJES!$H$5:$H$36,HERRAJES!$J$5:$J$36,_xlpm.clave_todas),IF(_xlpm.herr_prof>0,_xlpm.herr_prof,_xlpm.herr_todas))),"") -> 0 | L101: =IFERROR(IF(B101="","",IF(I101="",0,I101)+IF(J101="",0,J101)+IF(K101="",0,K101)),"") -> 1354.6455 | M101: =IFERROR(IF(L101="","",L101*$D$8),"") -> 1693.3069 | N101: =IFERROR(IF(M101="","",CEILING(M101,50)),"") -> 1700 | O101: 0 | P101: =IFERROR(IF(G101="","",G101*N101*(1-O101)),"") -> 1700
A102: V2 PB | B102: PISO CON ZOCLO | C102: 55 | D102: 106 | E102: — | F102: NOGAL | G102: 1 | H102: =IFERROR(IF(B102="","",(C102/100)*(D102/100)),"") -> 0.583 | I102: =IFERROR(IF(B102="","",_xlfn.LET(_xlpm.tamano,IF(H102<=0.5,"CHICO",IF(H102<=1,"MEDIANO","GRANDE")),_xlpm.clave,B102&"|"&_xlpm.tamano,_xlpm.fila,MATCH(_xlpm.clave,COSTOS_M2!$H$5:$H$67,0),_xlpm.mat_m2,INDEX(IF(F102="HUANACAXTLE",COSTOS_M2!$D$5:$D$67,IF(F102="ENCINO",COSTOS_M2!$E$5:$E$67,COSTOS_M2!$F$5:$F$67)),_xlpm.fila),_xlpm.cons_m2,INDEX(COSTOS_M2!$G$5:$G$67,_xlpm.fila),_xlpm.prof_factor,IF(AND(E102<>"—",E102<>"",ISNUMBER(E102)),POWER(E102/40,1.8),1),_xlpm.total_m2,(_xlpm.mat_m2+_xlpm.cons_m2)*H102*_xlpm.prof_factor*IF(C102>70,COSTOS_M2!$B$70,1)*IF(D102>244,COSTOS_M2!$B$71,1),_xlpm.total_m2)),"") -> 409.266 | J102: =IFERROR(IF(B102="","",INDEX(MANO_DE_OBRA!$P$10:$P$72,MATCH(B102&"|"&IF(H102<=0.5,"CHICO",IF(H102<=1,"MEDIANO","GRANDE")),MANO_DE_OBRA!$Q$10:$Q$72,0))),"") -> 469.28724 | K102: =IFERROR(IF(B102="","",_xlfn.LET(_xlpm.clave_prof,B102&"|"&E102,_xlpm.clave_todas,B102&"|TODAS",_xlpm.herr_prof,SUMIFS(HERRAJES!$H$5:$H$36,HERRAJES!$J$5:$J$36,_xlpm.clave_prof),_xlpm.herr_todas,SUMIFS(HERRAJES!$H$5:$H$36,HERRAJES!$J$5:$J$36,_xlpm.clave_todas),IF(_xlpm.herr_prof>0,_xlpm.herr_prof,_xlpm.herr_todas))),"") -> 0 | L102: =IFERROR(IF(B102="","",IF(I102="",0,I102)+IF(J102="",0,J102)+IF(K102="",0,K102)),"") -> 878.55324 | M102: =IFERROR(IF(L102="","",L102*$D$8),"") -> 1098.1916 | N102: =IFERROR(IF(M102="","",CEILING(M102,50)),"") -> 1100 | O102: 0 | P102: =IFERROR(IF(G102="","",G102*N102*(1-O102)),"") -> 1100
A103: V2 PB | B103: CIELO | C103: 55 | D103: 200 | E103: — | F103: NOGAL | G103: 1 | H103: =IFERROR(IF(B103="","",(C103/100)*(D103/100)),"") -> 1.1 | I103: =IFERROR(IF(B103="","",_xlfn.LET(_xlpm.tamano,IF(H103<=0.5,"CHICO",IF(H103<=1,"MEDIANO","GRANDE")),_xlpm.clave,B103&"|"&_xlpm.tamano,_xlpm.fila,MATCH(_xlpm.clave,COSTOS_M2!$H$5:$H$67,0),_xlpm.mat_m2,INDEX(IF(F103="HUANACAXTLE",COSTOS_M2!$D$5:$D$67,IF(F103="ENCINO",COSTOS_M2!$E$5:$E$67,COSTOS_M2!$F$5:$F$67)),_xlpm.fila),_xlpm.cons_m2,INDEX(COSTOS_M2!$G$5:$G$67,_xlpm.fila),_xlpm.prof_factor,IF(AND(E103<>"—",E103<>"",ISNUMBER(E103)),POWER(E103/40,1.8),1),_xlpm.total_m2,(_xlpm.mat_m2+_xlpm.cons_m2)*H103*_xlpm.prof_factor*IF(C103>70,COSTOS_M2!$B$70,1)*IF(D103>244,COSTOS_M2!$B$71,1),_xlpm.total_m2)),"") -> 888.8 | J103: =IFERROR(IF(B103="","",INDEX(MANO_DE_OBRA!$P$10:$P$72,MATCH(B103&"|"&IF(H103<=0.5,"CHICO",IF(H103<=1,"MEDIANO","GRANDE")),MANO_DE_OBRA!$Q$10:$Q$72,0))),"") -> 762.95904 | K103: =IFERROR(IF(B103="","",_xlfn.LET(_xlpm.clave_prof,B103&"|"&E103,_xlpm.clave_todas,B103&"|TODAS",_xlpm.herr_prof,SUMIFS(HERRAJES!$H$5:$H$36,HERRAJES!$J$5:$J$36,_xlpm.clave_prof),_xlpm.herr_todas,SUMIFS(HERRAJES!$H$5:$H$36,HERRAJES!$J$5:$J$36,_xlpm.clave_todas),IF(_xlpm.herr_prof>0,_xlpm.herr_prof,_xlpm.herr_todas))),"") -> 0 | L103: =IFERROR(IF(B103="","",IF(I103="",0,I103)+IF(J103="",0,J103)+IF(K103="",0,K103)),"") -> 1651.759 | M103: =IFERROR(IF(L103="","",L103*$D$8),"") -> 2064.6988 | N103: =IFERROR(IF(M103="","",CEILING(M103,50)),"") -> 2100 | O103: 0 | P103: =IFERROR(IF(G103="","",G103*N103*(1-O103)),"") -> 2100
A104: V2 PB | B104: CIELO | C104: 55 | D104: 106 | E104: — | F104: NOGAL | G104: 1 | H104: =IFERROR(IF(B104="","",(C104/100)*(D104/100)),"") -> 0.583 | I104: =IFERROR(IF(B104="","",_xlfn.LET(_xlpm.tamano,IF(H104<=0.5,"CHICO",IF(H104<=1,"MEDIANO","GRANDE")),_xlpm.clave,B104&"|"&_xlpm.tamano,_xlpm.fila,MATCH(_xlpm.clave,COSTOS_M2!$H$5:$H$67,0),_xlpm.mat_m2,INDEX(IF(F104="HUANACAXTLE",COSTOS_M2!$D$5:$D$67,IF(F104="ENCINO",COSTOS_M2!$E$5:$E$67,COSTOS_M2!$F$5:$F$67)),_xlpm.fila),_xlpm.cons_m2,INDEX(COSTOS_M2!$G$5:$G$67,_xlpm.fila),_xlpm.prof_factor,IF(AND(E104<>"—",E104<>"",ISNUMBER(E104)),POWER(E104/40,1.8),1),_xlpm.total_m2,(_xlpm.mat_m2+_xlpm.cons_m2)*H104*_xlpm.prof_factor*IF(C104>70,COSTOS_M2!$B$70,1)*IF(D104>244,COSTOS_M2!$B$71,1),_xlpm.total_m2)),"") -> 487.388 | J104: =IFERROR(IF(B104="","",INDEX(MANO_DE_OBRA!$P$10:$P$72,MATCH(B104&"|"&IF(H104<=0.5,"CHICO",IF(H104<=1,"MEDIANO","GRANDE")),MANO_DE_OBRA!$Q$10:$Q$72,0))),"") -> 520.0504 | K104: =IFERROR(IF(B104="","",_xlfn.LET(_xlpm.clave_prof,B104&"|"&E104,_xlpm.clave_todas,B104&"|TODAS",_xlpm.herr_prof,SUMIFS(HERRAJES!$H$5:$H$36,HERRAJES!$J$5:$J$36,_xlpm.clave_prof),_xlpm.herr_todas,SUMIFS(HERRAJES!$H$5:$H$36,HERRAJES!$J$5:$J$36,_xlpm.clave_todas),IF(_xlpm.herr_prof>0,_xlpm.herr_prof,_xlpm.herr_todas))),"") -> 0 | L104: =IFERROR(IF(B104="","",IF(I104="",0,I104)+IF(J104="",0,J104)+IF(K104="",0,K104)),"") -> 1007.4384 | M104: =IFERROR(IF(L104="","",L104*$D$8),"") -> 1259.298 | N104: =IFERROR(IF(M104="","",CEILING(M104,50)),"") -> 1300 | O104: 0 | P104: =IFERROR(IF(G104="","",G104*N104*(1-O104)),"") -> 1300
A105: V2 PB | B105: PARAL 2 VISTAS | C105: 55 | D105: 240 | E105: — | F105: NOGAL | G105: 4 | H105: =IFERROR(IF(B105="","",(C105/100)*(D105/100)),"") -> 1.32 | I105: =IFERROR(IF(B105="","",_xlfn.LET(_xlpm.tamano,IF(H105<=0.5,"CHICO",IF(H105<=1,"MEDIANO","GRANDE")),_xlpm.clave,B105&"|"&_xlpm.tamano,_xlpm.fila,MATCH(_xlpm.clave,COSTOS_M2!$H$5:$H$67,0),_xlpm.mat_m2,INDEX(IF(F105="HUANACAXTLE",COSTOS_M2!$D$5:$D$67,IF(F105="ENCINO",COSTOS_M2!$E$5:$E$67,COSTOS_M2!$F$5:$F$67)),_xlpm.fila),_xlpm.cons_m2,INDEX(COSTOS_M2!$G$5:$G$67,_xlpm.fila),_xlpm.prof_factor,IF(AND(E105<>"—",E105<>"",ISNUMBER(E105)),POWER(E105/40,1.8),1),_xlpm.total_m2,(_xlpm.mat_m2+_xlpm.cons_m2)*H105*_xlpm.prof_factor*IF(C105>70,COSTOS_M2!$B$70,1)*IF(D105>244,COSTOS_M2!$B$71,1),_xlpm.total_m2)),"") -> 1495.56 | J105: =IFERROR(IF(B105="","",INDEX(MANO_DE_OBRA!$P$10:$P$72,MATCH(B105&"|"&IF(H105<=0.5,"CHICO",IF(H105<=1,"MEDIANO","GRANDE")),MANO_DE_OBRA!$Q$10:$Q$72,0))),"") -> 751.15698 | K105: =IFERROR(IF(B105="","",_xlfn.LET(_xlpm.clave_prof,B105&"|"&E105,_xlpm.clave_todas,B105&"|TODAS",_xlpm.herr_prof,SUMIFS(HERRAJES!$H$5:$H$36,HERRAJES!$J$5:$J$36,_xlpm.clave_prof),_xlpm.herr_todas,SUMIFS(HERRAJES!$H$5:$H$36,HERRAJES!$J$5:$J$36,_xlpm.clave_todas),IF(_xlpm.herr_prof>0,_xlpm.herr_prof,_xlpm.herr_todas))),"") -> 0 | L105: =IFERROR(IF(B105="","",IF(I105="",0,I105)+IF(J105="",0,J105)+IF(K105="",0,K105)),"") -> 2246.717 | M105: =IFERROR(IF(L105="","",L105*$D$8),"") -> 2808.3962 | N105: =IFERROR(IF(M105="","",CEILING(M105,50)),"") -> 2850 | O105: 0 | P105: =IFERROR(IF(G105="","",G105*N105*(1-O105)),"") -> 11400
...

Sheet PRESUPUESTO_CLIENTE
A1: C A J I G A
A2: Diseño y Fabricación de Closets a la Medida
A5: CLIENTE: | B5: =COTIZADOR!B4 -> Monte Tauro 290 | E5: PROYECTO: | F5: =COTIZADOR!B3 -> Closets Monte Tauro 290 — Vestidor Niñas
A6: FECHA: | B6: =COTIZADOR!I3 -> 46081 | E6: COTIZACIÓN #: | F6: =COTIZADOR!I4 -> COT-2025-001
A9: # | B9: ZONA / ÁREA | C9: DESCRIPCIÓN | D9: CANTIDAD | E9: UNIDAD | F9: PRECIO UNIT | G9: DESCUENTO | H9: TOTAL
A10: 1 | B10: =IF(COTIZADOR!B14="","",COTIZADOR!B14) -> VESTIDOR NIÑAS | C10: =IF(COTIZADOR!B14="","",COTIZADOR!B14&" "&COTIZADOR!C14&"x"&COTIZADOR!D14&" "&COTIZADOR!F14) -> VESTIDOR NIÑAS x | D10: =IF(COTIZADOR!G14="","",COTIZADOR!G14) | E10: =IF(COTIZADOR!B14="","","PZA") -> PZA | F10: =IF(COTIZADOR!N14="","",COTIZADOR!N14) | G10: =IF(COTIZADOR!O14=0,"-",COTIZADOR!O14) -> - | H10: =IF(COTIZADOR!P14="","",COTIZADOR!P14)
A11: 2 | B11: =IF(COTIZADOR!B15="","",COTIZADOR!B15) -> PISO CON ZOCLO | C11: =IF(COTIZADOR!B15="","",COTIZADOR!B15&" "&COTIZADOR!C15&"x"&COTIZADOR!D15&" "&COTIZADOR!F15) -> PISO CON ZOCLO 55x100 NOGAL | D11: =IF(COTIZADOR!G15="","",COTIZADOR!G15) -> 1 | E11: =IF(COTIZADOR!B15="","","PZA") -> PZA | F11: =IF(COTIZADOR!N15="","",COTIZADOR!N15) -> 1100 | G11: =IF(COTIZADOR!O15=0,"-",COTIZADOR!O15) -> - | H11: =IF(COTIZADOR!P15="","",COTIZADOR!P15) -> 1100
A12: 3 | B12: =IF(COTIZADOR!B16="","",COTIZADOR!B16) -> PISO CON ZOCLO | C12: =IF(COTIZADOR!B16="","",COTIZADOR!B16&" "&COTIZADOR!C16&"x"&COTIZADOR!D16&" "&COTIZADOR!F16) -> PISO CON ZOCLO 55x175 NOGAL | D12: =IF(COTIZADOR!G16="","",COTIZADOR!G16) -> 1 | E12: =IF(COTIZADOR!B16="","","PZA") -> PZA | F12: =IF(COTIZADOR!N16="","",COTIZADOR!N16) -> 1450 | G12: =IF(COTIZADOR!O16=0,"-",COTIZADOR!O16) -> - | H12: =IF(COTIZADOR!P16="","",COTIZADOR!P16) -> 1450
A13: 4 | B13: =IF(COTIZADOR!B17="","",COTIZADOR!B17) -> CIELO | C13: =IF(COTIZADOR!B17="","",COTIZADOR!B17&" "&COTIZADOR!C17&"x"&COTIZADOR!D17&" "&COTIZADOR!F17) -> CIELO 55x100 NOGAL | D13: =IF(COTIZADOR!G17="","",COTIZADOR!G17) -> 1 | E13: =IF(COTIZADOR!B17="","","PZA") -> PZA | F13: =IF(COTIZADOR!N17="","",COTIZADOR!N17) -> 1250 | G13: =IF(COTIZADOR!O17=0,"-",COTIZADOR!O17) -> - | H13: =IF(COTIZADOR!P17="","",COTIZADOR!P17) -> 1250
A14: 5 | B14: =IF(COTIZADOR!B18="","",COTIZADOR!B18) -> CIELO | C14: =IF(COTIZADOR!B18="","",COTIZADOR!B18&" "&COTIZADOR!C18&"x"&COTIZADOR!D18&" "&COTIZADOR!F18) -> CIELO 55x175 NOGAL | D14: =IF(COTIZADOR!G18="","",COTIZADOR!G18) -> 1 | E14: =IF(COTIZADOR!B18="","","PZA") -> PZA | F14: =IF(COTIZADOR!N18="","",COTIZADOR!N18) -> 1700 | G14: =IF(COTIZADOR!O18=0,"-",COTIZADOR!O18) -> - | H14: =IF(COTIZADOR!P18="","",COTIZADOR!P18) -> 1700
A15: 6 | B15: =IF(COTIZADOR!B19="","",COTIZADOR!B19) -> PARAL 1 VISTA | C15: =IF(COTIZADOR!B19="","",COTIZADOR!B19&" "&COTIZADOR!C19&"x"&COTIZADOR!D19&" "&COTIZADOR!F19) -> PARAL 1 VISTA 55x295 NOGAL | D15: =IF(COTIZADOR!G19="","",COTIZADOR!G19) -> 2 | E15: =IF(COTIZADOR!B19="","","PZA") -> PZA | F15: =IF(COTIZADOR!N19="","",COTIZADOR!N19) -> 2600 | G15: =IF(COTIZADOR!O19=0,"-",COTIZADOR!O19) -> - | H15: =IF(COTIZADOR!P19="","",COTIZADOR!P19) -> 5200
A16: 7 | B16: =IF(COTIZADOR!B20="","",COTIZADOR!B20) -> PARAL DELGADO 2V | C16: =IF(COTIZADOR!B20="","",COTIZADOR!B20&" "&COTIZADOR!C20&"x"&COTIZADOR!D20&" "&COTIZADOR!F20) -> PARAL DELGADO 2V 55x295 NOGAL | D16: =IF(COTIZADOR!G20="","",COTIZADOR!G20) -> 2 | E16: =IF(COTIZADOR!B20="","","PZA") -> PZA | F16: =IF(COTIZADOR!N20="","",COTIZADOR!N20) -> 2900 | G16: =IF(COTIZADOR!O20=0,"-",COTIZADOR!O20) -> - | H16: =IF(COTIZADOR!P20="","",COTIZADOR!P20) -> 5800
A17: 8 | B17: =IF(COTIZADOR!B21="","",COTIZADOR!B21) -> ZAPATERA EXTRAÍBLE | C17: =IF(COTIZADOR!B21="","",COTIZADOR!B21&" "&COTIZADOR!C21&"x"&COTIZADOR!D21&" "&COTIZADOR!F21) -> ZAPATERA EXTRAÍBLE 100x55 NOGAL | D17: =IF(COTIZADOR!G21="","",COTIZADOR!G21) -> 4 | E17: =IF(COTIZADOR!B21="","","PZA") -> PZA | F17: =IF(COTIZADOR!N21="","",COTIZADOR!N21) -> 1500 | G17: =IF(COTIZADOR!O21=0,"-",COTIZADOR!O21) -> - | H17: =IF(COTIZADOR!P21="","",COTIZADOR!P21) -> 6000
A18: 9 | B18: =IF(COTIZADOR!B22="","",COTIZADOR!B22) -> ENTREPAÑO DELGADO | C18: =IF(COTIZADOR!B22="","",COTIZADOR!B22&" "&COTIZADOR!C22&"x"&COTIZADOR!D22&" "&COTIZADOR!F22) -> ENTREPAÑO DELGADO 55x100 NOGAL | D18: =IF(COTIZADOR!G22="","",COTIZADOR!G22) -> 2 | E18: =IF(COTIZADOR!B22="","","PZA") -> PZA | F18: =IF(COTIZADOR!N22="","",COTIZADOR!N22) -> 1050 | G18: =IF(COTIZADOR!O22=0,"-",COTIZADOR!O22) -> - | H18: =IF(COTIZADOR!P22="","",COTIZADOR!P22) -> 2100
A19: 10 | B19: =IF(COTIZADOR!B23="","",COTIZADOR!B23) -> ENTREPAÑO DELGADO | C19: =IF(COTIZADOR!B23="","",COTIZADOR!B23&" "&COTIZADOR!C23&"x"&COTIZADOR!D23&" "&COTIZADOR!F23) -> ENTREPAÑO DELGADO 55x71 NOGAL | D19: =IF(COTIZADOR!G23="","",COTIZADOR!G23) -> 6 | E19: =IF(COTIZADOR!B23="","","PZA") -> PZA | F19: =IF(COTIZADOR!N23="","",COTIZADOR!N23) -> 750 | G19: =IF(COTIZADOR!O23=0,"-",COTIZADOR!O23) -> - | H19: =IF(COTIZADOR!P23="","",COTIZADOR!P23) -> 4500
A20: 11 | B20: =IF(COTIZADOR!B24="","",COTIZADOR!B24) -> CAJÓN | C20: =IF(COTIZADOR!B24="","",COTIZADOR!B24&" "&COTIZADOR!C24&"x"&COTIZADOR!D24&" "&COTIZADOR!F24) -> CAJÓN 71x22 NOGAL | D20: =IF(COTIZADOR!G24="","",COTIZADOR!G24) -> 4 | E20: =IF(COTIZADOR!B24="","","PZA") -> PZA | F20: =IF(COTIZADOR!N24="","",COTIZADOR!N24) -> 1250 | G20: =IF(COTIZADOR!O24=0,"-",COTIZADOR!O24) -> - | H20: =IF(COTIZADOR!P24="","",COTIZADOR!P24) -> 5000
A21: 12 | B21: =IF(COTIZADOR!B25="","",COTIZADOR!B25) -> TUBO COLGAR | C21: =IF(COTIZADOR!B25="","",COTIZADOR!B25&" "&COTIZADOR!C25&"x"&COTIZADOR!D25&" "&COTIZADOR!F25) -> TUBO COLGAR ESPECIALx100 NOGAL | D21: =IF(COTIZADOR!G25="","",COTIZADOR!G25) -> 4 | E21: =IF(COTIZADOR!B25="","","PZA") -> PZA | F21: =IF(COTIZADOR!N25="","",COTIZADOR!N25) -> 50 | G21: =IF(COTIZADOR!O25=0,"-",COTIZADOR!O25) -> - | H21: =IF(COTIZADOR!P25="","",COTIZADOR!P25) -> 200
... A43: 34 | B43: =IF(COTIZADOR!B47="","",COTIZADOR!B47) -> PISO CON ZOCLO | C43: =IF(COTIZADOR!B47="","",COTIZADOR!B47&" "&COTIZADOR!C47&"x"&COTIZADOR!D47&" "&COTIZADOR!F47) -> PISO CON ZOCLO 25x250 NOGAL | D43: =IF(COTIZADOR!G47="","",COTIZADOR!G47) -> 1 | E43: =IF(COTIZADOR!B47="","","PZA") -> PZA | F43: =IF(COTIZADOR!N47="","",COTIZADOR!N47) -> 1300 | G43: =IF(COTIZADOR!O47=0,"-",COTIZADOR!O47) -> - | H43: =IF(COTIZADOR!P47="","",COTIZADOR!P47) -> 1300
A44: 35 | B44: =IF(COTIZADOR!B75="","",COTIZADOR!B75) | C44: =IF(COTIZADOR!B75="","",COTIZADOR!B75&" "&COTIZADOR!C75&"x"&COTIZADOR!D75&" "&COTIZADOR!F75) | D44: =IF(COTIZADOR!G75="","",COTIZADOR!G75) | E44: =IF(COTIZADOR!B75="","","PZA") | F44: =IF(COTIZADOR!N75="","",COTIZADOR!N75) | G44: =IF(COTIZADOR!O75=0,"-",COTIZADOR!O75) -> - | H44: =IF(COTIZADOR!P75="","",COTIZADOR!P75)
A46: LOGÍSTICA E INSTALACIÓN EN SITIO
A47: # | B47: CONCEPTO | H47: MONTO
A48: =IF(COTIZADOR!P199=0,"",1) | B48: =IF(COTIZADOR!P199=0,"","Traslado zona metropolitana CDMX") | H48: =IF(COTIZADOR!P199=0,"",COTIZADOR!P199)
A49: =IF(COTIZADOR!P200=0,"",2) | B49: =IF(COTIZADOR!P200=0,"","Traslado foráneo interior de la República") | H49: =IF(COTIZADOR!P200=0,"",COTIZADOR!P200)
A50: =IF(COTIZADOR!P201=0,"",3) | B50: =IF(COTIZADOR!P201=0,"","Viáticos") | H50: =IF(COTIZADOR!P201=0,"",COTIZADOR!P201)
A51: =IF(COTIZADOR!P202=0,"",4) | B51: =IF(COTIZADOR!P202=0,"","Hospedaje") | H51: =IF(COTIZADOR!P202=0,"",COTIZADOR!P202)
A52: =IF(COTIZADOR!P203=0,"",5) | B52: =IF(COTIZADOR!P203=0,"","Imprevistos en sitio") | H52: =IF(COTIZADOR!P203=0,"",COTIZADOR!P203)
A54: SUBTOTAL (Componentes + Logística, sin IVA) | F54: =COTIZADOR!P206 -> 599500
A55: IVA (16%) | F55: =COTIZADOR!P207 -> 95920
A56: TOTAL | F56: =COTIZADOR!P208 -> 695420
A58: CONDICIONES
A59: • Anticipo del 50% para iniciar fabricación.
A60: • Saldo del 50% contra entrega e instalación.
A61: • Tiempo de fabricación: 3 a 5 semanas según complejidad.
A62: • Garantía de 1 año en herrajes y estructura.
A63: • Cotización válida por =COTIZADOR!I6 días a partir de la fecha de emisión.
A65: Firma y sello: | F65: Acepto y apruebo:

Sheet GUÍA DE USO
A1: GUÍA RÁPIDA — SISTEMA COTIZADOR CAJIGA v3
A3: 📐 ARQUITECTURA DEL SISTEMA
A4: HOJA | B4: FUNCIÓN | C4: QUÉ EDITAS (🔵) | D4: FRECUENCIA
A5: FUO | B5: Factores de utilidad y markup | C5: Factor FUO, IVA | D5: Al cambiar política de precios
A6: INSUMOS | B6: Catálogo maestro: 368 insumos con precios reales | C6: Precio MXN, Merma % | D6: Mensual / al cambiar precios
A7: MATERIALES | B7: Costo material+consumibles por m² por componente | C7: $/m² por madera y tamaño | D7: Al actualizar costos de madera
A8: MANO_DE_OBRA | B8: Horas por área × 12 componentes × 3 tamaños | C8: Horas por área | D8: Al actualizar tiempos
A9: HERRAJES | B9: Herrajes por componente (correderas, bisagras, etc.) | C9: Precio, cantidad | D9: Al cambiar herrajes
A10: COTIZADOR | B10: Hoja principal — arma cotizaciones aquí | C10: Componente, dims, material, cant | D10: Por cada cotización
A11: PRESUPUESTO_CLIENTE | B11: Se genera solo — imprimir/PDF para el cliente | C11: Nada (todo automático) | D11: Al entregar cotización
A13: 🛠️ CÓMO COTIZAR (PASO A PASO)
A14: PASO | B14: ACCIÓN
A15: 1 | B15: Abre COTIZADOR. Llena datos del proyecto (A3:B6) y elige nivel FUO en I5
A16: 2 | B16: En cada fila (14+), selecciona COMPONENTE del dropdown
A17: 3 | B17: Selecciona ANCHO, ingresa LARGO/ALTO, selecciona PROF. CAJÓN (si aplica) y MATERIAL
A18: 4 | B18: Ingresa CANTIDAD. El sistema calcula automáticamente: M² → Material → MO → Herraje → Precio
A19: 5 | B19: Aplica descuento (%) si es necesario en columna O
A20: 6 | B20: Ve a PRESUPUESTO_CLIENTE — ya está listo para imprimir/PDF
A22: 💡 TIPS Y REGLAS
A23: 🔵 AZUL = Tú editas. ⬛ NEGRO = Cálculo automático. 🟢 VERDE = Jala de otra hoja.
A24: ⚡ Proyecto nuevo: Guardar como → renombrar con nombre del cliente.
A25: 📏 Ancho > 70cm o Alto > 244cm aplican factor especial ×1.30 automáticamente.
A26: 🗄️ Cajones: la corredera se selecciona por PROFUNDIDAD (35-60cm). Profundidad = clave de herraje.
A27: 🚪 Puertas abatibles: incluyen 4 bisagras + 4 contras automáticamente.
A28: 📐 Tamaño CHICO (≤0.5m²), MEDIANO (≤1m²), GRANDE (>1m²) — determina MO y costo material.
A29: ➕ Para agregar un nuevo COMPONENTE: agrega fila en MATERIALES, MANO_DE_OBRA, HERRAJES y _LISTAS.
A30: ➕ Para agregar un nuevo MATERIAL (ej: Tzalam): agrega columna en MATERIALES y opción en _LISTAS.
A31: 🔒 Para proteger fórmulas: Revisar > Proteger hoja (desbloquea solo celdas azules).

Sheet COMPONENTES
A1: CAJIGA — CATÁLOGO DE COMPONENTES
A2: Cada componente es una unidad cotizable (ej: PARAL, PUERTA, CAJÓN). Ingresa dimensión, material y clave de insumos. El costo base se calcula automáticamente desde INSUMOS.
A4: IDENTIFICACIÓN | D4: DIMENSIÓN / VARIANTE | H4: INSUMOS PRINCIPALES (CLAVE) | K4: COSTOS CALCULADOS
A6: CLAVE COMP. | B6: NOMBRE COMPONENTE | C6: ZONA/TIPO | D6: ALTO (cm) | E6: ANCHO (cm) | F6: PROF (cm) | G6: MATERIAL | H6: INSUMO 1 | I6: INSUMO 2 | J6: INSUMO 3 | K6: COSTO MAT. | L6: COSTO MO | M6: COSTO TOTAL | N6: UNIDAD
A7: PAR-001 | B7: PARAL DOBLE VISTA | C7: CUERPO | D7: 195 | E7: 40 | G7: ENCINO | H7: MAC001 | I7: INS003 | J7: BAR001 | K7: 850 | L7: 450 | M7: =K7+L7 -> 1300 | N7: PZA
A8: PAR-002 | B8: PARAL DOBLE VISTA | C8: CUERPO | D8: 210 | E8: 40 | G8: ENCINO | H8: MAC001 | I8: INS003 | J8: BAR001 | K8: 920 | L8: 450 | M8: =K8+L8 -> 1370 | N8: PZA
A9: PAR-003 | B9: PARAL DOBLE VISTA | C9: CUERPO | D9: 244 | E9: 40 | G9: ENCINO | H9: MAC001 | I9: INS003 | J9: BAR001 | K9: 1050 | L9: 500 | M9: =K9+L9 -> 1550 | N9: PZA
A10: PAR-004 | B10: PARAL DOBLE VISTA | C10: CUERPO | D10: 195 | E10: 60 | G10: ENCINO | H10: MAC001 | I10: INS003 | J10: BAR001 | K10: 1100 | L10: 500 | M10: =K10+L10 -> 1600 | N10: PZA
A11: PAR-010 | B11: PARAL SIMPLE | C11: CUERPO | D11: 195 | E11: 40 | G11: MDF LACADO | H11: MDF001 | I11: INS003 | J11: BAR002 | K11: 520 | L11: 380 | M11: =K11+L11 -> 900 | N11: PZA
A12: PAR-011 | B12: PARAL SIMPLE | C12: CUERPO | D12: 210 | E12: 40 | G12: MDF LACADO | H12: MDF001 | I12: INS003 | J12: BAR002 | K12: 580 | L12: 380 | M12: =K12+L12 -> 960 | N12: PZA
A13: ENT-001 | B13: ENTREPAÑO FIJO | C13: CUERPO | E13: 60 | F13: 40 | G13: MDF LACADO | H13: MDF001 | I13: INS003 | J13: INS001 | K13: 280 | L13: 120 | M13: =K13+L13 -> 400 | N13: PZA
A14: ENT-002 | B14: ENTREPAÑO FIJO | C14: CUERPO | E14: 90 | F14: 40 | G14: MDF LACADO | H14: MDF001 | I14: INS003 | J14: INS001 | K14: 320 | L14: 120 | M14: =K14+L14 -> 440 | N14: PZA
A15: ENT-003 | B15: ENTREPAÑO AJUSTABLE | C15: CUERPO | E15: 60 | F15: 40 | G15: MDF LACADO | H15: MDF001 | I15: INS003 | J15: HER001 | K15: 310 | L15: 130 | M15: =K15+L15 -> 440 | N15: PZA
A16: CAJ-001 | B16: CAJÓN SIMPLE | C16: CAJONES | D16: 15 | E16: 60 | F16: 40 | G16: MDF LACADO | H16: MDF001 | I16: HER001 | J16: INS001 | K16: 480 | L16: 250 | M16: =K16+L16 -> 730 | N16: PZA
A17: CAJ-002 | B17: CAJÓN SOFT CLOSE | C17: CAJONES | D17: 15 | E17: 60 | F17: 40 | G17: MDF LACADO | H17: MDF001 | I17: HER002 | J17: INS001 | K17: 620 | L17: 280 | M17: =K17+L17 -> 900 | N17: PZA
A18: CAJ-003 | B18: CAJÓN PROFUNDO | C18: CAJONES | D18: 20 | E18: 60 | F18: 50 | G18: MDF LACADO | H18: MDF001 | I18: HER002 | J18: INS001 | K18: 720 | L18: 300 | M18: =K18+L18 -> 1020 | N18: PZA
A19: PTA-001 | B19: PUERTA ABATIBLE MDF | C19: PUERTAS | D19: 195 | E19: 50 | G19: MDF LACADO | H19: MDF001 | I19: HER010 | J19: HER020 | K19: 680 | L19: 350 | M19: =K19+L19 -> 1030 | N19: PZA
A20: PTA-002 | B20: PUERTA ABATIBLE MACIZA | C20: PUERTAS | D20: 195 | E20: 50 | G20: ENCINO | H20: MAC001 | I20: HER010 | J20: HER020 | K20: 1200 | L20: 500 | M20: =K20+L20 -> 1700 | N20: PZA
A21: PTA-003 | B21: PUERTA CORREDERA MDF | C21: PUERTAS | D21: 195 | E21: 60 | G21: MDF LACADO | H21: MDF001 | I21: HER030 | J21: HER031 | K21: 850 | L21: 380 | M21: =K21+L21 -> 1230 | N21: PZA
A22: PTA-004 | B22: PUERTA CORREDERA ESPEJO | C22: PUERTAS | D22: 210 | E22: 60 | G22: MELAMINA+ESPEJO | H22: MEL001 | I22: HER030 | J22: HER031 | K22: 980 | L22: 400 | M22: =K22+L22 -> 1380 | N22: PZA
A23: ORG-001 | B23: ZAPATERA | C23: ORGANIZACIÓN | D23: 40 | E23: 60 | F23: 40 | G23: METÁLICA | H23: ACC001 | I23: INS001 | K23: 320 | L23: 80 | M23: =K23+L23 -> 400 | N23: PZA
A24: ORG-002 | B24: CANASTO METÁLICO | C24: ORGANIZACIÓN | D24: 20 | E24: 60 | F24: 40 | G24: METÁLICA | H24: ACC002 | I24: INS001 | K24: 285 | L24: 60 | M24: =K24+L24 -> 345 | N24: PZA
A25: ORG-003 | B25: SECCIÓN COLGAR LARGO | C25: ORGANIZACIÓN | D25: 195 | E25: 60 | F25: 55 | G25: MDF LACADO | H25: MDF001 | I25: HER001 | J25: INS003 | K25: 580 | L25: 200 | M25: =K25+L25 -> 780 | N25: PZA
A26: ORG-004 | B26: SECCIÓN COLGAR CORTO | C26: ORGANIZACIÓN | D26: 120 | E26: 60 | F26: 55 | G26: MDF LACADO | H26: MDF001 | I26: HER001 | J26: INS003 | K26: 420 | L26: 180 | M26: =K26+L26 -> 600 | N26: PZA
A27: ILU-001 | B27: ILUMINACIÓN LED 1m | C27: ILUMINACIÓN | E27: 100 | G27: LED | H27: ACC010 | K27: 220 | L27: 120 | M27: =K27+L27 -> 340 | N27: PZA
A28: INS-001 | B28: INSTALACIÓN CARPINTERÍA | C28: INSTALACIÓN | G28: — | H28: MO003 | K28: 700 | L28: 0 | M28: =K28+L28 -> 700 | N28: PZA
A29: INS-002 | B29: INSTALACIÓN + BARNIZ | C29: INSTALACIÓN | G29: — | H29: MO003 | I29: MO002 | K29: 1350 | L29: 0 | M29: =K29+L29 -> 1350 | N29: PZA
A31: ⚡ Agrega nuevos componentes aquí con su clave única. INSUMO 1/2/3 son las claves de la hoja INSUMOS para referencia. COSTO MAT y COSTO MO son inputs en azul (editables por el usuario).

Sheet _LISTAS
A1: COMPONENTES | B1: ANCHO | C1: PROFUNDIDAD | D1: MATERIAL | E1: ALTO_CAJON | F1: FUO
B2: 5
A3: PARAL 1 VISTA | B3: 40 | C3: 35 | D3: NOGAL | E3: 16 | F3: FUO 1.15
A4: PARAL 2 VISTAS | B4: 50 | C4: 40 | D4: ENCINO | E4: 22 | F4: FUO 1.25
A5: PISO | B5: 60 | C5: 45 | D5: HUANACAXTLE | E5: ESPECIAL | F5: FUO 1.32
A6: PISO CON ZOCLO | B6: 70 | C6: 50 | F6: FUO 1.40
A7: CIELO | B7: ESPECIAL | C7: 55 | F7: FUO 1.48
A8: ENTREPAÑO | C8: 60 | F8: FUO 1.55
A9: ENTREPAÑO LED | C9: ESPECIAL | F9: FUO 1.65
A10: CAJÓN | C10: — | F10: FUO 1.75
A11: PUERTA ABATIBLE | F11: FUO 1.88
A12: PUERTA CORREDERA | F12: FUO 2.00
A13: PUERTA ESPEJO
A14: TUBO COLGAR
A15: ZAPATERA EXTRAÍBLE
A16: PARAL DELGADO 2V
A17: ENTREPAÑO DELGADO
A18: ESPEJO
A19: MOLDURA SENCILLA
A20: MOLDURA MEDIA
A21: MOLDURA DIFÍCIL
A22: MOLDURA GRUESA DIFÍCIL
A23: FONDO MADERA
